Workbook
Name MonthlyHours: #REF!

Sheet RFR Base Line
M1: 2025 - Q1 - Quarter | P1: 2025 - Q2 - Quarter | S1: Q1 Burn | T1: Q2 Burn | U1: H1 Burn
M2: =SUBTOTAL(9,M4:M1048576) -> #REF! | N2: =SUBTOTAL(9,N4:N1048576) -> #REF! | O2: =SUBTOTAL(9,O4:O1048576) -> #REF! | P2: =SUBTOTAL(9,P4:P1048576) -> #REF! | Q2: =SUBTOTAL(9,Q4:Q1048576) -> #REF! | R2: =SUBTOTAL(9,R4:R1048576) -> #REF! | S2: =SUBTOTAL(9,S4:S1048576) -> #REF! | T2: =SUBTOTAL(9,T4:T1048576) -> #REF! | U2: =SUBTOTAL(9,U4:U1048576) -> #REF!
A3: EmpID | B3: Name | C3: Location | D3: ACT/PCT | E3: Skill Set | F3: Verizon TQ ID | G3: Verizon TQ Description | H3: ESA ID | I3: ESA Description | J3: Department | K3: Hourly Rate ($) | L3: Monthly Rate ($) | M3: 45658 | N3: 45689 | O3: 45717 | P3: 45748 | Q3: 45778 | R3: 45809 | S3: Q1 Burn | T3: Q2 Forecasted Burn | U3: H1 Burn Total | V3: Comments
A4: =#REF! -> #REF! | B4: =#REF! -> #REF! | C4: =#REF! -> #REF! | D4: =#REF! -> #REF! | E4: Java Springboot Microservices SpringReactive | F4: VZGTTQ00009462 | G4: VCG Flex (Strategically Ready Offers) TQ4164 CTS | H4: 1000431127 | I4: Verizon- VCG Flex - Strategica | J4: ADM | K4: =#REF! -> #REF! | L4: =#REF! -> #REF! | M4: =#REF! -> #REF! | N4: =#REF! -> #REF! | O4: =#REF! -> #REF! | P4: =#REF! -> #REF! | Q4: =#REF! -> #REF! | R4: =#REF! -> #REF! | ... U4: =#REF! -> #REF!
A5: =#REF! -> #REF! | B5: =#REF! -> #REF! | C5: =#REF! -> #REF! | D5: =#REF! -> #REF! | E5: QA Analyst | F5: VZGTTQ00009462 | G5: VCG Flex (Strategically Ready Offers) TQ4164 CTS | H5: 1000431127 | I5: Verizon- VCG Flex - Strategica | J5: QEA | K5: =#REF! -> #REF! | L5: =#REF! -> #REF! | M5: =#REF! -> #REF! | N5: =#REF! -> #REF! | O5: =#REF! -> #REF! | P5: =#REF! -> #REF! | Q5: =#REF! -> #REF! | R5: =#REF! -> #REF! | ... U5: =#REF! -> #REF!
A6: =#REF! -> #REF! | B6: =#REF! -> #REF! | C6: =#REF! -> #REF! | D6: =#REF! -> #REF! | E6: QA Analyst | F6: VZGTTQ00009462 | G6: VCG Flex (Strategically Ready Offers) TQ4164 CTS | H6: 1000431127 | I6: Verizon- VCG Flex - Strategica | J6: QEA | K6: =#REF! -> #REF! | L6: =#REF! -> #REF! | M6: =#REF! -> #REF! | N6: =#REF! -> #REF! | O6: =#REF! -> #REF! | P6: =#REF! -> #REF! | Q6: =#REF! -> #REF! | R6: =#REF! -> #REF! | ... U6: =#REF! -> #REF!
A7: =#REF! -> #REF! | B7: =#REF! -> #REF! | C7: =#REF! -> #REF! | D7: =#REF! -> #REF! | E7: QA Analyst | F7: VZGTTQ00009462 | G7: VCG Flex (Strategically Ready Offers) TQ4164 CTS | H7: 1000431127 | I7: Verizon- VCG Flex - Strategica | J7: ADM | K7: =#REF! -> #REF! | L7: =#REF! -> #REF! | M7: =#REF! -> #REF! | N7: =#REF! -> #REF! | O7: =#REF! -> #REF! | P7: =#REF! -> #REF! | Q7: =#REF! -> #REF! | R7: =#REF! -> #REF! | ... U7: =#REF! -> #REF!
A8: =#REF! -> #REF! | B8: =#REF! -> #REF! | C8: =#REF! -> #REF! | D8: =#REF! -> #REF! | E8: =#REF! -> #REF! | F8: VZGTTQ00009462 | G8: VCG Flex (Strategically Ready Offers) TQ4164 CTS | H8: 1000431127 | I8: Verizon- VCG Flex - Strategica | J8: ADM | K8: =#REF! -> #REF! | L8: =#REF! -> #REF! | M8: =#REF! -> #REF! | N8: =#REF! -> #REF! | O8: =#REF! -> #REF! | P8: =#REF! -> #REF! | Q8: =#REF! -> #REF! | R8: =#REF! -> #REF! | ... U8: =#REF! -> #REF!
A9: =#REF! -> #REF! | B9: =#REF! -> #REF! | C9: =#REF! -> #REF! | D9: =#REF! -> #REF! | E9: =#REF! -> #REF! | F9: VZGTTQ00009462 | G9: VCG Flex (Strategically Ready Offers) TQ4164 CTS | H9: 1000431127 | I9: Verizon- VCG Flex - Strategica | J9: QEA | K9: =#REF! -> #REF! | L9: =#REF! -> #REF! | M9: =#REF! -> #REF! | N9: =#REF! -> #REF! | O9: =#REF! -> #REF! | P9: =#REF! -> #REF! | Q9: =#REF! -> #REF! | R9: =#REF! -> #REF! | ... U9: =#REF! -> #REF!
A10: =#REF! -> #REF! | B10: =#REF! -> #REF! | C10: =#REF! -> #REF! | D10: =#REF! -> #REF! | E10: =#REF! -> #REF! | F10: VZGTTQ00009462 | G10: VCG Flex (Strategically Ready Offers) TQ4164 CTS | H10: 1000431127 | I10: Verizon- VCG Flex - Strategica | J10: QEA | K10: =#REF! -> #REF! | L10: =#REF! -> #REF! | M10: =#REF! -> #REF! | N10: =#REF! -> #REF! | O10: =#REF! -> #REF! | P10: =#REF! -> #REF! | Q10: =#REF! -> #REF! | R10: =#REF! -> #REF! | ... U10: =#REF! -> #REF!
A11: =#REF! -> #REF! | B11: =#REF! -> #REF! | C11: =#REF! -> #REF! | D11: =#REF! -> #REF! | E11: =#REF! -> #REF! | F11: VZGTTQ00009462 | G11: VCG Flex (Strategically Ready Offers) TQ4164 CTS | H11: 1000431127 | I11: Verizon- VCG Flex - Strategica | J11: ADM | K11: =#REF! -> #REF! | L11: =#REF! -> #REF! | M11: =#REF! -> #REF! | N11: =#REF! -> #REF! | O11: =#REF! -> #REF! | P11: =#REF! -> #REF! | Q11: =#REF! -> #REF! | R11: =#REF! -> #REF! | ... U11: =#REF! -> #REF!
A12: =#REF! -> #REF! | B12: =#REF! -> #REF! | C12: =#REF! -> #REF! | D12: =#REF! -> #REF! | E12: =#REF! -> #REF! | F12: VZGTTQ00009462 | G12: VCG Flex (Strategically Ready Offers) TQ4164 CTS | H12: 1000431127 | I12: Verizon- VCG Flex - Strategica | J12: ADM | K12: =#REF! -> #REF! | L12: =#REF! -> #REF! | M12: =#REF! -> #REF! | N12: =#REF! -> #REF! | O12: =#REF! -> #REF! | P12: =#REF! -> #REF! | Q12: =#REF! -> #REF! | R12: =#REF! -> #REF! | ... U12: =#REF! -> #REF!
A13: =#REF! -> #REF! | B13: =#REF! -> #REF! | C13: =#REF! -> #REF! | D13: =#REF! -> #REF! | E13: =#REF! -> #REF! | F13: VZGTTQ00009462 | G13: VCG Flex (Strategically Ready Offers) TQ4164 CTS | H13: 1000431127 | I13: Verizon- VCG Flex - Strategica | J13: Pega | K13: =#REF! -> #REF! | L13: =#REF! -> #REF! | M13: =#REF! -> #REF! | N13: =#REF! -> #REF! | O13: =#REF! -> #REF! | P13: =#REF! -> #REF! | Q13: =#REF! -> #REF! | R13: =#REF! -> #REF! | ... U13: =#REF! -> #REF!
A14: =#REF! -> #REF! | B14: =#REF! -> #REF! | C14: =#REF! -> #REF! | D14: =#REF! -> #REF! | E14: =#REF! -> #REF! | F14: VZGTTQ00009462 | G14: VCG Flex (Strategically Ready Offers) TQ4164 CTS | H14: 1000431127 | I14: Verizon- VCG Flex - Strategica | J14: Pega | K14: =#REF! -> #REF! | L14: =#REF! -> #REF! | M14: =#REF! -> #REF! | N14: =#REF! -> #REF! | O14: =#REF! -> #REF! | P14: =#REF! -> #REF! | Q14: =#REF! -> #REF! | R14: =#REF! -> #REF! | ... V14: =#REF! -> #REF!
A15: =#REF! -> #REF! | B15: =#REF! -> #REF! | C15: =#REF! -> #REF! | D15: =#REF! -> #REF! | E15: =#REF! -> #REF! | F15: VZGTTQ00009462 | G15: VCG Flex (Strategically Ready Offers) TQ4164 CTS | H15: 1000431127 | I15: Verizon- VCG Flex - Strategica | J15: ADM | K15: =#REF! -> #REF! | L15: =#REF! -> #REF! | M15: =#REF! -> #REF! | N15: =#REF! -> #REF! | O15: =#REF! -> #REF! | P15: =#REF! -> #REF! | Q15: =#REF! -> #REF! | R15: =#REF! -> #REF! | ... U15: =#REF! -> #REF!
A16: =#REF! -> #REF! | B16: =#REF! -> #REF! | C16: =#REF! -> #REF! | D16: =#REF! -> #REF! | E16: =#REF! -> #REF! | F16: VZGTTQ00009462 | G16: VCG Flex (Strategically Ready Offers) TQ4164 CTS | H16: 1000431127 | I16: Verizon- VCG Flex - Strategica | J16: Pega | K16: =#REF! -> #REF! | L16: =#REF! -> #REF! | M16: =#REF! -> #REF! | N16: =#REF! -> #REF! | O16: =#REF! -> #REF! | P16: =#REF! -> #REF! | Q16: =#REF! -> #REF! | R16: =#REF! -> #REF! | ... U16: =#REF! -> #REF!
A17: =#REF! -> #REF! | B17: =#REF! -> #REF! | C17: =#REF! -> #REF! | D17: =#REF! -> #REF! | E17: =#REF! -> #REF! | F17: VZGTTQ00009462 | G17: VCG Flex (Strategically Ready Offers) TQ4164 CTS | H17: 1000431127 | I17: Verizon- VCG Flex - Strategica | J17: ADM | K17: =#REF! -> #REF! | L17: =#REF! -> #REF! | M17: =#REF! -> #REF! | N17: =#REF! -> #REF! | O17: =#REF! -> #REF! | P17: =#REF! -> #REF! | Q17: =#REF! -> #REF! | R17: =#REF! -> #REF! | ... V17: =#REF! -> #REF!
A18: =#REF! -> #REF! | B18: =#REF! -> #REF! | C18: =#REF! -> #REF! | D18: =#REF! -> #REF! | E18: =#REF! -> #REF! | F18: VZGTTQ00009462 | G18: VCG Flex (Strategically Ready Offers) TQ4164 CTS | H18: 1000410331 | I18: VDSI VCG ACT Consol Journey | J18: ADM | K18: =#REF! -> #REF! | L18: =#REF! -> #REF! | M18: =#REF! -> #REF! | N18: =#REF! -> #REF! | O18: =#REF! -> #REF! | P18: =#REF! -> #REF! | Q18: =#REF! -> #REF! | R18: =#REF! -> #REF! | ... V18: =#REF! -> #REF!
A19: =#REF! -> #REF! | B19: =#REF! -> #REF! | C19: =#REF! -> #REF! | D19: =#REF! -> #REF! | E19: =#REF! -> #REF! | F19: VZGTTQ00009462 | G19: VCG Flex (Strategically Ready Offers) TQ4164 CTS | H19: 1000431127 | I19: Verizon- VCG Flex - Strategica | J19: ADM | K19: =#REF! -> #REF! | L19: =#REF! -> #REF! | M19: =#REF! -> #REF! | N19: =#REF! -> #REF! | O19: =#REF! -> #REF! | P19: =#REF! -> #REF! | Q19: =#REF! -> #REF! | R19: =#REF! -> #REF! | ... U19: =#REF! -> #REF!
A20: =#REF! -> #REF! | B20: =#REF! -> #REF! | C20: =#REF! -> #REF! | D20: =#REF! -> #REF! | E20: =#REF! -> #REF! | F20: VZGTTQ00008473 | G20: VCG Flex 2024 (CPI_EPC_PRE_DEEPSHIKHA) TQ4164 CTS | H20: 1000416318 | I20: Verizon-VCG Flex CPI EPC TQ846 | J20: ADM | K20: =#REF! -> #REF! | L20: =#REF! -> #REF! | M20: =#REF! -> #REF! | N20: =#REF! -> #REF! | O20: =#REF! -> #REF! | P20: =#REF! -> #REF! | Q20: =#REF! -> #REF! | R20: =#REF! -> #REF! | ... U20: =#REF! -> #REF!
A21: =#REF! -> #REF! | B21: =#REF! -> #REF! | C21: =#REF! -> #REF! | D21: =#REF! -> #REF! | E21: =#REF! -> #REF! | F21: VZGTTQ00008473 | G21: VCG Flex 2024 (CPI_EPC_PRE_DEEPSHIKHA) TQ4164 CTS | H21: 1000416318 | I21: Verizon-VCG Flex CPI EPC TQ846 | J21: ADM | K21: =#REF! -> #REF! | L21: =#REF! -> #REF! | M21: =#REF! -> #REF! | N21: =#REF! -> #REF! | O21: =#REF! -> #REF! | P21: =#REF! -> #REF! | Q21: =#REF! -> #REF! | R21: =#REF! -> #REF! | ... U21: =#REF! -> #REF!
A22: =#REF! -> #REF! | B22: =#REF! -> #REF! | C22: =#REF! -> #REF! | D22: =#REF! -> #REF! | E22: =#REF! -> #REF! | F22: VZGTTQ00008473 | G22: VCG Flex 2024 (CPI_EPC_PRE_DEEPSHIKHA) TQ4164 CTS | H22: 1000416318 | I22: Verizon-VCG Flex CPI EPC TQ846 | J22: ADM | K22: =#REF! -> #REF! | L22: =#REF! -> #REF! | M22: =#REF! -> #REF! | N22: =#REF! -> #REF! | O22: =#REF! -> #REF! | P22: =#REF! -> #REF! | Q22: =#REF! -> #REF! | R22: =#REF! -> #REF! | ... U22: =#REF! -> #REF!
A23: =#REF! -> #REF! | B23: =#REF! -> #REF! | C23: =#REF! -> #REF! | D23: =#REF! -> #REF! | E23: =#REF! -> #REF! | F23: VZGTTQ00008473 | G23: VCG Flex 2024 (CPI_EPC_PRE_DEEPSHIKHA) TQ4164 CTS | H23: 1000416318 | I23: Verizon-VCG Flex CPI EPC TQ846 | J23: ADM | K23: =#REF! -> #REF! | L23: =#REF! -> #REF! | M23: =#REF! -> #REF! | N23: =#REF! -> #REF! | O23: =#REF! -> #REF! | P23: =#REF! -> #REF! | Q23: =#REF! -> #REF! | R23: =#REF! -> #REF! | ... U23: =#REF! -> #REF!
A24: =#REF! -> #REF! | B24: =#REF! -> #REF! | C24: =#REF! -> #REF! | D24: =#REF! -> #REF! | E24: =#REF! -> #REF! | F24: VZGTTQ00008473 | G24: VCG Flex 2024 (CPI_EPC_PRE_DEEPSHIKHA) TQ4164 CTS | H24: 1000416318 | I24: Verizon-VCG Flex CPI EPC TQ846 | J24: ADM | K24: =#REF! -> #REF! | L24: =#REF! -> #REF! | M24: =#REF! -> #REF! | N24: =#REF! -> #REF! | O24: =#REF! -> #REF! | P24: =#REF! -> #REF! | Q24: =#REF! -> #REF! | R24: =#REF! -> #REF! | ... U24: =#REF! -> #REF!
A25: =#REF! -> #REF! | B25: =#REF! -> #REF! | C25: =#REF! -> #REF! | D25: =#REF! -> #REF! | E25: =#REF! -> #REF! | F25: VZGTTQ00008473 | G25: VCG Flex 2024 (CPI_EPC_PRE_DEEPSHIKHA) TQ4164 CTS | H25: 1000416318 | I25: Verizon-VCG Flex CPI EPC TQ846 | J25: ADM | K25: =#REF! -> #REF! | L25: =#REF! -> #REF! | M25: =#REF! -> #REF! | N25: =#REF! -> #REF! | O25: =#REF! -> #REF! | P25: =#REF! -> #REF! | Q25: =#REF! -> #REF! | R25: =#REF! -> #REF! | ... U25: =#REF! -> #REF!
A26: =#REF! -> #REF! | B26: =#REF! -> #REF! | C26: =#REF! -> #REF! | D26: =#REF! -> #REF! | E26: =#REF! -> #REF! | F26: VZGTTQ00008473 | G26: VCG Flex 2024 (CPI_EPC_PRE_DEEPSHIKHA) TQ4164 CTS | H26: 1000416318 | I26: Verizon-VCG Flex CPI EPC TQ846 | J26: ADM | K26: =#REF! -> #REF! | L26: =#REF! -> #REF! | M26: =#REF! -> #REF! | N26: =#REF! -> #REF! | O26: =#REF! -> #REF! | P26: =#REF! -> #REF! | Q26: =#REF! -> #REF! | R26: =#REF! -> #REF! | ... U26: =#REF! -> #REF!
A27: =#REF! -> #REF! | B27: =#REF! -> #REF! | C27: =#REF! -> #REF! | D27: =#REF! -> #REF! | E27: =#REF! -> #REF! | F27: VZGTTQ00008473 | G27: VCG Flex 2024 (CPI_EPC_PRE_DEEPSHIKHA) TQ4164 CTS | H27: 1000416318 | I27: Verizon-VCG Flex CPI EPC TQ846 | J27: ADM | K27: =#REF! -> #REF! | L27: =#REF! -> #REF! | M27: =#REF! -> #REF! | N27: =#REF! -> #REF! | O27: =#REF! -> #REF! | P27: =#REF! -> #REF! | Q27: =#REF! -> #REF! | R27: =#REF! -> #REF! | ... U27: =#REF! -> #REF!
A28: =#REF! -> #REF! | B28: =#REF! -> #REF! | C28: =#REF! -> #REF! | D28: =#REF! -> #REF! | E28: =#REF! -> #REF! | F28: VZGTTQ00008473 | G28: VCG Flex 2024 (CPI_EPC_PRE_DEEPSHIKHA) TQ4164 CTS | H28: 1000416318 | I28: Verizon-VCG Flex CPI EPC TQ846 | J28: ADM | K28: =#REF! -> #REF! | L28: =#REF! -> #REF! | M28: =#REF! -> #REF! | N28: =#REF! -> #REF! | O28: =#REF! -> #REF! | P28: =#REF! -> #REF! | Q28: =#REF! -> #REF! | R28: =#REF! -> #REF! | ... U28: =#REF! -> #REF!
A29: =#REF! -> #REF! | B29: =#REF! -> #REF! | C29: =#REF! -> #REF! | D29: =#REF! -> #REF! | E29: =#REF! -> #REF! | F29: VZGTTQ00008473 | G29: VCG Flex 2024 (CPI_EPC_PRE_DEEPSHIKHA) TQ4164 CTS | H29: 1000416318 | I29: Verizon-VCG Flex CPI EPC TQ846 | J29: ADM | K29: =#REF! -> #REF! | L29: =#REF! -> #REF! | M29: =#REF! -> #REF! | N29: =#REF! -> #REF! | O29: =#REF! -> #REF! | P29: =#REF! -> #REF! | Q29: =#REF! -> #REF! | R29: =#REF! -> #REF! | ... U29: =#REF! -> #REF!
A30: =#REF! -> #REF! | B30: =#REF! -> #REF! | C30: =#REF! -> #REF! | D30: =#REF! -> #REF! | E30: =#REF! -> #REF! | F30: VZGTTQ00008473 | G30: VCG Flex 2024 (CPI_EPC_PRE_DEEPSHIKHA) TQ4164 CTS | H30: 1000416318 | I30: Verizon-VCG Flex CPI EPC TQ846 | J30: ADM | K30: =#REF! -> #REF! | L30: =#REF! -> #REF! | M30: =#REF! -> #REF! | N30: =#REF! -> #REF! | O30: =#REF! -> #REF! | P30: =#REF! -> #REF! | Q30: =#REF! -> #REF! | R30: =#REF! -> #REF! | ... U30: =#REF! -> #REF!
... A35: =#REF! -> #REF! | B35: =#REF! -> #REF! | C35: =#REF! -> #REF! | D35: =#REF! -> #REF! | E35: =#REF! -> #REF! | F35: VZGTTQ00008473 | G35: VCG Flex 2024 (CPI_EPC_PRE_DEEPSHIKHA) TQ4164 CTS | H35: 1000448527 | I35: Verizon-Value Strategic Fulfil | J35: IDE | K35: =#REF! -> #REF! | L35: =#REF! -> #REF! | M35: =#REF! -> #REF! | N35: =#REF! -> #REF! | O35: =#REF! -> #REF! | P35: =#REF! -> #REF! | Q35: =#REF! -> #REF! | R35: =#REF! -> #REF! | ... U35: =#REF! -> #REF!
A36: ='TQ12042-DB'!#REF! -> #REF! | B36: ='TQ12042-DB'!#REF! -> #REF! | C36: ='TQ12042-DB'!#REF! -> #REF! | D36: ='TQ12042-DB'!#REF! -> #REF! | E36: ='TQ12042-DB'!#REF! -> #REF! | F36: VZGTTQ00008351 | G36: VCG Flex 2024 (FPP) CTS TQ4164 | H36: 1000415076 | I36: Verizon-VCG Flex FPP TQ8351-JA | J36: QEA | K36: ='TQ12042-DB'!#REF! -> #REF! | L36: ='TQ12042-DB'!#REF! -> #REF! | M36: ='TQ12042-DB'!#REF! -> #REF! | N36: ='TQ12042-DB'!#REF! -> #REF! | O36: ='TQ12042-DB'!#REF! -> #REF! | P36: ='TQ12042-DB'!#REF! -> #REF! | Q36: ='TQ12042-DB'!#REF! -> #REF! | R36: ='TQ12042-DB'!#REF! -> #REF! | ... U36: ='TQ12042-DB'!#REF! -> #REF!
A37: ='TQ12042-DB'!#REF! -> #REF! | B37: ='TQ12042-DB'!#REF! -> #REF! | C37: ='TQ12042-DB'!#REF! -> #REF! | D37: ='TQ12042-DB'!#REF! -> #REF! | E37: ='TQ12042-DB'!#REF! -> #REF! | F37: VZGTTQ00008351 | G37: VCG Flex 2024 (FPP) CTS TQ4164 | H37: 1000415076 | I37: Verizon-VCG Flex FPP TQ8351-JA | J37: ADM | K37: ='TQ12042-DB'!#REF! -> #REF! | L37: ='TQ12042-DB'!#REF! -> #REF! | M37: ='TQ12042-DB'!#REF! -> #REF! | N37: ='TQ12042-DB'!#REF! -> #REF! | O37: ='TQ12042-DB'!#REF! -> #REF! | P37: ='TQ12042-DB'!#REF! -> #REF! | Q37: ='TQ12042-DB'!#REF! -> #REF! | R37: ='TQ12042-DB'!#REF! -> #REF! | ... U37: ='TQ12042-DB'!#REF! -> #REF!
A38: ='TQ12042-DB'!#REF! -> #REF! | B38: ='TQ12042-DB'!#REF! -> #REF! | C38: ='TQ12042-DB'!#REF! -> #REF! | D38: ='TQ12042-DB'!#REF! -> #REF! | E38: ='TQ12042-DB'!#REF! -> #REF! | F38: VZGTTQ00008351 | G38: VCG Flex 2024 (FPP) CTS TQ4164 | H38: 1000415076 | I38: Verizon-VCG Flex FPP TQ8351-JA | J38: ADM | K38: ='TQ12042-DB'!#REF! -> #REF! | L38: ='TQ12042-DB'!#REF! -> #REF! | M38: ='TQ12042-DB'!#REF! -> #REF! | N38: ='TQ12042-DB'!#REF! -> #REF! | O38: ='TQ12042-DB'!#REF! -> #REF! | P38: ='TQ12042-DB'!#REF! -> #REF! | Q38: ='TQ12042-DB'!#REF! -> #REF! | R38: ='TQ12042-DB'!#REF! -> #REF! | ... U38: ='TQ12042-DB'!#REF! -> #REF!
A39: ='TQ12042-DB'!#REF! -> #REF! | B39: ='TQ12042-DB'!#REF! -> #REF! | C39: ='TQ12042-DB'!#REF! -> #REF! | D39: ='TQ12042-DB'!#REF! -> #REF! | E39: ='TQ12042-DB'!#REF! -> #REF! | F39: VZGTTQ00008351 | G39: VCG Flex 2024 (FPP) CTS TQ4164 | H39: 1000415076 | I39: Verizon-VCG Flex FPP TQ8351-JA | J39: IDE | K39: ='TQ12042-DB'!#REF! -> #REF! | L39: ='TQ12042-DB'!#REF! -> #REF! | M39: ='TQ12042-DB'!#REF! -> #REF! | N39: ='TQ12042-DB'!#REF! -> #REF! | O39: ='TQ12042-DB'!#REF! -> #REF! | P39: ='TQ12042-DB'!#REF! -> #REF! | Q39: ='TQ12042-DB'!#REF! -> #REF! | R39: ='TQ12042-DB'!#REF! -> #REF! | ... U39: ='TQ12042-DB'!#REF! -> #REF!
A40: ='TQ12042-DB'!#REF! -> #REF! | B40: ='TQ12042-DB'!#REF! -> #REF! | C40: ='TQ12042-DB'!#REF! -> #REF! | D40: ='TQ12042-DB'!#REF! -> #REF! | E40: ='TQ12042-DB'!#REF! -> #REF! | F40: VZGTTQ00008351 | G40: VCG Flex 2024 (FPP) CTS TQ4164 | H40: 1000415076 | I40: Verizon-VCG Flex FPP TQ8351-JA | J40: IOT | K40: ='TQ12042-DB'!#REF! -> #REF! | L40: ='TQ12042-DB'!#REF! -> #REF! | M40: ='TQ12042-DB'!#REF! -> #REF! | N40: ='TQ12042-DB'!#REF! -> #REF! | O40: ='TQ12042-DB'!#REF! -> #REF! | P40: ='TQ12042-DB'!#REF! -> #REF! | Q40: ='TQ12042-DB'!#REF! -> #REF! | R40: ='TQ12042-DB'!#REF! -> #REF! | ... U40: ='TQ12042-DB'!#REF! -> #REF!
A41: ='TQ12042-DB'!#REF! -> #REF! | B41: ='TQ12042-DB'!#REF! -> #REF! | C41: ='TQ12042-DB'!#REF! -> #REF! | D41: ='TQ12042-DB'!#REF! -> #REF! | E41: ='TQ12042-DB'!#REF! -> #REF! | F41: VZGTTQ00008351 | G41: VCG Flex 2024 (FPP) CTS TQ4164 | H41: 1000415076 | I41: Verizon-VCG Flex FPP TQ8351-JA | J41: ADM | K41: ='TQ12042-DB'!#REF! -> #REF! | L41: ='TQ12042-DB'!#REF! -> #REF! | M41: ='TQ12042-DB'!#REF! -> #REF! | N41: ='TQ12042-DB'!#REF! -> #REF! | O41: ='TQ12042-DB'!#REF! -> #REF! | P41: ='TQ12042-DB'!#REF! -> #REF! | Q41: ='TQ12042-DB'!#REF! -> #REF! | R41: ='TQ12042-DB'!#REF! -> #REF! | ... U41: ='TQ12042-DB'!#REF! -> #REF!
A42: ='TQ12042-DB'!#REF! -> #REF! | B42: ='TQ12042-DB'!#REF! -> #REF! | C42: ='TQ12042-DB'!#REF! -> #REF! | D42: ='TQ12042-DB'!#REF! -> #REF! | E42: ='TQ12042-DB'!#REF! -> #REF! | F42: VZGTTQ00008351 | G42: VCG Flex 2024 (FPP) CTS TQ4164 | H42: 1000415076 | I42: Verizon-VCG Flex FPP TQ8351-JA | J42: ADM | K42: ='TQ12042-DB'!#REF! -> #REF! | L42: ='TQ12042-DB'!#REF! -> #REF! | M42: ='TQ12042-DB'!#REF! -> #REF! | N42: ='TQ12042-DB'!#REF! -> #REF! | O42: ='TQ12042-DB'!#REF! -> #REF! | P42: ='TQ12042-DB'!#REF! -> #REF! | Q42: ='TQ12042-DB'!#REF! -> #REF! | R42: ='TQ12042-DB'!#REF! -> #REF! | ... U42: ='TQ12042-DB'!#REF! -> #REF!
A43: ='TQ12042-DB'!#REF! -> #REF! | B43: ='TQ12042-DB'!#REF! -> #REF! | C43: ='TQ12042-DB'!#REF! -> #REF! | D43: ='TQ12042-DB'!#REF! -> #REF! | E43: ='TQ12042-DB'!#REF! -> #REF! | F43: VZGTTQ00008351 | G43: VCG Flex 2024 (FPP) CTS TQ4164 | H43: 1000415076 | I43: Verizon-VCG Flex FPP TQ8351-JA | J43: Pega | K43: ='TQ12042-DB'!#REF! -> #REF! | L43: ='TQ12042-DB'!#REF! -> #REF! | M43: ='TQ12042-DB'!#REF! -> #REF! | N43: ='TQ12042-DB'!#REF! -> #REF! | O43: ='TQ12042-DB'!#REF! -> #REF! | P43: ='TQ12042-DB'!#REF! -> #REF! | Q43: ='TQ12042-DB'!#REF! -> #REF! | R43: ='TQ12042-DB'!#REF! -> #REF! | ... U43: ='TQ12042-DB'!#REF! -> #REF!
A44: ='TQ12042-DB'!#REF! -> #REF! | B44: ='TQ12042-DB'!#REF! -> #REF! | C44: ='TQ12042-DB'!#REF! -> #REF! | D44: ='TQ12042-DB'!#REF! -> #REF! | E44: ='TQ12042-DB'!#REF! -> #REF! | F44: VZGTTQ00008351 | G44: VCG Flex 2024 (FPP) CTS TQ4164 | H44: 1000415076 | I44: Verizon-VCG Flex FPP TQ8351-JA | J44: ADM | K44: ='TQ12042-DB'!#REF! -> #REF! | L44: ='TQ12042-DB'!#REF! -> #REF! | M44: ='TQ12042-DB'!#REF! -> #REF! | N44: ='TQ12042-DB'!#REF! -> #REF! | O44: ='TQ12042-DB'!#REF! -> #REF! | P44: ='TQ12042-DB'!#REF! -> #REF! | Q44: ='TQ12042-DB'!#REF! -> #REF! | R44: ='TQ12042-DB'!#REF! -> #REF! | ... U44: ='TQ12042-DB'!#REF! -> #REF!
A45: ='TQ12042-DB'!#REF! -> #REF! | B45: ='TQ12042-DB'!#REF! -> #REF! | C45: ='TQ12042-DB'!#REF! -> #REF! | D45: ='TQ12042-DB'!#REF! -> #REF! | E45: ='TQ12042-DB'!#REF! -> #REF! | F45: VZGTTQ00008351 | G45: VCG Flex 2024 (FPP) CTS TQ4164 | H45: 1000415076 | I45: Verizon-VCG Flex FPP TQ8351-JA | J45: Pega | K45: ='TQ12042-DB'!#REF! -> #REF! | L45: ='TQ12042-DB'!#REF! -> #REF! | M45: ='TQ12042-DB'!#REF! -> #REF! | N45: ='TQ12042-DB'!#REF! -> #REF! | O45: ='TQ12042-DB'!#REF! -> #REF! | P45: ='TQ12042-DB'!#REF! -> #REF! | Q45: ='TQ12042-DB'!#REF! -> #REF! | R45: ='TQ12042-DB'!#REF! -> #REF! | ... U45: ='TQ12042-DB'!#REF! -> #REF!
A46: ='TQ12042-DB'!#REF! -> #REF! | B46: ='TQ12042-DB'!#REF! -> #REF! | C46: ='TQ12042-DB'!#REF! -> #REF! | D46: ='TQ12042-DB'!#REF! -> #REF! | E46: ='TQ12042-DB'!#REF! -> #REF! | F46: VZGTTQ00008351 | G46: VCG Flex 2024 (FPP) CTS TQ4164 | H46: 1000415076 | I46: Verizon-VCG Flex FPP TQ8351-JA | J46: QEA | K46: ='TQ12042-DB'!#REF! -> #REF! | L46: ='TQ12042-DB'!#REF! -> #REF! | M46: ='TQ12042-DB'!#REF! -> #REF! | N46: ='TQ12042-DB'!#REF! -> #REF! | O46: ='TQ12042-DB'!#REF! -> #REF! | P46: ='TQ12042-DB'!#REF! -> #REF! | Q46: ='TQ12042-DB'!#REF! -> #REF! | R46: ='TQ12042-DB'!#REF! -> #REF! | ... U46: ='TQ12042-DB'!#REF! -> #REF!
A47: ='TQ12042-DB'!#REF! -> #REF! | B47: ='TQ12042-DB'!#REF! -> #REF! | C47: ='TQ12042-DB'!#REF! -> #REF! | D47: ='TQ12042-DB'!#REF! -> #REF! | E47: ='TQ12042-DB'!#REF! -> #REF! | F47: VZGTTQ00008351 | G47: VCG Flex 2024 (FPP) CTS TQ4164 | H47: 1000415076 | I47: Verizon-VCG Flex FPP TQ8351-JA | J47: Pega | K47: ='TQ12042-DB'!#REF! -> #REF! | L47: ='TQ12042-DB'!#REF! -> #REF! | M47: ='TQ12042-DB'!#REF! -> #REF! | N47: ='TQ12042-DB'!#REF! -> #REF! | O47: ='TQ12042-DB'!#REF! -> #REF! | P47: ='TQ12042-DB'!#REF! -> #REF! | Q47: ='TQ12042-DB'!#REF! -> #REF! | R47: ='TQ12042-DB'!#REF! -> #REF! | ... U47: ='TQ12042-DB'!#REF! -> #REF!
A48: ='TQ12042-DB'!#REF! -> #REF! | B48: ='TQ12042-DB'!#REF! -> #REF! | C48: ='TQ12042-DB'!#REF! -> #REF! | D48: ='TQ12042-DB'!#REF! -> #REF! | E48: ='TQ12042-DB'!#REF! -> #REF! | F48: VZGTTQ00008351 | G48: VCG Flex 2024 (FPP) CTS TQ4164 | H48: 1000415076 | I48: Verizon-VCG Flex FPP TQ8351-JA | J48: Pega | K48: ='TQ12042-DB'!#REF! -> #REF! | L48: ='TQ12042-DB'!#REF! -> #REF! | M48: ='TQ12042-DB'!#REF! -> #REF! | N48: ='TQ12042-DB'!#REF! -> #REF! | O48: ='TQ12042-DB'!#REF! -> #REF! | P48: ='TQ12042-DB'!#REF! -> #REF! | Q48: ='TQ12042-DB'!#REF! -> #REF! | R48: ='TQ12042-DB'!#REF! -> #REF! | ... U48: ='TQ12042-DB'!#REF! -> #REF!
A49: ='TQ12042-DB'!#REF! -> #REF! | B49: ='TQ12042-DB'!#REF! -> #REF! | C49: ='TQ12042-DB'!#REF! -> #REF! | D49: ='TQ12042-DB'!#REF! -> #REF! | E49: ='TQ12042-DB'!#REF! -> #REF! | F49: VZGTTQ00008351 | G49: VCG Flex 2024 (FPP) CTS TQ4164 | H49: #N/A | I49: #N/A | J49: #N/A | K49: ='TQ12042-DB'!#REF! -> #REF! | L49: ='TQ12042-DB'!#REF! -> #REF! | M49: ='TQ12042-DB'!#REF! -> #REF! | N49: ='TQ12042-DB'!#REF! -> #REF! | O49: ='TQ12042-DB'!#REF! -> #REF! | P49: ='TQ12042-DB'!#REF! -> #REF! | Q49: ='TQ12042-DB'!#REF! -> #REF! | R49: ='TQ12042-DB'!#REF! -> #REF! | ... U49: ='TQ12042-DB'!#REF! -> #REF!
A50: ='TQ12042-DB'!#REF! -> #REF! | B50: ='TQ12042-DB'!#REF! -> #REF! | C50: ='TQ12042-DB'!#REF! -> #REF! | D50: ='TQ12042-DB'!#REF! -> #REF! | E50: ='TQ12042-DB'!#REF! -> #REF! | F50: VZGTTQ00008351 | G50: VCG Flex 2024 (FPP) CTS TQ4164 | H50: 1000415076 | I50: Verizon-VCG Flex FPP TQ8351-JA | J50: QEA | K50: ='TQ12042-DB'!#REF! -> #REF! | L50: ='TQ12042-DB'!#REF! -> #REF! | M50: ='TQ12042-DB'!#REF! -> #REF! | N50: ='TQ12042-DB'!#REF! -> #REF! | O50: ='TQ12042-DB'!#REF! -> #REF! | P50: ='TQ12042-DB'!#REF! -> #REF! | Q50: ='TQ12042-DB'!#REF! -> #REF! | R50: ='TQ12042-DB'!#REF! -> #REF! | ... U50: ='TQ12042-DB'!#REF! -> #REF!
A51: ='TQ12042-DB'!#REF! -> #REF! | B51: ='TQ12042-DB'!#REF! -> #REF! | C51: ='TQ12042-DB'!#REF! -> #REF! | D51: ='TQ12042-DB'!#REF! -> #REF! | E51: ='TQ12042-DB'!#REF! -> #REF! | F51: VZGTTQ00008351 | G51: VCG Flex 2024 (FPP) CTS TQ4164 | H51: 1000415076 | I51: Verizon-VCG Flex FPP TQ8351-JA | J51: Pega | K51: ='TQ12042-DB'!#REF! -> #REF! | L51: ='TQ12042-DB'!#REF! -> #REF! | M51: ='TQ12042-DB'!#REF! -> #REF! | N51: ='TQ12042-DB'!#REF! -> #REF! | O51: ='TQ12042-DB'!#REF! -> #REF! | P51: ='TQ12042-DB'!#REF! -> #REF! | Q51: ='TQ12042-DB'!#REF! -> #REF! | R51: ='TQ12042-DB'!#REF! -> #REF! | ... U51: ='TQ12042-DB'!#REF! -> #REF!
A52: ='TQ11829-DB'!#REF! -> #REF! | B52: ='TQ11829-DB'!#REF! -> #REF! | C52: ='TQ11829-DB'!#REF! -> #REF! | D52: ='TQ11829-DB'!#REF! -> #REF! | E52: ='TQ11829-DB'!#REF! -> #REF! | F52: VZGTTQ00004628 | G52: VCG Flex (Maslow) TQ4164 CTS | H52: 1000447309 | I52: Verizon-VCG Maslov inst CMS HM | J52: ADM | K52: ='TQ11829-DB'!#REF! -> #REF! | L52: ='TQ11829-DB'!#REF! -> #REF! | M52: ='TQ11829-DB'!#REF! -> #REF! | N52: ='TQ11829-DB'!#REF! -> #REF! | O52: ='TQ11829-DB'!#REF! -> #REF! | P52: ='TQ11829-DB'!#REF! -> #REF! | Q52: ='TQ11829-DB'!#REF! -> #REF! | R52: ='TQ11829-DB'!#REF! -> #REF! | ... V52: ='TQ11829-DB'!#REF! -> #REF!
A53: ='TQ11829-DB'!#REF! -> #REF! | B53: ='TQ11829-DB'!#REF! -> #REF! | C53: ='TQ11829-DB'!#REF! -> #REF! | D53: ='TQ11829-DB'!#REF! -> #REF! | E53: ='TQ11829-DB'!#REF! -> #REF! | F53: VZGTTQ00004628 | G53: VCG Flex (Maslow) TQ4164 CTS | H53: 1000447309 | I53: Verizon-VCG Maslov inst CMS HM | J53: AIA | K53: ='TQ11829-DB'!#REF! -> #REF! | L53: ='TQ11829-DB'!#REF! -> #REF! | M53: ='TQ11829-DB'!#REF! -> #REF! | N53: ='TQ11829-DB'!#REF! -> #REF! | O53: ='TQ11829-DB'!#REF! -> #REF! | P53: ='TQ11829-DB'!#REF! -> #REF! | Q53: ='TQ11829-DB'!#REF! -> #REF! | R53: ='TQ11829-DB'!#REF! -> #REF! | ... V53: ='TQ11829-DB'!#REF! -> #REF!
A54: ='TQ11829-DB'!#REF! -> #REF! | B54: ='TQ11829-DB'!#REF! -> #REF! | C54: ='TQ11829-DB'!#REF! -> #REF! | D54: ='TQ11829-DB'!#REF! -> #REF! | E54: ='TQ11829-DB'!#REF! -> #REF! | F54: VZGTTQ00004628 | G54: VCG Flex (Maslow) TQ4164 CTS | H54: 1000447309 | I54: Verizon-VCG Maslov inst CMS HM | J54: ADM | K54: ='TQ11829-DB'!#REF! -> #REF! | L54: ='TQ11829-DB'!#REF! -> #REF! | M54: ='TQ11829-DB'!#REF! -> #REF! | N54: ='TQ11829-DB'!#REF! -> #REF! | O54: ='TQ11829-DB'!#REF! -> #REF! | P54: ='TQ11829-DB'!#REF! -> #REF! | Q54: ='TQ11829-DB'!#REF! -> #REF! | R54: ='TQ11829-DB'!#REF! -> #REF! | ... V54: ='TQ11829-DB'!#REF! -> #REF!
A55: ='TQ11829-DB'!#REF! -> #REF! | B55: ='TQ11829-DB'!#REF! -> #REF! | C55: ='TQ11829-DB'!#REF! -> #REF! | D55: ='TQ11829-DB'!#REF! -> #REF! | E55: ='TQ11829-DB'!#REF! -> #REF! | F55: VZGTTQ00004628 | G55: VCG Flex (Maslow) TQ4164 CTS | H55: 1000431127 | I55: Verizon- VCG Flex - Strategica | J55: Pega | K55: ='TQ11829-DB'!#REF! -> #REF! | L55: ='TQ11829-DB'!#REF! -> #REF! | M55: ='TQ11829-DB'!#REF! -> #REF! | N55: ='TQ11829-DB'!#REF! -> #REF! | O55: ='TQ11829-DB'!#REF! -> #REF! | P55: ='TQ11829-DB'!#REF! -> #REF! | Q55: ='TQ11829-DB'!#REF! -> #REF! | R55: ='TQ11829-DB'!#REF! -> #REF! | ... V55: ='TQ11829-DB'!#REF! -> #REF!
A56: ='TQ11829-DB'!#REF! -> #REF! | B56: ='TQ11829-DB'!#REF! -> #REF! | C56: ='TQ11829-DB'!#REF! -> #REF! | D56: ='TQ11829-DB'!#REF! -> #REF! | E56: ='TQ11829-DB'!#REF! -> #REF! | F56: VZGTTQ00004628 | G56: VCG Flex (Maslow) TQ4164 CTS | H56: 1000447309 | I56: Verizon-VCG Maslov inst CMS HM | J56: ADM | K56: ='TQ11829-DB'!#REF! -> #REF! | L56: ='TQ11829-DB'!#REF! -> #REF! | M56: ='TQ11829-DB'!#REF! -> #REF! | N56: ='TQ11829-DB'!#REF! -> #REF! | O56: ='TQ11829-DB'!#REF! -> #REF! | P56: ='TQ11829-DB'!#REF! -> #REF! | Q56: ='TQ11829-DB'!#REF! -> #REF! | R56: ='TQ11829-DB'!#REF! -> #REF! | ... V56: ='TQ11829-DB'!#REF! -> #REF!
A57: ='TQ11829-DB'!#REF! -> #REF! | B57: ='TQ11829-DB'!#REF! -> #REF! | C57: ='TQ11829-DB'!#REF! -> #REF! | D57: ='TQ11829-DB'!#REF! -> #REF! | E57: ='TQ11829-DB'!#REF! -> #REF! | F57: VZGTTQ00004628 | G57: VCG Flex (Maslow) TQ4164 CTS | H57: 1000447309 | I57: Verizon-VCG Maslov inst CMS HM | J57: ADM | K57: ='TQ11829-DB'!#REF! -> #REF! | L57: ='TQ11829-DB'!#REF! -> #REF! | M57: ='TQ11829-DB'!#REF! -> #REF! | N57: ='TQ11829-DB'!#REF! -> #REF! | O57: ='TQ11829-DB'!#REF! -> #REF! | P57: ='TQ11829-DB'!#REF! -> #REF! | Q57: ='TQ11829-DB'!#REF! -> #REF! | R57: ='TQ11829-DB'!#REF! -> #REF! | ... V57: ='TQ11829-DB'!#REF! -> #REF!
A58: ='TQ11829-DB'!#REF! -> #REF! | B58: ='TQ11829-DB'!#REF! -> #REF! | C58: ='TQ11829-DB'!#REF! -> #REF! | D58: ='TQ11829-DB'!#REF! -> #REF! | E58: ='TQ11829-DB'!#REF! -> #REF! | F58: VZGTTQ00004628 | G58: VCG Flex (Maslow) TQ4164 CTS | H58: 1000447309 | I58: Verizon-VCG Maslov inst CMS HM | J58: ADM | K58: ='TQ11829-DB'!#REF! -> #REF! | L58: ='TQ11829-DB'!#REF! -> #REF! | M58: ='TQ11829-DB'!#REF! -> #REF! | N58: ='TQ11829-DB'!#REF! -> #REF! | O58: ='TQ11829-DB'!#REF! -> #REF! | P58: ='TQ11829-DB'!#REF! -> #REF! | Q58: ='TQ11829-DB'!#REF! -> #REF! | R58: ='TQ11829-DB'!#REF! -> #REF! | ... V58: ='TQ11829-DB'!#REF! -> #REF!
A59: ='TQ11829-DB'!#REF! -> #REF! | B59: ='TQ11829-DB'!#REF! -> #REF! | C59: ='TQ11829-DB'!#REF! -> #REF! | D59: ='TQ11829-DB'!#REF! -> #REF! | E59: ='TQ11829-DB'!#REF! -> #REF! | F59: VZGTTQ00004628 | G59: VCG Flex (Maslow) TQ4164 CTS | H59: #N/A | I59: #N/A | J59: #N/A | K59: ='TQ11829-DB'!#REF! -> #REF! | L59: ='TQ11829-DB'!#REF! -> #REF! | M59: ='TQ11829-DB'!#REF! -> #REF! | N59: ='TQ11829-DB'!#REF! -> #REF! | O59: ='TQ11829-DB'!#REF! -> #REF! | P59: ='TQ11829-DB'!#REF! -> #REF! | Q59: ='TQ11829-DB'!#REF! -> #REF! | R59: ='TQ11829-DB'!#REF! -> #REF! | ... V59: ='TQ11829-DB'!#REF! -> #REF!
A60: =#REF! -> #REF! | B60: =#REF! -> #REF! | C60: =#REF! -> #REF! | D60: =#REF! -> #REF! | E60: =#REF! -> #REF! | F60: VZGTTQ00011059 | G60: VCG Flex (XCIO VBG CBRO) CTS TQ4164 | H60: 1000451136 | I60: Verizon-VCG HM Contract Transp | J60: IDE | K60: =#REF! -> #REF! | L60: =#REF! -> #REF! | M60: =#REF! -> #REF! | N60: =#REF! -> #REF! | O60: =#REF! -> #REF! | P60: =#REF! -> #REF! | Q60: =#REF! -> #REF! | R60: =#REF! -> #REF! | ... V60: =#REF! -> #REF!
A61: =#REF! -> #REF! | B61: =#REF! -> #REF! | C61: =#REF! -> #REF! | D61: =#REF! -> #REF! | E61: =#REF! -> #REF! | F61: VZGTTQ00011059 | G61: VCG Flex (XCIO VBG CBRO) CTS TQ4164 | H61: #N/A | I61: #N/A | J61: #N/A | K61: =#REF! -> #REF! | L61: =#REF! -> #REF! | M61: =#REF! -> #REF! | N61: =#REF! -> #REF! | O61: =#REF! -> #REF! | P61: =#REF! -> #REF! | Q61: =#REF! -> #REF! | R61: =#REF! -> #REF! | ... V61: =#REF! -> #REF!
A62: =#REF! -> #REF! | B62: =#REF! -> #REF! | C62: =#REF! -> #REF! | D62: =#REF! -> #REF! | E62: =#REF! -> #REF! | F62: VZGTTQ00011059 | G62: VCG Flex (XCIO VBG CBRO) CTS TQ4164 | H62: #N/A | I62: #N/A | J62: #N/A | K62: =#REF! -> #REF! | L62: =#REF! -> #REF! | M62: =#REF! -> #REF! | N62: =#REF! -> #REF! | O62: =#REF! -> #REF! | P62: =#REF! -> #REF! | Q62: =#REF! -> #REF! | R62: =#REF! -> #REF! | ... V62: =#REF! -> #REF!
A63: =#REF! -> #REF! | B63: =#REF! -> #REF! | C63: =#REF! -> #REF! | D63: =#REF! -> #REF! | E63: =#REF! -> #REF! | F63: VZGTTQ00011059 | G63: VCG Flex (XCIO VBG CBRO) CTS TQ4164 | H63: 1000430852 | I63: Verizon-VCG Federated innovati | J63: IDE | K63: =#REF! -> #REF! | L63: =#REF! -> #REF! | M63: =#REF! -> #REF! | N63: =#REF! -> #REF! | O63: =#REF! -> #REF! | P63: =#REF! -> #REF! | Q63: =#REF! -> #REF! | R63: =#REF! -> #REF! | ... V63: =#REF! -> #REF!
A64: =#REF! -> #REF! | B64: =#REF! -> #REF! | C64: =#REF! -> #REF! | D64: =#REF! -> #REF! | E64: =#REF! -> #REF! | F64: VZGTTQ00011059 | G64: VCG Flex (XCIO VBG CBRO) CTS TQ4164 | H64: #N/A | I64: #N/A | J64: #N/A | K64: =#REF! -> #REF! | L64: =#REF! -> #REF! | M64: =#REF! -> #REF! | N64: =#REF! -> #REF! | O64: =#REF! -> #REF! | P64: =#REF! -> #REF! | Q64: =#REF! -> #REF! | R64: =#REF! -> #REF! | ... V64: =#REF! -> #REF!
A65: ='VZGTTQ00011460 - RA'!#REF! -> #REF! | B65: ='VZGTTQ00011460 - RA'!#REF! -> #REF! | C65: ='VZGTTQ00011460 - RA'!#REF! -> #REF! | D65: ='VZGTTQ00011460 - RA'!#REF! -> #REF! | E65: ='VZGTTQ00011460 - RA'!#REF! -> #REF! | F65: VZGTTQ00009564 | G65: VCG Flex (Project Elvis) TQ4164 CTS | H65: 1000417402 | I65: Verizon-VCG Flex Elvis HM 2025 | J65: ADM | K65: ='VZGTTQ00011460 - RA'!#REF! -> #REF! | L65: ='VZGTTQ00011460 - RA'!#REF! -> #REF! | M65: ='VZGTTQ00011460 - RA'!#REF! -> #REF! | N65: ='VZGTTQ00011460 - RA'!#REF! -> #REF! | O65: ='VZGTTQ00011460 - RA'!#REF! -> #REF! | P65: ='VZGTTQ00011460 - RA'!#REF! -> #REF! | Q65: ='VZGTTQ00011460 - RA'!#REF! -> #REF! | R65: ='VZGTTQ00011460 - RA'!#REF! -> #REF! | ... U65: ='VZGTTQ00011460 - RA'!#REF! -> #REF!
A66: ='VZGTTQ00011460 - RA'!#REF! -> #REF! | B66: ='VZGTTQ00011460 - RA'!#REF! -> #REF! | C66: ='VZGTTQ00011460 - RA'!#REF! -> #REF! | D66: ='VZGTTQ00011460 - RA'!#REF! -> #REF! | E66: ='VZGTTQ00011460 - RA'!#REF! -> #REF! | F66: VZGTTQ00009564 | G66: VCG Flex (Project Elvis) TQ4164 CTS | H66: 1000417402 | I66: Verizon-VCG Flex Elvis HM 2025 | J66: Pega | K66: ='VZGTTQ00011460 - RA'!#REF! -> #REF! | L66: ='VZGTTQ00011460 - RA'!#REF! -> #REF! | M66: ='VZGTTQ00011460 - RA'!#REF! -> #REF! | N66: ='VZGTTQ00011460 - RA'!#REF! -> #REF! | O66: ='VZGTTQ00011460 - RA'!#REF! -> #REF! | P66: ='VZGTTQ00011460 - RA'!#REF! -> #REF! | Q66: ='VZGTTQ00011460 - RA'!#REF! -> #REF! | R66: ='VZGTTQ00011460 - RA'!#REF! -> #REF! | ... U66: ='VZGTTQ00011460 - RA'!#REF! -> #REF!
A67: ='VZGTTQ00011460 - RA'!#REF! -> #REF! | B67: ='VZGTTQ00011460 - RA'!#REF! -> #REF! | C67: ='VZGTTQ00011460 - RA'!#REF! -> #REF! | D67: ='VZGTTQ00011460 - RA'!#REF! -> #REF! | E67: ='VZGTTQ00011460 - RA'!#REF! -> #REF! | F67: VZGTTQ00009564 | G67: VCG Flex (Project Elvis) TQ4164 CTS | H67: 1000417402 | I67: Verizon-VCG Flex Elvis HM 2025 | J67: Pega | K67: ='VZGTTQ00011460 - RA'!#REF! -> #REF! | L67: ='VZGTTQ00011460 - RA'!#REF! -> #REF! | M67: ='VZGTTQ00011460 - RA'!#REF! -> #REF! | N67: ='VZGTTQ00011460 - RA'!#REF! -> #REF! | O67: ='VZGTTQ00011460 - RA'!#REF! -> #REF! | P67: ='VZGTTQ00011460 - RA'!#REF! -> #REF! | Q67: ='VZGTTQ00011460 - RA'!#REF! -> #REF! | R67: ='VZGTTQ00011460 - RA'!#REF! -> #REF! | ... U67: ='VZGTTQ00011460 - RA'!#REF! -> #REF!
A68: ='VZGTTQ00011460 - RA'!#REF! -> #REF! | B68: ='VZGTTQ00011460 - RA'!#REF! -> #REF! | C68: ='VZGTTQ00011460 - RA'!#REF! -> #REF! | D68: ='VZGTTQ00011460 - RA'!#REF! -> #REF! | E68: ='VZGTTQ00011460 - RA'!#REF! -> #REF! | F68: VZGTTQ00009564 | G68: VCG Flex (Project Elvis) TQ4164 CTS | H68: 1000417402 | I68: Verizon-VCG Flex Elvis HM 2025 | J68: Pega | K68: ='VZGTTQ00011460 - RA'!#REF! -> #REF! | L68: ='VZGTTQ00011460 - RA'!#REF! -> #REF! | M68: ='VZGTTQ00011460 - RA'!#REF! -> #REF! | N68: ='VZGTTQ00011460 - RA'!#REF! -> #REF! | O68: ='VZGTTQ00011460 - RA'!#REF! -> #REF! | P68: ='VZGTTQ00011460 - RA'!#REF! -> #REF! | Q68: ='VZGTTQ00011460 - RA'!#REF! -> #REF! | R68: ='VZGTTQ00011460 - RA'!#REF! -> #REF! | ... U68: ='VZGTTQ00011460 - RA'!#REF! -> #REF!
A69: ='VZGTTQ00011460 - RA'!#REF! -> #REF! | B69: ='VZGTTQ00011460 - RA'!#REF! -> #REF! | C69: ='VZGTTQ00011460 - RA'!#REF! -> #REF! | D69: ='VZGTTQ00011460 - RA'!#REF! -> #REF! | E69: ='VZGTTQ00011460 - RA'!#REF! -> #REF! | F69: VZGTTQ00009564 | G69: VCG Flex (Project Elvis) TQ4164 CTS | H69: 1000417402 | I69: Verizon-VCG Flex Elvis HM 2025 | J69: Pega | K69: ='VZGTTQ00011460 - RA'!#REF! -> #REF! | L69: ='VZGTTQ00011460 - RA'!#REF! -> #REF! | M69: ='VZGTTQ00011460 - RA'!#REF! -> #REF! | N69: ='VZGTTQ00011460 - RA'!#REF! -> #REF! | O69: ='VZGTTQ00011460 - RA'!#REF! -> #REF! | P69: ='VZGTTQ00011460 - RA'!#REF! -> #REF! | Q69: ='VZGTTQ00011460 - RA'!#REF! -> #REF! | R69: ='VZGTTQ00011460 - RA'!#REF! -> #REF! | ... U69: ='VZGTTQ00011460 - RA'!#REF! -> #REF!
A70: ='VZGTTQ00011460 - RA'!#REF! -> #REF! | B70: ='VZGTTQ00011460 - RA'!#REF! -> #REF! | C70: ='VZGTTQ00011460 - RA'!#REF! -> #REF! | D70: ='VZGTTQ00011460 - RA'!#REF! -> #REF! | E70: ='VZGTTQ00011460 - RA'!#REF! -> #REF! | F70: VZGTTQ00009564 | G70: VCG Flex (Project Elvis) TQ4164 CTS | H70: 1000417402 | I70: Verizon-VCG Flex Elvis HM 2025 | J70: ADM | K70: ='VZGTTQ00011460 - RA'!#REF! -> #REF! | L70: ='VZGTTQ00011460 - RA'!#REF! -> #REF! | M70: ='VZGTTQ00011460 - RA'!#REF! -> #REF! | N70: ='VZGTTQ00011460 - RA'!#REF! -> #REF! | O70: ='VZGTTQ00011460 - RA'!#REF! -> #REF! | P70: ='VZGTTQ00011460 - RA'!#REF! -> #REF! | Q70: ='VZGTTQ00011460 - RA'!#REF! -> #REF! | R70: ='VZGTTQ00011460 - RA'!#REF! -> #REF! | ... U70: ='VZGTTQ00011460 - RA'!#REF! -> #REF!
A71: ='VZGTTQ00011460 - RA'!#REF! -> #REF! | B71: ='VZGTTQ00011460 - RA'!#REF! -> #REF! | C71: ='VZGTTQ00011460 - RA'!#REF! -> #REF! | D71: ='VZGTTQ00011460 - RA'!#REF! -> #REF! | E71: ='VZGTTQ00011460 - RA'!#REF! -> #REF! | F71: VZGTTQ00009564 | G71: VCG Flex (Project Elvis) TQ4164 CTS | H71: 1000441057 | I71: Verizon-Clarify Decomposition- | J71: IDE | K71: ='VZGTTQ00011460 - RA'!#REF! -> #REF! | L71: ='VZGTTQ00011460 - RA'!#REF! -> #REF! | M71: ='VZGTTQ00011460 - RA'!#REF! -> #REF! | N71: ='VZGTTQ00011460 - RA'!#REF! -> #REF! | O71: ='VZGTTQ00011460 - RA'!#REF! -> #REF! | P71: ='VZGTTQ00011460 - RA'!#REF! -> #REF! | Q71: ='VZGTTQ00011460 - RA'!#REF! -> #REF! | R71: ='VZGTTQ00011460 - RA'!#REF! -> #REF! | ... U71: ='VZGTTQ00011460 - RA'!#REF! -> #REF!
A72: ='VZGTTQ00011460 - RA'!#REF! -> #REF! | B72: ='VZGTTQ00011460 - RA'!#REF! -> #REF! | C72: ='VZGTTQ00011460 - RA'!#REF! -> #REF! | D72: ='VZGTTQ00011460 - RA'!#REF! -> #REF! | E72: ='VZGTTQ00011460 - RA'!#REF! -> #REF! | F72: VZGTTQ00009564 | G72: VCG Flex (Project Elvis) TQ4164 CTS | H72: #N/A | I72: #N/A | J72: #N/A | K72: ='VZGTTQ00011460 - RA'!#REF! -> #REF! | L72: ='VZGTTQ00011460 - RA'!#REF! -> #REF! | M72: ='VZGTTQ00011460 - RA'!#REF! -> #REF! | N72: ='VZGTTQ00011460 - RA'!#REF! -> #REF! | O72: ='VZGTTQ00011460 - RA'!#REF! -> #REF! | P72: ='VZGTTQ00011460 - RA'!#REF! -> #REF! | Q72: ='VZGTTQ00011460 - RA'!#REF! -> #REF! | R72: ='VZGTTQ00011460 - RA'!#REF! -> #REF! | ... U72: ='VZGTTQ00011460 - RA'!#REF! -> #REF!
A73: ='VZGTTQ00011460 - RA'!#REF! -> #REF! | B73: ='VZGTTQ00011460 - RA'!#REF! -> #REF! | C73: ='VZGTTQ00011460 - RA'!#REF! -> #REF! | D73: ='VZGTTQ00011460 - RA'!#REF! -> #REF! | E73: ='VZGTTQ00011460 - RA'!#REF! -> #REF! | F73: VZGTTQ00009564 | G73: VCG Flex (Project Elvis) TQ4164 CTS | H73: 1000417402 | I73: Verizon-VCG Flex Elvis HM 2025 | J73: ADM | K73: ='VZGTTQ00011460 - RA'!#REF! -> #REF! | L73: ='VZGTTQ00011460 - RA'!#REF! -> #REF! | M73: ='VZGTTQ00011460 - RA'!#REF! -> #REF! | N73: ='VZGTTQ00011460 - RA'!#REF! -> #REF! | O73: ='VZGTTQ00011460 - RA'!#REF! -> #REF! | P73: ='VZGTTQ00011460 - RA'!#REF! -> #REF! | Q73: ='VZGTTQ00011460 - RA'!#REF! -> #REF! | R73: ='VZGTTQ00011460 - RA'!#REF! -> #REF! | ... U73: ='VZGTTQ00011460 - RA'!#REF! -> #REF!
A74: ='VZGTTQ00011460 - RA'!#REF! -> #REF! | B74: ='VZGTTQ00011460 - RA'!#REF! -> #REF! | C74: ='VZGTTQ00011460 - RA'!#REF! -> #REF! | D74: ='VZGTTQ00011460 - RA'!#REF! -> #REF! | E74: ='VZGTTQ00011460 - RA'!#REF! -> #REF! | F74: VZGTTQ00009564 | G74: VCG Flex (Project Elvis) TQ4164 CTS | H74: 1000417402 | I74: Verizon-VCG Flex Elvis HM 2025 | J74: ADM | K74: ='VZGTTQ00011460 - RA'!#REF! -> #REF! | L74: ='VZGTTQ00011460 - RA'!#REF! -> #REF! | M74: ='VZGTTQ00011460 - RA'!#REF! -> #REF! | N74: ='VZGTTQ00011460 - RA'!#REF! -> #REF! | O74: ='VZGTTQ00011460 - RA'!#REF! -> #REF! | P74: ='VZGTTQ00011460 - RA'!#REF! -> #REF! | Q74: ='VZGTTQ00011460 - RA'!#REF! -> #REF! | R74: ='VZGTTQ00011460 - RA'!#REF! -> #REF! | ... U74: ='VZGTTQ00011460 - RA'!#REF! -> #REF!
A75: ='VZGTTQ00011460 - RA'!#REF! -> #REF! | B75: ='VZGTTQ00011460 - RA'!#REF! -> #REF! | C75: ='VZGTTQ00011460 - RA'!#REF! -> #REF! | D75: ='VZGTTQ00011460 - RA'!#REF! -> #REF! | E75: ='VZGTTQ00011460 - RA'!#REF! -> #REF! | F75: VZGTTQ00009564 | G75: VCG Flex (Project Elvis) TQ4164 CTS | H75: #N/A | I75: #N/A | J75: #N/A | K75: ='VZGTTQ00011460 - RA'!#REF! -> #REF! | L75: ='VZGTTQ00011460 - RA'!#REF! -> #REF! | M75: ='VZGTTQ00011460 - RA'!#REF! -> #REF! | N75: ='VZGTTQ00011460 - RA'!#REF! -> #REF! | O75: ='VZGTTQ00011460 - RA'!#REF! -> #REF! | P75: ='VZGTTQ00011460 - RA'!#REF! -> #REF! | Q75: ='VZGTTQ00011460 - RA'!#REF! -> #REF! | R75: ='VZGTTQ00011460 - RA'!#REF! -> #REF! | ... V75: ='VZGTTQ00011460 - RA'!#REF! -> #REF!
A76: ='VZGTTQ00011460 - RA'!#REF! -> #REF! | B76: ='VZGTTQ00011460 - RA'!#REF! -> #REF! | C76: ='VZGTTQ00011460 - RA'!#REF! -> #REF! | D76: ='VZGTTQ00011460 - RA'!#REF! -> #REF! | E76: ='VZGTTQ00011460 - RA'!#REF! -> #REF! | F76: VZGTTQ00009564 | G76: VCG Flex (Project Elvis) TQ4164 CTS | H76: #N/A | I76: #N/A | J76: #N/A | K76: ='VZGTTQ00011460 - RA'!#REF! -> #REF! | L76: ='VZGTTQ00011460 - RA'!#REF! -> #REF! | M76: ='VZGTTQ00011460 - RA'!#REF! -> #REF! | N76: ='VZGTTQ00011460 - RA'!#REF! -> #REF! | O76: ='VZGTTQ00011460 - RA'!#REF! -> #REF! | P76: ='VZGTTQ00011460 - RA'!#REF! -> #REF! | Q76: ='VZGTTQ00011460 - RA'!#REF! -> #REF! | R76: ='VZGTTQ00011460 - RA'!#REF! -> #REF! | ... V76: ='VZGTTQ00011460 - RA'!#REF! -> #REF!
A77: ='VZGTTQ00011460 - RA'!#REF! -> #REF! | B77: ='VZGTTQ00011460 - RA'!#REF! -> #REF! | C77: ='VZGTTQ00011460 - RA'!#REF! -> #REF! | D77: ='VZGTTQ00011460 - RA'!#REF! -> #REF! | E77: ='VZGTTQ00011460 - RA'!#REF! -> #REF! | F77: VZGTTQ00009564 | G77: VCG Flex (Project Elvis) TQ4164 CTS | H77: #N/A | I77: #N/A | J77: #N/A | K77: ='VZGTTQ00011460 - RA'!#REF! -> #REF! | L77: ='VZGTTQ00011460 - RA'!#REF! -> #REF! | M77: ='VZGTTQ00011460 - RA'!#REF! -> #REF! | N77: ='VZGTTQ00011460 - RA'!#REF! -> #REF! | O77: ='VZGTTQ00011460 - RA'!#REF! -> #REF! | P77: ='VZGTTQ00011460 - RA'!#REF! -> #REF! | Q77: ='VZGTTQ00011460 - RA'!#REF! -> #REF! | R77: ='VZGTTQ00011460 - RA'!#REF! -> #REF! | ... V77: ='VZGTTQ00011460 - RA'!#REF! -> #REF!
A78: ='VZGTTQ00011460 - RA'!#REF! -> #REF! | B78: ='VZGTTQ00011460 - RA'!#REF! -> #REF! | C78: ='VZGTTQ00011460 - RA'!#REF! -> #REF! | D78: ='VZGTTQ00011460 - RA'!#REF! -> #REF! | E78: ='VZGTTQ00011460 - RA'!#REF! -> #REF! | F78: VZGTTQ00009564 | G78: VCG Flex (Project Elvis) TQ4164 CTS | H78: #N/A | I78: #N/A | J78: #N/A | K78: ='VZGTTQ00011460 - RA'!#REF! -> #REF! | L78: ='VZGTTQ00011460 - RA'!#REF! -> #REF! | M78: ='VZGTTQ00011460 - RA'!#REF! -> #REF! | N78: ='VZGTTQ00011460 - RA'!#REF! -> #REF! | O78: ='VZGTTQ00011460 - RA'!#REF! -> #REF! | P78: ='VZGTTQ00011460 - RA'!#REF! -> #REF! | Q78: ='VZGTTQ00011460 - RA'!#REF! -> #REF! | R78: ='VZGTTQ00011460 - RA'!#REF! -> #REF! | ... V78: ='VZGTTQ00011460 - RA'!#REF! -> #REF!
A79: ='VZGTTQ00011460 - RA'!#REF! -> #REF! | B79: ='VZGTTQ00011460 - RA'!#REF! -> #REF! | C79: ='VZGTTQ00011460 - RA'!#REF! -> #REF! | D79: ='VZGTTQ00011460 - RA'!#REF! -> #REF! | E79: ='VZGTTQ00011460 - RA'!#REF! -> #REF! | F79: VZGTTQ00009564 | G79: VCG Flex (Project Elvis) TQ4164 CTS | H79: 1000417402 | I79: Verizon-VCG Flex Elvis HM 2025 | J79: QEA | K79: ='VZGTTQ00011460 - RA'!#REF! -> #REF! | L79: ='VZGTTQ00011460 - RA'!#REF! -> #REF! | M79: ='VZGTTQ00011460 - RA'!#REF! -> #REF! | N79: ='VZGTTQ00011460 - RA'!#REF! -> #REF! | O79: ='VZGTTQ00011460 - RA'!#REF! -> #REF! | P79: ='VZGTTQ00011460 - RA'!#REF! -> #REF! | Q79: ='VZGTTQ00011460 - RA'!#REF! -> #REF! | R79: ='VZGTTQ00011460 - RA'!#REF! -> #REF! | ... V79: ='VZGTTQ00011460 - RA'!#REF! -> #REF!
A80: ='VZGTTQ00011460 - RA'!#REF! -> #REF! | B80: ='VZGTTQ00011460 - RA'!#REF! -> #REF! | C80: ='VZGTTQ00011460 - RA'!#REF! -> #REF! | D80: ='VZGTTQ00011460 - RA'!#REF! -> #REF! | E80: ='VZGTTQ00011460 - RA'!#REF! -> #REF! | F80: VZGTTQ00009564 | G80: VCG Flex (Project Elvis) TQ4164 CTS | H80: 1000417402 | I80: Verizon-VCG Flex Elvis HM 2025 | J80: QEA | K80: ='VZGTTQ00011460 - RA'!#REF! -> #REF! | L80: ='VZGTTQ00011460 - RA'!#REF! -> #REF! | M80: ='VZGTTQ00011460 - RA'!#REF! -> #REF! | N80: ='VZGTTQ00011460 - RA'!#REF! -> #REF! | O80: ='VZGTTQ00011460 - RA'!#REF! -> #REF! | P80: ='VZGTTQ00011460 - RA'!#REF! -> #REF! | Q80: ='VZGTTQ00011460 - RA'!#REF! -> #REF! | R80: ='VZGTTQ00011460 - RA'!#REF! -> #REF! | ... V80: ='VZGTTQ00011460 - RA'!#REF! -> #REF!
A81: ='VZGTTQ00011460 - RA'!#REF! -> #REF! | B81: ='VZGTTQ00011460 - RA'!#REF! -> #REF! | C81: ='VZGTTQ00011460 - RA'!#REF! -> #REF! | D81: ='VZGTTQ00011460 - RA'!#REF! -> #REF! | E81: ='VZGTTQ00011460 - RA'!#REF! -> #REF! | F81: VZGTTQ00009564 | G81: VCG Flex (Project Elvis) TQ4164 CTS | H81: 1000417402 | I81: Verizon-VCG Flex Elvis HM 2025 | J81: QEA | K81: ='VZGTTQ00011460 - RA'!#REF! -> #REF! | L81: ='VZGTTQ00011460 - RA'!#REF! -> #REF! | M81: ='VZGTTQ00011460 - RA'!#REF! -> #REF! | N81: ='VZGTTQ00011460 - RA'!#REF! -> #REF! | O81: ='VZGTTQ00011460 - RA'!#REF! -> #REF! | P81: ='VZGTTQ00011460 - RA'!#REF! -> #REF! | Q81: ='VZGTTQ00011460 - RA'!#REF! -> #REF! | R81: ='VZGTTQ00011460 - RA'!#REF! -> #REF! | ... V81: ='VZGTTQ00011460 - RA'!#REF! -> #REF!
A82: ='VZGTTQ00011460 - RA'!#REF! -> #REF! | B82: ='VZGTTQ00011460 - RA'!#REF! -> #REF! | C82: ='VZGTTQ00011460 - RA'!#REF! -> #REF! | D82: ='VZGTTQ00011460 - RA'!#REF! -> #REF! | E82: ='VZGTTQ00011460 - RA'!#REF! -> #REF! | F82: VZGTTQ00009564 | G82: VCG Flex (Project Elvis) TQ4164 CTS | H82: 1000417402 | I82: Verizon-VCG Flex Elvis HM 2025 | J82: QEA | K82: ='VZGTTQ00011460 - RA'!#REF! -> #REF! | L82: ='VZGTTQ00011460 - RA'!#REF! -> #REF! | M82: ='VZGTTQ00011460 - RA'!#REF! -> #REF! | N82: ='VZGTTQ00011460 - RA'!#REF! -> #REF! | O82: ='VZGTTQ00011460 - RA'!#REF! -> #REF! | P82: ='VZGTTQ00011460 - RA'!#REF! -> #REF! | Q82: ='VZGTTQ00011460 - RA'!#REF! -> #REF! | R82: ='VZGTTQ00011460 - RA'!#REF! -> #REF! | ... V82: ='VZGTTQ00011460 - RA'!#REF! -> #REF!
A83: ='VZGTTQ00011460 - RA'!#REF! -> #REF! | B83: ='VZGTTQ00011460 - RA'!#REF! -> #REF! | C83: ='VZGTTQ00011460 - RA'!#REF! -> #REF! | D83: ='VZGTTQ00011460 - RA'!#REF! -> #REF! | E83: ='VZGTTQ00011460 - RA'!#REF! -> #REF! | F83: VZGTTQ00009564 | G83: VCG Flex (Project Elvis) TQ4164 CTS | H83: 1000417402 | I83: Verizon-VCG Flex Elvis HM 2025 | J83: QEA | K83: ='VZGTTQ00011460 - RA'!#REF! -> #REF! | L83: ='VZGTTQ00011460 - RA'!#REF! -> #REF! | M83: ='VZGTTQ00011460 - RA'!#REF! -> #REF! | N83: ='VZGTTQ00011460 - RA'!#REF! -> #REF! | O83: ='VZGTTQ00011460 - RA'!#REF! -> #REF! | P83: ='VZGTTQ00011460 - RA'!#REF! -> #REF! | Q83: ='VZGTTQ00011460 - RA'!#REF! -> #REF! | R83: ='VZGTTQ00011460 - RA'!#REF! -> #REF! | ... V83: ='VZGTTQ00011460 - RA'!#REF! -> #REF!
A84: ='VZGTTQ00011460 - RA'!#REF! -> #REF! | B84: ='VZGTTQ00011460 - RA'!#REF! -> #REF! | C84: ='VZGTTQ00011460 - RA'!#REF! -> #REF! | D84: ='VZGTTQ00011460 - RA'!#REF! -> #REF! | E84: ='VZGTTQ00011460 - RA'!#REF! -> #REF! | F84: VZGTTQ00009564 | G84: VCG Flex (Project Elvis) TQ4164 CTS | H84: 1000417402 | I84: Verizon-VCG Flex Elvis HM 2025 | J84: QEA | K84: ='VZGTTQ00011460 - RA'!#REF! -> #REF! | L84: ='VZGTTQ00011460 - RA'!#REF! -> #REF! | M84: ='VZGTTQ00011460 - RA'!#REF! -> #REF! | N84: ='VZGTTQ00011460 - RA'!#REF! -> #REF! | O84: ='VZGTTQ00011460 - RA'!#REF! -> #REF! | P84: ='VZGTTQ00011460 - RA'!#REF! -> #REF! | Q84: ='VZGTTQ00011460 - RA'!#REF! -> #REF! | R84: ='VZGTTQ00011460 - RA'!#REF! -> #REF! | ... V84: ='VZGTTQ00011460 - RA'!#REF! -> #REF!
A85: ='VZGTTQ00011460 - RA'!#REF! -> #REF! | B85: ='VZGTTQ00011460 - RA'!#REF! -> #REF! | C85: ='VZGTTQ00011460 - RA'!#REF! -> #REF! | D85: ='VZGTTQ00011460 - RA'!#REF! -> #REF! | E85: ='VZGTTQ00011460 - RA'!#REF! -> #REF! | F85: VZGTTQ00009564 | G85: VCG Flex (Project Elvis) TQ4164 CTS | H85: 1000417402 | I85: Verizon-VCG Flex Elvis HM 2025 | J85: QEA | K85: ='VZGTTQ00011460 - RA'!#REF! -> #REF! | L85: ='VZGTTQ00011460 - RA'!#REF! -> #REF! | M85: ='VZGTTQ00011460 - RA'!#REF! -> #REF! | N85: ='VZGTTQ00011460 - RA'!#REF! -> #REF! | O85: ='VZGTTQ00011460 - RA'!#REF! -> #REF! | P85: ='VZGTTQ00011460 - RA'!#REF! -> #REF! | Q85: ='VZGTTQ00011460 - RA'!#REF! -> #REF! | R85: ='VZGTTQ00011460 - RA'!#REF! -> #REF! | ... V85: ='VZGTTQ00011460 - RA'!#REF! -> #REF!
A86: ='VZGTTQ00011460 - RA'!#REF! -> #REF! | B86: ='VZGTTQ00011460 - RA'!#REF! -> #REF! | C86: ='VZGTTQ00011460 - RA'!#REF! -> #REF! | D86: ='VZGTTQ00011460 - RA'!#REF! -> #REF! | E86: ='VZGTTQ00011460 - RA'!#REF! -> #REF! | F86: VZGTTQ00009564 | G86: VCG Flex (Project Elvis) TQ4164 CTS | H86: 1000417402 | I86: Verizon-VCG Flex Elvis HM 2025 | J86: QEA | K86: ='VZGTTQ00011460 - RA'!#REF! -> #REF! | L86: ='VZGTTQ00011460 - RA'!#REF! -> #REF! | M86: ='VZGTTQ00011460 - RA'!#REF! -> #REF! | N86: ='VZGTTQ00011460 - RA'!#REF! -> #REF! | O86: ='VZGTTQ00011460 - RA'!#REF! -> #REF! | P86: ='VZGTTQ00011460 - RA'!#REF! -> #REF! | Q86: ='VZGTTQ00011460 - RA'!#REF! -> #REF! | R86: ='VZGTTQ00011460 - RA'!#REF! -> #REF! | ... V86: ='VZGTTQ00011460 - RA'!#REF! -> #REF!
A87: ='VZGTTQ00011460 - RA'!#REF! -> #REF! | B87: ='VZGTTQ00011460 - RA'!#REF! -> #REF! | C87: ='VZGTTQ00011460 - RA'!#REF! -> #REF! | D87: ='VZGTTQ00011460 - RA'!#REF! -> #REF! | E87: ='VZGTTQ00011460 - RA'!#REF! -> #REF! | F87: VZGTTQ00009564 | G87: VCG Flex (Project Elvis) TQ4164 CTS | H87: 1000417402 | I87: Verizon-VCG Flex Elvis HM 2025 | J87: QEA | K87: ='VZGTTQ00011460 - RA'!#REF! -> #REF! | L87: ='VZGTTQ00011460 - RA'!#REF! -> #REF! | M87: ='VZGTTQ00011460 - RA'!#REF! -> #REF! | N87: ='VZGTTQ00011460 - RA'!#REF! -> #REF! | O87: ='VZGTTQ00011460 - RA'!#REF! -> #REF! | P87: ='VZGTTQ00011460 - RA'!#REF! -> #REF! | Q87: ='VZGTTQ00011460 - RA'!#REF! -> #REF! | R87: ='VZGTTQ00011460 - RA'!#REF! -> #REF! | ... V87: ='VZGTTQ00011460 - RA'!#REF! -> #REF!
A88: ='VZGTTQ00011460 - RA'!#REF! -> #REF! | B88: ='VZGTTQ00011460 - RA'!#REF! -> #REF! | C88: ='VZGTTQ00011460 - RA'!#REF! -> #REF! | D88: ='VZGTTQ00011460 - RA'!#REF! -> #REF! | E88: ='VZGTTQ00011460 - RA'!#REF! -> #REF! | F88: VZGTTQ00009564 | G88: VCG Flex (Project Elvis) TQ4164 CTS | H88: #N/A | I88: #N/A | J88: #N/A | K88: ='VZGTTQ00011460 - RA'!#REF! -> #REF! | L88: ='VZGTTQ00011460 - RA'!#REF! -> #REF! | M88: ='VZGTTQ00011460 - RA'!#REF! -> #REF! | N88: ='VZGTTQ00011460 - RA'!#REF! -> #REF! | O88: ='VZGTTQ00011460 - RA'!#REF! -> #REF! | P88: ='VZGTTQ00011460 - RA'!#REF! -> #REF! | Q88: ='VZGTTQ00011460 - RA'!#REF! -> #REF! | R88: ='VZGTTQ00011460 - RA'!#REF! -> #REF! | ... V88: ='VZGTTQ00011460 - RA'!#REF! -> #REF!
A89: ='VZGTTQ00011460 - RA'!#REF! -> #REF! | B89: ='VZGTTQ00011460 - RA'!#REF! -> #REF! | C89: ='VZGTTQ00011460 - RA'!#REF! -> #REF! | D89: ='VZGTTQ00011460 - RA'!#REF! -> #REF! | E89: ='VZGTTQ00011460 - RA'!#REF! -> #REF! | F89: VZGTTQ00009564 | G89: VCG Flex (Project Elvis) TQ4164 CTS | H89: 1000417402 | I89: Verizon-VCG Flex Elvis HM 2025 | J89: QEA | K89: ='VZGTTQ00011460 - RA'!#REF! -> #REF! | L89: ='VZGTTQ00011460 - RA'!#REF! -> #REF! | M89: ='VZGTTQ00011460 - RA'!#REF! -> #REF! | N89: ='VZGTTQ00011460 - RA'!#REF! -> #REF! | O89: ='VZGTTQ00011460 - RA'!#REF! -> #REF! | P89: ='VZGTTQ00011460 - RA'!#REF! -> #REF! | Q89: ='VZGTTQ00011460 - RA'!#REF! -> #REF! | R89: ='VZGTTQ00011460 - RA'!#REF! -> #REF! | ... V89: ='VZGTTQ00011460 - RA'!#REF! -> #REF!
A90: ='VZGTTQ00011460 - RA'!#REF! -> #REF! | B90: ='VZGTTQ00011460 - RA'!#REF! -> #REF! | C90: ='VZGTTQ00011460 - RA'!#REF! -> #REF! | D90: ='VZGTTQ00011460 - RA'!#REF! -> #REF! | E90: ='VZGTTQ00011460 - RA'!#REF! -> #REF! | F90: VZGTTQ00009564 | G90: VCG Flex (Project Elvis) TQ4164 CTS | H90: 1000417402 | I90: Verizon-VCG Flex Elvis HM 2025 | J90: QEA | K90: ='VZGTTQ00011460 - RA'!#REF! -> #REF! | L90: ='VZGTTQ00011460 - RA'!#REF! -> #REF! | M90: ='VZGTTQ00011460 - RA'!#REF! -> #REF! | N90: ='VZGTTQ00011460 - RA'!#REF! -> #REF! | O90: ='VZGTTQ00011460 - RA'!#REF! -> #REF! | P90: ='VZGTTQ00011460 - RA'!#REF! -> #REF! | Q90: ='VZGTTQ00011460 - RA'!#REF! -> #REF! | R90: ='VZGTTQ00011460 - RA'!#REF! -> #REF! | ... V90: ='VZGTTQ00011460 - RA'!#REF! -> #REF!
A91: ='VZGTTQ00011460 - RA'!#REF! -> #REF! | B91: ='VZGTTQ00011460 - RA'!#REF! -> #REF! | C91: ='VZGTTQ00011460 - RA'!#REF! -> #REF! | D91: ='VZGTTQ00011460 - RA'!#REF! -> #REF! | E91: ='VZGTTQ00011460 - RA'!#REF! -> #REF! | F91: VZGTTQ00009564 | G91: VCG Flex (Project Elvis) TQ4164 CTS | H91: 1000417402 | I91: Verizon-VCG Flex Elvis HM 2025 | J91: ADM | K91: ='VZGTTQ00011460 - RA'!#REF! -> #REF! | L91: ='VZGTTQ00011460 - RA'!#REF! -> #REF! | M91: ='VZGTTQ00011460 - RA'!#REF! -> #REF! | N91: ='VZGTTQ00011460 - RA'!#REF! -> #REF! | O91: ='VZGTTQ00011460 - RA'!#REF! -> #REF! | P91: ='VZGTTQ00011460 - RA'!#REF! -> #REF! | Q91: ='VZGTTQ00011460 - RA'!#REF! -> #REF! | R91: ='VZGTTQ00011460 - RA'!#REF! -> #REF! | ... U91: ='VZGTTQ00011460 - RA'!#REF! -> #REF!
A92: ='VZGTTQ00011460 - RA'!#REF! -> #REF! | B92: ='VZGTTQ00011460 - RA'!#REF! -> #REF! | C92: ='VZGTTQ00011460 - RA'!#REF! -> #REF! | D92: ='VZGTTQ00011460 - RA'!#REF! -> #REF! | E92: ='VZGTTQ00011460 - RA'!#REF! -> #REF! | F92: VZGTTQ00009564 | G92: VCG Flex (Project Elvis) TQ4164 CTS | H92: 1000417402 | I92: Verizon-VCG Flex Elvis HM 2025 | J92: ADM | K92: ='VZGTTQ00011460 - RA'!#REF! -> #REF! | L92: ='VZGTTQ00011460 - RA'!#REF! -> #REF! | M92: ='VZGTTQ00011460 - RA'!#REF! -> #REF! | N92: ='VZGTTQ00011460 - RA'!#REF! -> #REF! | O92: ='VZGTTQ00011460 - RA'!#REF! -> #REF! | P92: ='VZGTTQ00011460 - RA'!#REF! -> #REF! | Q92: ='VZGTTQ00011460 - RA'!#REF! -> #REF! | R92: ='VZGTTQ00011460 - RA'!#REF! -> #REF! | ... U92: ='VZGTTQ00011460 - RA'!#REF! -> #REF!
A93: ='VZGTTQ00011460 - RA'!#REF! -> #REF! | B93: ='VZGTTQ00011460 - RA'!#REF! -> #REF! | C93: ='VZGTTQ00011460 - RA'!#REF! -> #REF! | D93: ='VZGTTQ00011460 - RA'!#REF! -> #REF! | E93: ='VZGTTQ00011460 - RA'!#REF! -> #REF! | F93: VZGTTQ00009564 | G93: VCG Flex (Project Elvis) TQ4164 CTS | H93: 1000417402 | I93: Verizon-VCG Flex Elvis HM 2025 | J93: ADM | K93: ='VZGTTQ00011460 - RA'!#REF! -> #REF! | L93: ='VZGTTQ00011460 - RA'!#REF! -> #REF! | M93: ='VZGTTQ00011460 - RA'!#REF! -> #REF! | N93: ='VZGTTQ00011460 - RA'!#REF! -> #REF! | O93: ='VZGTTQ00011460 - RA'!#REF! -> #REF! | P93: ='VZGTTQ00011460 - RA'!#REF! -> #REF! | Q93: ='VZGTTQ00011460 - RA'!#REF! -> #REF! | R93: ='VZGTTQ00011460 - RA'!#REF! -> #REF! | ... U93: ='VZGTTQ00011460 - RA'!#REF! -> #REF!
A94: ='VZGTTQ00011460 - RA'!#REF! -> #REF! | B94: ='VZGTTQ00011460 - RA'!#REF! -> #REF! | C94: ='VZGTTQ00011460 - RA'!#REF! -> #REF! | D94: ='VZGTTQ00011460 - RA'!#REF! -> #REF! | E94: ='VZGTTQ00011460 - RA'!#REF! -> #REF! | F94: VZGTTQ00009564 | G94: VCG Flex (Project Elvis) TQ4164 CTS | H94: 1000417402 | I94: Verizon-VCG Flex Elvis HM 2025 | J94: ADM | K94: ='VZGTTQ00011460 - RA'!#REF! -> #REF! | L94: ='VZGTTQ00011460 - RA'!#REF! -> #REF! | M94: ='VZGTTQ00011460 - RA'!#REF! -> #REF! | N94: ='VZGTTQ00011460 - RA'!#REF! -> #REF! | O94: ='VZGTTQ00011460 - RA'!#REF! -> #REF! | P94: ='VZGTTQ00011460 - RA'!#REF! -> #REF! | Q94: ='VZGTTQ00011460 - RA'!#REF! -> #REF! | R94: ='VZGTTQ00011460 - RA'!#REF! -> #REF! | ... U94: ='VZGTTQ00011460 - RA'!#REF! -> #REF!
A95: ='LOE-Ref-VZGTTQ00011797-BH'!A9 -> 779427 | B95: ='LOE-Ref-VZGTTQ00011797-BH'!B9 -> Swetha Tanneeru | C95: ='LOE-Ref-VZGTTQ00011797-BH'!C9 -> Onshore | D95: ='LOE-Ref-VZGTTQ00011797-BH'!D9 -> ACT-196 | E95: ='LOE-Ref-VZGTTQ00011797-BH'!G9 -> Java Springboot Microservices SpringReactive | F95: VZGTTQ00008730 | G95: VCG Flex (Mobile Offers Post Paid) TQ4164 CTS | H95: 1000412773 | I95: Verizon-VCG Flex Mobile Offers | J95: IOT | K95: ='LOE-Ref-VZGTTQ00011797-BH'!K9 -> 97 | L95: ='LOE-Ref-VZGTTQ00011797-BH'!L9 -> 16296 | M95: ='LOE-Ref-VZGTTQ00011797-BH'!M9 -> 16296 | N95: ='LOE-Ref-VZGTTQ00011797-BH'!N9 -> 16296 | O95: ='LOE-Ref-VZGTTQ00011797-BH'!O9 -> 16296 | P95: ='LOE-Ref-VZGTTQ00011797-BH'!P9 -> 16296 | Q95: ='LOE-Ref-VZGTTQ00011797-BH'!Q9 -> 16296 | R95: ='LOE-Ref-VZGTTQ00011797-BH'!R9 -> 0 | S95: ='LOE-Ref-VZGTTQ00011797-BH'!Y9 -> 48888 | T95: ='LOE-Ref-VZGTTQ00011797-BH'!Z9 -> 32592 | U95: ='LOE-Ref-VZGTTQ00011797-BH'!AC9 -> 81480
A96: ='LOE-Ref-VZGTTQ00011797-BH'!A10 -> 793528 | B96: ='LOE-Ref-VZGTTQ00011797-BH'!B10 -> Jupally, Radhika Reddy | C96: ='LOE-Ref-VZGTTQ00011797-BH'!C10 -> Onshore | D96: ='LOE-Ref-VZGTTQ00011797-BH'!D10 -> ACT-199 | E96: ='LOE-Ref-VZGTTQ00011797-BH'!G10 -> ReactJS | F96: VZGTTQ00008730 | G96: VCG Flex (Mobile Offers Post Paid) TQ4164 CTS | H96: 1000412773 | I96: Verizon-VCG Flex Mobile Offers | J96: ADM | K96: ='LOE-Ref-VZGTTQ00011797-BH'!K10 -> 97 | L96: ='LOE-Ref-VZGTTQ00011797-BH'!L10 -> 16296 | M96: ='LOE-Ref-VZGTTQ00011797-BH'!M10 -> 16296 | N96: ='LOE-Ref-VZGTTQ00011797-BH'!N10 -> 16296 | O96: ='LOE-Ref-VZGTTQ00011797-BH'!O10 -> 16296 | P96: ='LOE-Ref-VZGTTQ00011797-BH'!P10 -> 16296 | Q96: ='LOE-Ref-VZGTTQ00011797-BH'!Q10 -> 16296 | R96: ='LOE-Ref-VZGTTQ00011797-BH'!R10 -> 16296 | S96: ='LOE-Ref-VZGTTQ00011797-BH'!Y10 -> 48888 | T96: ='LOE-Ref-VZGTTQ00011797-BH'!Z10 -> 48888 | U96: ='LOE-Ref-VZGTTQ00011797-BH'!AC10 -> 97776
A97: ='LOE-Ref-VZGTTQ00011797-BH'!A11 -> 2190947 | B97: ='LOE-Ref-VZGTTQ00011797-BH'!B11 -> Sangu, Sreedhar Reddy | C97: ='LOE-Ref-VZGTTQ00011797-BH'!C11 -> Onshore | D97: ='LOE-Ref-VZGTTQ00011797-BH'!D11 -> ACT-199 | E97: ='LOE-Ref-VZGTTQ00011797-BH'!G11 -> PEGA | F97: VZGTTQ00008730 | G97: VCG Flex (Mobile Offers Post Paid) TQ4164 CTS | H97: 1000412773 | I97: Verizon-VCG Flex Mobile Offers | J97: Pega | K97: ='LOE-Ref-VZGTTQ00011797-BH'!K11 -> 115 | L97: ='LOE-Ref-VZGTTQ00011797-BH'!L11 -> 19320 | M97: ='LOE-Ref-VZGTTQ00011797-BH'!M11 -> 19320 | N97: ='LOE-Ref-VZGTTQ00011797-BH'!N11 -> 19320 | O97: ='LOE-Ref-VZGTTQ00011797-BH'!O11 -> 19320 | P97: ='LOE-Ref-VZGTTQ00011797-BH'!P11 -> 19320 | Q97: ='LOE-Ref-VZGTTQ00011797-BH'!Q11 -> 19320 | R97: ='LOE-Ref-VZGTTQ00011797-BH'!R11 -> 0 | S97: ='LOE-Ref-VZGTTQ00011797-BH'!Y11 -> 57960 | T97: ='LOE-Ref-VZGTTQ00011797-BH'!Z11 -> 38640 | U97: ='LOE-Ref-VZGTTQ00011797-BH'!AC11 -> 96600
A98: ='LOE-Ref-VZGTTQ00011797-BH'!A12 -> 970768 | B98: ='LOE-Ref-VZGTTQ00011797-BH'!B12 -> Vaidya, Snehal Abhijeet | C98: ='LOE-Ref-VZGTTQ00011797-BH'!C12 -> Onshore | D98: ='LOE-Ref-VZGTTQ00011797-BH'!D12 -> ACT-196 | E98: ='LOE-Ref-VZGTTQ00011797-BH'!G12 -> QA Analyst | F98: VZGTTQ00008730 | G98: VCG Flex (Mobile Offers Post Paid) TQ4164 CTS | H98: 1000412773 | I98: Verizon-VCG Flex Mobile Offers | J98: QEA | K98: ='LOE-Ref-VZGTTQ00011797-BH'!K12 -> 85 | L98: ='LOE-Ref-VZGTTQ00011797-BH'!L12 -> 14280 | M98: ='LOE-Ref-VZGTTQ00011797-BH'!M12 -> 14280 | N98: ='LOE-Ref-VZGTTQ00011797-BH'!N12 -> 14280 | O98: ='LOE-Ref-VZGTTQ00011797-BH'!O12 -> 14280 | P98: ='LOE-Ref-VZGTTQ00011797-BH'!P12 -> 14280 | Q98: ='LOE-Ref-VZGTTQ00011797-BH'!Q12 -> 14280 | R98: ='LOE-Ref-VZGTTQ00011797-BH'!R12 -> 14280 | S98: ='LOE-Ref-VZGTTQ00011797-BH'!Y12 -> 42840 | T98: ='LOE-Ref-VZGTTQ00011797-BH'!Z12 -> 42840 | U98: ='LOE-Ref-VZGTTQ00011797-BH'!AC12 -> 85680 | V98: ='LOE-Ref-VZGTTQ00011797-BH'!AF12 -> CarrierUnlock
A99: ='LOE-Ref-VZGTTQ00011797-BH'!A13 -> 622443 | B99: ='LOE-Ref-VZGTTQ00011797-BH'!B13 -> Vijay Kumar Vadlamudi | C99: ='LOE-Ref-VZGTTQ00011797-BH'!C13 -> Onshore | D99: ='LOE-Ref-VZGTTQ00011797-BH'!D13 -> ACT-196 | E99: ='LOE-Ref-VZGTTQ00011797-BH'!G13 -> PATL | F99: VZGTTQ00008730 | G99: VCG Flex (Mobile Offers Post Paid) TQ4164 CTS | H99: 1000412773 | I99: Verizon-VCG Flex Mobile Offers | J99: ADM | K99: ='LOE-Ref-VZGTTQ00011797-BH'!K13 -> 110 | L99: ='LOE-Ref-VZGTTQ00011797-BH'!L13 -> 18480 | M99: ='LOE-Ref-VZGTTQ00011797-BH'!M13 -> 18480 | N99: ='LOE-Ref-VZGTTQ00011797-BH'!N13 -> 18480 | O99: ='LOE-Ref-VZGTTQ00011797-BH'!O13 -> 18480 | P99: ='LOE-Ref-VZGTTQ00011797-BH'!P13 -> 18480 | Q99: ='LOE-Ref-VZGTTQ00011797-BH'!Q13 -> 18480 | R99: ='LOE-Ref-VZGTTQ00011797-BH'!R13 -> 18480 | S99: ='LOE-Ref-VZGTTQ00011797-BH'!Y13 -> 55440 | T99: ='LOE-Ref-VZGTTQ00011797-BH'!Z13 -> 55440 | U99: ='LOE-Ref-VZGTTQ00011797-BH'!AC13 -> 110880
A100: ='LOE-Ref-VZGTTQ00011797-BH'!A14 -> 630305 | B100: ='LOE-Ref-VZGTTQ00011797-BH'!B14 -> Thiyagu Rajendran | C100: ='LOE-Ref-VZGTTQ00011797-BH'!C14 -> Onshore | D100: ='LOE-Ref-VZGTTQ00011797-BH'!D14 -> ACT-196 | E100: ='LOE-Ref-VZGTTQ00011797-BH'!G14 -> Java Springboot Microservices SpringReactive | F100: VZGTTQ00008730 | G100: VCG Flex (Mobile Offers Post Paid) TQ4164 CTS | H100: 1000412773 | I100: Verizon-VCG Flex Mobile Offers | J100: ADM | K100: ='LOE-Ref-VZGTTQ00011797-BH'!K14 -> 97 | L100: ='LOE-Ref-VZGTTQ00011797-BH'!L14 -> 16296 | M100: ='LOE-Ref-VZGTTQ00011797-BH'!M14 -> 16296 | N100: ='LOE-Ref-VZGTTQ00011797-BH'!N14 -> 16296 | O100: ='LOE-Ref-VZGTTQ00011797-BH'!O14 -> 16296 | P100: ='LOE-Ref-VZGTTQ00011797-BH'!P14 -> 16296 | Q100: ='LOE-Ref-VZGTTQ00011797-BH'!Q14 -> 16296 | R100: ='LOE-Ref-VZGTTQ00011797-BH'!R14 -> 16296 | S100: ='LOE-Ref-VZGTTQ00011797-BH'!Y14 -> 48888 | T100: ='LOE-Ref-VZGTTQ00011797-BH'!Z14 -> 48888 | U100: ='LOE-Ref-VZGTTQ00011797-BH'!AC14 -> 97776
A101: ='LOE-Ref-VZGTTQ00011797-BH'!A15 -> 630304 | B101: ='LOE-Ref-VZGTTQ00011797-BH'!B15 -> Thangavel, Manikandan | C101: ='LOE-Ref-VZGTTQ00011797-BH'!C15 -> Onshore | D101: ='LOE-Ref-VZGTTQ00011797-BH'!D15 -> ACT-199 | E101: ='LOE-Ref-VZGTTQ00011797-BH'!G15 -> Java Springboot Microservices SpringReactive | F101: VZGTTQ00008730 | G101: VCG Flex (Mobile Offers Post Paid) TQ4164 CTS | H101: 1000412773 | I101: Verizon-VCG Flex Mobile Offers | J101: ADM | K101: ='LOE-Ref-VZGTTQ00011797-BH'!K15 -> 97 | L101: ='LOE-Ref-VZGTTQ00011797-BH'!L15 -> 16296 | M101: ='LOE-Ref-VZGTTQ00011797-BH'!M15 -> 16296 | N101: ='LOE-Ref-VZGTTQ00011797-BH'!N15 -> 16296 | O101: ='LOE-Ref-VZGTTQ00011797-BH'!O15 -> 16296 | P101: ='LOE-Ref-VZGTTQ00011797-BH'!P15 -> 16296 | Q101: ='LOE-Ref-VZGTTQ00011797-BH'!Q15 -> 16296 | R101: ='LOE-Ref-VZGTTQ00011797-BH'!R15 -> 16296 | S101: ='LOE-Ref-VZGTTQ00011797-BH'!Y15 -> 48888 | T101: ='LOE-Ref-VZGTTQ00011797-BH'!Z15 -> 48888 | U101: ='LOE-Ref-VZGTTQ00011797-BH'!AC15 -> 97776 | V101: ='LOE-Ref-VZGTTQ00011797-BH'!AF15 -> Fandom
A102: ='LOE-Ref-VZGTTQ00011797-BH'!A16 -> 913405 | B102: ='LOE-Ref-VZGTTQ00011797-BH'!B16 -> Gade, Sudheer Kumar | C102: ='LOE-Ref-VZGTTQ00011797-BH'!C16 -> Onshore | D102: ='LOE-Ref-VZGTTQ00011797-BH'!D16 -> ACT-196 | E102: ='LOE-Ref-VZGTTQ00011797-BH'!G16 -> PEGA | F102: VZGTTQ00008730 | G102: VCG Flex (Mobile Offers Post Paid) TQ4164 CTS | H102: 1000412773 | I102: Verizon-VCG Flex Mobile Offers | J102: Pega | K102: ='LOE-Ref-VZGTTQ00011797-BH'!K16 -> 115 | L102: ='LOE-Ref-VZGTTQ00011797-BH'!L16 -> 19320 | M102: ='LOE-Ref-VZGTTQ00011797-BH'!M16 -> 19320 | N102: ='LOE-Ref-VZGTTQ00011797-BH'!N16 -> 19320 | O102: ='LOE-Ref-VZGTTQ00011797-BH'!O16 -> 19320 | P102: ='LOE-Ref-VZGTTQ00011797-BH'!P16 -> 19320 | Q102: ='LOE-Ref-VZGTTQ00011797-BH'!Q16 -> 19320 | R102: ='LOE-Ref-VZGTTQ00011797-BH'!R16 -> 19320 | S102: ='LOE-Ref-VZGTTQ00011797-BH'!Y16 -> 57960 | T102: ='LOE-Ref-VZGTTQ00011797-BH'!Z16 -> 57960 | U102: ='LOE-Ref-VZGTTQ00011797-BH'!AC16 -> 115920 | V102: ='LOE-Ref-VZGTTQ00011797-BH'!AF16 -> Discovery
A103: ='LOE-Ref-VZGTTQ00011797-BH'!A17 -> 952674 | B103: ='LOE-Ref-VZGTTQ00011797-BH'!B17 -> Labib,Nehad Assad | C103: ='LOE-Ref-VZGTTQ00011797-BH'!C17 -> Onshore | D103: ='LOE-Ref-VZGTTQ00011797-BH'!D17 -> ACT-199 | E103: ='LOE-Ref-VZGTTQ00011797-BH'!G17 -> PEGA | F103: VZGTTQ00008730 | G103: VCG Flex (Mobile Offers Post Paid) TQ4164 CTS | H103: 1000412773 | I103: Verizon-VCG Flex Mobile Offers | J103: ADM | K103: ='LOE-Ref-VZGTTQ00011797-BH'!K17 -> 110 | L103: ='LOE-Ref-VZGTTQ00011797-BH'!L17 -> 18480 | M103: ='LOE-Ref-VZGTTQ00011797-BH'!M17 -> 18480 | N103: ='LOE-Ref-VZGTTQ00011797-BH'!N17 -> 18480 | O103: ='LOE-Ref-VZGTTQ00011797-BH'!O17 -> 18480 | P103: ='LOE-Ref-VZGTTQ00011797-BH'!P17 -> 18480 | Q103: ='LOE-Ref-VZGTTQ00011797-BH'!Q17 -> 18480 | R103: ='LOE-Ref-VZGTTQ00011797-BH'!R17 -> 18480 | S103: ='LOE-Ref-VZGTTQ00011797-BH'!Y17 -> 55440 | T103: ='LOE-Ref-VZGTTQ00011797-BH'!Z17 -> 55440 | U103: ='LOE-Ref-VZGTTQ00011797-BH'!AC17 -> 110880 | V103: ='LOE-Ref-VZGTTQ00011797-BH'!AF17 -> Elysium
A104: ='LOE-Ref-VZGTTQ00011797-BH'!A18 -> 883179 | B104: ='LOE-Ref-VZGTTQ00011797-BH'!B18 -> Pottipati, Sreenadh | C104: ='LOE-Ref-VZGTTQ00011797-BH'!C18 -> Onshore | D104: ='LOE-Ref-VZGTTQ00011797-BH'!D18 -> ACT-115 | E104: ='LOE-Ref-VZGTTQ00011797-BH'!G18 -> Pro*C | F104: VZGTTQ00008730 | G104: VCG Flex (Mobile Offers Post Paid) TQ4164 CTS | H104: 1000412773 | I104: Verizon-VCG Flex Mobile Offers | J104: IOT | K104: ='LOE-Ref-VZGTTQ00011797-BH'!K18 -> 97 | L104: ='LOE-Ref-VZGTTQ00011797-BH'!L18 -> 16296 | M104: ='LOE-Ref-VZGTTQ00011797-BH'!M18 -> 0 | N104: ='LOE-Ref-VZGTTQ00011797-BH'!N18 -> 0 | O104: ='LOE-Ref-VZGTTQ00011797-BH'!O18 -> 16296 | P104: ='LOE-Ref-VZGTTQ00011797-BH'!P18 -> 16296 | Q104: ='LOE-Ref-VZGTTQ00011797-BH'!Q18 -> 16296 | R104: ='LOE-Ref-VZGTTQ00011797-BH'!R18 -> 16296 | S104: ='LOE-Ref-VZGTTQ00011797-BH'!Y18 -> 16296 | T104: ='LOE-Ref-VZGTTQ00011797-BH'!Z18 -> 48888 | U104: ='LOE-Ref-VZGTTQ00011797-BH'!AC18 -> 65184
...

Sheet Legend
A1: Flex | B1: Old Project ID | C1: Old Project Name | D1: New Flex 2.0 ESA ID | E1: New Flex 2.0 ESA Project Description | F1: Verizon Sr.D name | G1: Old Verizon TQ | H1: Old SOW | I1: Old Verizon TQ Descroption | J1: New TQ ID | K1: New SOW | L1: New Verizon TQ Descroption | M1: Tower Lead
A2: Global SOW | B2: 1000445090 | C2: Verizon-VCG H&M Tanglewood-JAN | D2: 1000456940 | E2: Verizon-VCG HM Flex2.0 Tanglew | F2: Apurava Sheth | G2: VZGTTQ00010318 | H2: Old SOW | I2: VCG Flex (Tanglewood) TQ4164 CTS | J2: VZGTTQ00011832 | K2: New SOW | L2: VCG Flex (Tanglewood) CTS TQ9703 | M2: Arun Jayaprakash
A3: Global SOW | B3: 1000410706 | C3: Verizon-VCG H&M Flex ACT 5G Pr | D3: 1000456928 | E3: Verizon-VCG HM Flex2.0 5G | F3: Apurava Sheth | G3: VZGTTQ00008385 | H3: Old SOW | I3: VCG Flex 2024 (5G FWA Consumer Products) TQ4164 CTS | J3: VZGTTQ00011596 | K3: New SOW | L3: VCG Flex (5G FWA Consumer Products) TQ9703 CTS | M3: Arun Jayaprakash
A4: Global SOW | B4: 1000410707 | C4: Verizon-VCG H&M Flex ACT Dig H | D4: 1000456930 | E4: Verizon-VCG HM Flex2.0 Dig Hom | F4: Apurava Sheth | G4: VZGTTQ00008947 | H4: Old SOW | I4: VCG Flex (Home App) TQ4164 CTS | J4: VZGTTQ00011409 | K4: New SOW | L4: VCG Flex (5G FWA Digital Experience) TQ4164 CTS - 2025 | M4: Arun Jayaprakash
D5: 1000460544 | E5: Verizon-VCG Flex 2.0 Home App- | F5: Apurava Sheth | J5: VZGTTQ00011434 | K5: New SOW | L5: VCG Flex (Home App) TQ4164 CTS - 2025 | M5: Arun Jayaprakash
A6: Global SOW | B6: 1000412773 | C6: Verizon-VCG H&M Flex Mobile Of | D6: 1000456932 | E6: Verizon-VCG HM Flex 2.0 Mobile | F6: Brian Hurd | G6: VZGTTQ00008730 | H6: Old SOW | I6: VCG Flex (Mobile Offers Post Paid) TQ4164 CTS | J6: VZGTTQ00011797 | K6: New SOW | L6: VCG Flex (Mobile Offers Post Paid) TQ9703 CTS | M6: Vijay Vadalmudi
A7: Global SOW | B7: 1000416318 | C7: Verizon-VCG H&M Flex CPI EPC T | D7: 1000456939 | E7: Verizon-VCG HM Flex2.0 CPI EPC | F7: Deepshikha Bansal | G7: VZGTTQ00008473 | H7: Old SOW | I7: VCG Flex 2024 (CPI_EPC_PRE_DEEPSHIKHA) TQ4164 CTS | J7: VZGTTQ00011503 | K7: New SOW | L7: VCG Flex 2024 (CPI_EPC_PRE_DEEPSHIKHA) TQ4164 CTS - 2025 | M7: Parthiban Ilango
A8: Global SOW | B8: 1000430852 | C8: Verizon-VCG H&M Federated inno | D8: 1000430852 | E8: Verizon-VCG H&M Federated inno | F8: Deepshikha Bansal | G8: VZGTTQ00009511 | H8: Old SOW | I8: VCG Flex (Innovation - Federated Catalog) TQ4164 CTS | J8: VZGTTQ00009511 | K8: New SOW | L8: VCG Flex (Innovation - Federated Catalog) TQ4164 CTS | M8: Parthiban Ilango
A9: Global SOW | B9: 1000431127 | C9: Verizon- VCG H&M Flex - Strate | D9: 1000459566 | E9: Verizon VCG Flex 2.0 HM Strate | F9: Deepshikha Bansal | G9: VZGTTQ00009462 | H9: Old SOW | I9: VCG Flex (Strategically Ready Offers) TQ4164 CTS | J9: VZGTTQ00012012 | K9: New SOW | L9: VCG Flex (Strategically Ready Offers) TQ9703 CTS | M9: Parthiban Ilango
A10: Global SOW | B10: 1000454900 | C10: Verizon-VCG HM OEM-Invoicing-J | D10: 1000454900 | E10: Verizon-VCG HM OEM-Invoicing-J | F10: Deepshikha Bansal | G10: VZGTTQ00011403 | H10: Old SOW | I10: VCG Flex (OEM Invoicing) TQ4164 CTS | J10: VZGTTQ00011403 | K10: New SOW | L10: VCG Flex (OEM Invoicing) TQ4164 CTS | M10: Parthiban Ilango
A11: Global SOW | B11: 1000415076 | C11: Verizon-VCG H&M Flex FPP TQ835 | D11: 1000459568 | E11: Verizon-VCG H&M Flex 2.0 FPP- | F11: Deepshikha Bansal | G11: VZGTTQ00008351 | H11: Old SOW | I11: VCG Flex 2024 (FPP) CTS TQ4164 | J11: VZGTTQ00012042 | K11: New SOW | L11: VCG Flex 2024 (FPP) CTS TQ4164 | M11: Parthiban Ilango
A12: Global SOW | B12: 1000451136 | C12: Verizon-VCG H&M Contract Trans | D12: 1000456941 | E12: Verizon-VCG HM Flex2.0 Contrac | F12: Deepshikha Bansal | G12: VZGTTQ00011059 | H12: Old SOW | I12: VCG Flex (XCIO VBG CBRO) CTS TQ4164 | J12: VZGTTQ00012094 | K12: New SOW | L12: VCG Flex (XCIO VBG CBRO) CTS TQ4164 | M12: Parthiban Ilango
A13: Global SOW | B13: 1000447309 | C13: Verizon-VCG Maslov inst CMS HM | D13: 1000459572 | E13: Verizon-VCG Flex2.0 Maslov ins | F13: Deepshikha Bansal | G13: VZGTTQ00011829 | H13: Old SOW | I13: VCG Flex (Maslow) CTS TQ9703 | J13: VZGTTQ00011829 | K13: New SOW | L13: VCG Flex (Maslow) CTS TQ9703 | M13: Parthiban Ilango
A14: Global SOW | B14: 1000422748 | C14: Verizon-VCG H&M Flex Commissio | D14: 1000456890 | E14: Verizon-VCG HM Flex2.0 Commiss | F14: Harsha Dave | G14: VZGTTQ00008929 | H14: Old SOW | I14: VCG Flex (Commissions) TQ4164 CTS | J14: VZGTTQ00011825 | K14: New SOW | L14: VCG Flex (Sales Performance and commission operations) TQ9703 CTS | M14: Arun Jayaprakash
A15: Global SOW | B15: 1000445724 | C15: Verizon-VCG Flex Sales Perf Ex | D15: 1000456890 | E15: VCG Flex (Sales Performance and commission) TQ4164 CTS | F15: Harsha Dave | G15: VZGTTQ00010436 | H15: Old SOW | I15: VCG Flex (Commissions) TQ4164 CTS | J15: VZGTTQ00011825 | K15: New SOW | L15: VCG Flex (Sales Performance and commission operations) TQ9703 CTS | M15: Arun Jayaprakash
A16: Global SOW | B16: 1000417402 | C16: Verizon-VCG H&M Flex Elvis HM | D16: 1000459563 | E16: Verizon-VCG Flex 2.0 HM Elvis | F16: Rama Achan | G16: VZGTTQ00009564 | H16: Old SOW | I16: VCG Flex (Project Elvis) TQ4164 CTS | J16: VZGTTQ00011460 | K16: New SOW | L16: VCG Flex (Project Elvis) TQ4164 CTS - 2025 | M16: Kali Prasad
A17: Global SOW | B17: 1000417403 | C17: Verizon-VCG H&M Flex DigiOps - | D17: 1000456926 | E17: Verizon-VCG HM Flex2.0 Digiops Business | F17: Umar Mujeeb | G17: VZGTTQ00008593 | H17: Old SOW | I17: VCG Flex (Digital Ops Enabler) TQ4164 CTS | J17: VZGTTQ00011597 | K17: New SOW | L17: VCG Flex (Digital Ops Enabler) TQ4164 CTS - 2025 | M17: Kali Prasad
... A19: Global SOW | B19: 1000455006 | C19: Verizon-VCG HM Marketing Base | D19: 1000456949 | E19: Verizon-VCG HM Flex2.0 Marktng | F19: Umar Mujeeb | G19: VZGTTQ00011151 | H19: Old SOW | I19: VCG Flex (Marketing Base Personalization) TQ4164 CTS | J19: VZGTTQ00011917 | K19: New SOW | L19: VCG Flex (Marketing Base Personalization) TQ9703 CTS | M19: Kali Prasad
A20: Global SOW | D20: 1000440471 | E20: Verizon-VCG Flex S&P Enterpris | J20: VZGTTQ00010502 | K20: New SOW | L20: TSGI Flex - VCG Solution Architecture SOW with Cognizant - Ravi Thomare | M20: Dipanakr Roy
A21: Global SOW | D21: 1000449935 | E21: Verizon-VCG CVR Equifax-APR 20 | J21: VZGTTQ00010960 | K21: New SOW | L21: Flex VCG-CTS - ELEU Equifax Verification - VZGTTQ00010109 | M21: Dipanakr Roy
A22: India SOW | D22: 1000458633 | E22: VDSI-Flex-H&M-Base Marketing | F22: Mangala Seetharaman | J22: VZGTTQ00011931 | K22: New SOW | L22: VCG VZI_Base Marketing_CTS_Sai | M22: Kali Prasad
A23: India SOW | D23: 1000458648 | E23: VDSI-Flex-H&M-Unified communications & Pega QA | F23: Mangala Seetharaman | J23: VZGTTQ00011913 | K23: New SOW | L23: VCG VZI_Unified communications & Pega QA_CTS_Amjad | M23: Kali Prasad
A24: India SOW | D24: 1000458649 | E24: VDSI-Flex-H&M-Marketing Products & Platforms | F24: Mangala Seetharaman | J24: VZGTTQ00011836 | K24: New SOW | L24: VCG VZI_Device & Accessory/ Consumer Products/ MarketingAutomation_CTS_Arun | M24: Ranjith
A25: India SOW | D25: 1000458637 | E25: VDSI-Flex-H&M-Plans ,Perks & Service Offers | F25: Mangala Seetharaman | J25: VZGTTQ00011938 | K25: New SOW | L25: VCG VZI_Plans ,Perks& Service Offers_CTS_Samta | M25: Srini K
A26: India SOW | D26: 1000458636 | E26: VDSI-Flex-H&M-Consumer Products | F26: Robert Sunderdas | J26: VZGTTQ00011861 | K26: New SOW | L26: VCG VZI_Consumer Products_CTS_Harini | M26: Suneeta Kolla / Arun Jayaprakash
A27: India SOW | D27: 1000458645 | E27: VDSI-Flex-H&M-Digital CX | F27: Robert Sunderdas | J27: VZGTTQ00012147 | K27: New SOW | L27: VCG VZI_Digital CX_CTS_Harini | M27: Suneeta Kolla / Arun Jayaprakash
A28: India SOW | D28: 1000458868 | E28: VDSI-Flex-H&M-Compensation & Ops | F28: Robert Sunderdas | J28: VZGTTQ00011944 | K28: New SOW | L28: VCG VZI_Customer service ops_CTS_Harini | M28: Suneeta Kolla / Arun Jayaprakash
A29: India SOW | D29: 1000458647 | E29: VDSI-Flex-H&M- Customer Service Ops | F29: Robert Sunderdas | J29: VZGTTQ00011932 | K29: New SOW | L29: VCG VZI_ Customer service ops-Leads_CTS_Harini | M29: Suneeta Kolla / Arun Jayaprakash
A30: India SOW | D30: 1000458654 | E30: VDSI-Flex-H&M-Vision SOR Platforms- SCM Apps | F30: Robert Sunderdas | J30: VZGTTQ00011950 | K30: New SOW | L30: VCG VZI_Vision SOR Platforms- SCM Apps_CTS_Anand | M30: Kali Prasad
A31: India SOW | D31: 1000458651 | E31: VDSI-Flex-H&M-Vision SOR Platforms - IFE BCP | F31: Robert Sunderdas | J31: VZGTTQ00011840 | K31: New SOW | L31: VCG VZI_Vision SOR Platforms_CTS_Anand | M31: Kali Prasad
A32: Global SOW | D32: 1000456935 | E32: Verizon-VCG HM Flex 2.0 Compli | M32: Dipanakr Roy
A33: Global SOW | D33: 1000458009 | E33: Verizon-VCG HM TQ11465-VBG NSA | F33: Deepshikha Bansal | J33: VZGTTQ00011465 | K33: New SOW | L33: VCG Flex (VBG NSA Deepshikha) TQ4164 CTS | M33: Parthiban Ilango
A34: Global SOW | D34: 1000462526 | E34: Verizon-VCG H&M Churn Base Mar | F34: Umar Mujeeb | J34: VZGTTQ00012148 | K34: New SOW | L34: VCG Flex (Base Marketing Churn)TQ9703 CTS | M34: Kali Prasad
A35: Global SOW | D35: 1000462570 | E35: Verizon-NBX Opportunity H&M-AU | F35: Umar Mujeeb | M35: Kali Prasad
D36: 1000467271 | E36: VDSI-Flex-H&M-Turing_AI | F36: Mangala Seetharaman | M36: Kali Prasad
M1048576: Arun Jayaprakash

Sheet H&M May RFR
A1: 45778 | B1: Home and Marketing,SOR - May RFR
A2: Cognizant Project ID | B2: Cognizant Project Descriptiom | C2: Verizon Project ID (TQ ID) | D2: Verizon Project Description | E2: ESA Manager | F2: ADM | G2: Adobe | H2: AIA | I2: CIS | J2: IDE | K2: IOA | L2: IOT | M2: Pega | N2: QEA | O2: Vertical Core | P2: Grand Total | R2: ADM | S2: Adobe | T2: AIA | U2: CIS | V2: IDE | W2: IOA | X2: IOT | Y2: Pega | Z2: QEA | AA2: Vertical Core | AB2: Grand Total
A3: 1000348365 | B3: VDSI-VCG H&M 1Messaging and Co | C3: VZGTTQ00005360 | D3: ONE MESSAGE AND COMPENSATION APPLICATIONS DEVELOPMENT | E3: Ramasamy,Ravisankar | F3: 57378.146 | G3: 18823.415 | H3: 0 | J3: 0 | K3: 0 | N3: 0 | P3: =SUM(F3:O3) -> 76201.561 | R3: =F3/$P3 -> 0.75297862 | S3: =G3/$P3 -> 0.24702138 | T3: =H3/$P3 -> 0 | U3: =I3/$P3 -> 0 | V3: =J3/$P3 -> 0 | W3: =K3/$P3 -> 0 | X3: =L3/$P3 -> 0 | Y3: =M3/$P3 -> 0 | ... AA3: =O3/$P3 -> 0 | AB3: =SUM(R3:AA3) -> 1
A4: 1000415076 | B4: Verizon-VCG H&M Flex FPP TQ835 | C4: VZGTTQ00008351 | D4: VCG Flex 2024 (FPP) CTS TQ4164 | E4: Ilango,Parthiban | F4: 49392 | J4: 4200 | L4: 16296 | M4: 57288 | N4: 12600 | P4: =SUM(F4:O4) -> 139776 | R4: =F4/$P4 -> 0.35336538 | S4: =G4/$P4 -> 0 | T4: =H4/$P4 -> 0 | U4: =I4/$P4 -> 0 | V4: =J4/$P4 -> 0.030048077 | W4: =K4/$P4 -> 0 | X4: =L4/$P4 -> 0.11658654 | Y4: =M4/$P4 -> 0.40985577 | ... AA4: =O4/$P4 -> 0 | AB4: =SUM(R4:AA4) -> 1
A5: 1000410707 | B5: Verizon-VCG H&M Flex ACT Dig H | C5: VZGTTQ00008374 | D5: VCG Flex (5G FWA Digital Experience) TQ4164 CTS | E5: Jayaprakash,Arun Kumar | F5: 36960 | J5: 17640 | N5: 16800 | P5: =SUM(F5:O5) -> 71400 | R5: =F5/$P5 -> 0.51764706 | S5: =G5/$P5 -> 0 | T5: =H5/$P5 -> 0 | U5: =I5/$P5 -> 0 | V5: =J5/$P5 -> 0.24705882 | W5: =K5/$P5 -> 0 | X5: =L5/$P5 -> 0 | Y5: =M5/$P5 -> 0 | ... AA5: =O5/$P5 -> 0 | AB5: =SUM(R5:AA5) -> 1
A6: 1000410706 | B6: Verizon-VCG H&M Flex ACT 5G Pr | C6: VZGTTQ00008385 | D6: VCG Flex 2024 (5G FWA Consumer Products) TQ4164 CTS | E6: Mylapore Somasekhar,Jeyakumaar | F6: 81480 | J6: 33600 | M6: 0 | N6: 0 | P6: =SUM(F6:O6) -> 115080 | R6: =F6/$P6 -> 0.7080292 | S6: =G6/$P6 -> 0 | T6: =H6/$P6 -> 0 | U6: =I6/$P6 -> 0 | V6: =J6/$P6 -> 0.2919708 | W6: =K6/$P6 -> 0 | X6: =L6/$P6 -> 0 | Y6: =M6/$P6 -> 0 | ... AA6: =O6/$P6 -> 0 | AB6: =SUM(R6:AA6) -> 1
A7: 1000416318 | B7: Verizon-VCG H&M Flex CPI EPC T | C7: VZGTTQ00008473 | D7: VCG Flex 2024 (CPI_EPC_PRE_DEEPSHIKHA) TQ4164 CTS | E7: Ilango,Parthiban | F7: 229656 | J7: 16296 | P7: =SUM(F7:O7) -> 245952 | R7: =F7/$P7 -> 0.93374317 | S7: =G7/$P7 -> 0 | T7: =H7/$P7 -> 0 | U7: =I7/$P7 -> 0 | V7: =J7/$P7 -> 0.066256831 | W7: =K7/$P7 -> 0 | X7: =L7/$P7 -> 0 | Y7: =M7/$P7 -> 0 | ... AA7: =O7/$P7 -> 0 | AB7: =SUM(R7:AA7) -> 1
A8: 1000417403 | B8: Verizon-VCG H&M Flex DigiOps - | C8: VZGTTQ00008593 | D8: VCG Flex (Digital Ops Enabler) TQ4164 CTS | E8: Jain,Atik | F8: 0 | G8: 42000 | N8: 0 | P8: =SUM(F8:O8) -> 42000 | R8: =F8/$P8 -> 0 | S8: =G8/$P8 -> 1 | T8: =H8/$P8 -> 0 | U8: =I8/$P8 -> 0 | V8: =J8/$P8 -> 0 | W8: =K8/$P8 -> 0 | X8: =L8/$P8 -> 0 | Y8: =M8/$P8 -> 0 | ... AA8: =O8/$P8 -> 0 | AB8: =SUM(R8:AA8) -> 1
A9: 1000412773 | B9: Verizon-VCG H&M Flex Mobile Of | C9: VZGTTQ00008730 | D9: VCG Flex (Mobile Offers Post Paid) TQ4164 CTS | E9: Vadlamudi,Vijay Kumar | F9: 425712 | J9: 192528 | K9: 3696 | L9: 48552 | M9: 133056 | N9: 50400 | P9: =SUM(F9:O9) -> 853944 | R9: =F9/$P9 -> 0.49852449 | S9: =G9/$P9 -> 0 | T9: =H9/$P9 -> 0 | U9: =I9/$P9 -> 0 | V9: =J9/$P9 -> 0.22545741 | W9: =K9/$P9 -> 0.0043281527 | X9: =L9/$P9 -> 0.056856187 | Y9: =M9/$P9 -> 0.1558135 | ... AA9: =O9/$P9 -> 0 | AB9: =SUM(R9:AA9) -> 1
A10: 1000422748 | B10: Verizon-VCG H&M Flex Commissio | C10: VZGTTQ00008929 | D10: VCG Flex (Commissions) TQ4164 CTS | E10: Singh,Shweta | F10: 101160 | H10: 6256 | P10: =SUM(F10:O10) -> 107416 | R10: =F10/$P10 -> 0.94175914 | S10: =G10/$P10 -> 0 | T10: =H10/$P10 -> 0.058240858 | U10: =I10/$P10 -> 0 | V10: =J10/$P10 -> 0 | W10: =K10/$P10 -> 0 | X10: =L10/$P10 -> 0 | Y10: =M10/$P10 -> 0 | ... AA10: =O10/$P10 -> 0 | AB10: =SUM(R10:AA10) -> 1
A11: 1000422753 | B11: Verizon-VCG H&M Flex Home APP | C11: VZGTTQ00008947 | D11: VCG Flex (Home App) TQ4164 CTS | E11: Mylapore Somasekhar,Jeyakumaar | F11: 15960 | J11: 0 | M11: 19320 | N11: 30576 | P11: =SUM(F11:O11) -> 65856 | R11: =F11/$P11 -> 0.24234694 | S11: =G11/$P11 -> 0 | T11: =H11/$P11 -> 0 | U11: =I11/$P11 -> 0 | V11: =J11/$P11 -> 0 | W11: =K11/$P11 -> 0 | X11: =L11/$P11 -> 0 | Y11: =M11/$P11 -> 0.29336735 | ... AA11: =O11/$P11 -> 0 | AB11: =SUM(R11:AA11) -> 1
A12: 1000416320 | B12: Verizon-VCG H&M Flex oneMessag | C12: VZGTTQ00009022 | D12: VCG Flex (VBG One Message AEM Migration) TQ4164 CTS | E12: Chennam,Sujana Sree | F12: 105000 | M12: 16296 | N12: 12600 | P12: =SUM(F12:O12) -> 133896 | R12: =F12/$P12 -> 0.78419072 | S12: =G12/$P12 -> 0 | T12: =H12/$P12 -> 0 | U12: =I12/$P12 -> 0 | V12: =J12/$P12 -> 0 | W12: =K12/$P12 -> 0 | X12: =L12/$P12 -> 0 | Y12: =M12/$P12 -> 0.1217064 | ... AA12: =O12/$P12 -> 0 | AB12: =SUM(R12:AA12) -> 1
A13: 1000425394 | B13: VDSI VCG H&M Knowledge Orchest | C13: VZGTTQ00009155 | D13: VCG Knowledge Orchestration | E13: Thangavadivel,Sharathkumar | F13: 7572.2927 | G13: 21083.512 | N13: 7108.6829 | P13: =SUM(F13:O13) -> 35764.488 | R13: =F13/$P13 -> 0.21172658 | S13: =G13/$P13 -> 0.58950969 | T13: =H13/$P13 -> 0 | U13: =I13/$P13 -> 0 | V13: =J13/$P13 -> 0 | W13: =K13/$P13 -> 0 | X13: =L13/$P13 -> 0 | Y13: =M13/$P13 -> 0 | ... AA13: =O13/$P13 -> 0 | AB13: =SUM(R13:AA13) -> 1
A14: 1000425175 | B14: VDSI VCG H&M IFE and BCP | C14: VZGTTQ00009158 | D14: VCG IFE and BCP | E14: P,Arunkumar | F14: 22328.39 | J14: 20744.39 | P14: =SUM(F14:O14) -> 43072.78 | R14: =F14/$P14 -> 0.51838748 | S14: =G14/$P14 -> 0 | T14: =H14/$P14 -> 0 | U14: =I14/$P14 -> 0 | V14: =J14/$P14 -> 0.48161252 | W14: =K14/$P14 -> 0 | X14: =L14/$P14 -> 0 | Y14: =M14/$P14 -> 0 | ... AA14: =O14/$P14 -> 0 | AB14: =SUM(R14:AA14) -> 1
A15: 1000428977 | B15: VDSI-VCG H&M 5G Home Network | C15: VZGTTQ00009363 | D15: VCG_5G Products, Home Network and Platform | E15: Periyakaruppan,Kannan | F15: 81642.537 | H15: 16524.683 | I15: 3786.1463 | J15: 75879.61 | K15: 0 | M15: 8817.1707 | N15: 74439.415 | P15: =SUM(F15:O15) -> 261089.56 | R15: =F15/$P15 -> 0.31269935 | S15: =G15/$P15 -> 0 | T15: =H15/$P15 -> 0.063291243 | U15: =I15/$P15 -> 0.014501332 | V15: =J15/$P15 -> 0.29062675 | W15: =K15/$P15 -> 0 | X15: =L15/$P15 -> 0 | Y15: =M15/$P15 -> 0.033770675 | ... AA15: =O15/$P15 -> 0 | AB15: =SUM(R15:AA15) -> 1
A16: 1000428976 | B16: VDSI-VCG H&M 5G Home-Tanglewoo | C16: VZGTTQ00009364 | D16: VCG_5G Products and Tanglewood | E16: Periyakaruppan,Kannan | F16: 14442.732 | J16: 127872.59 | K16: 23513.171 | M16: 30810.732 | N16: 65987.122 | P16: =SUM(F16:O16) -> 262626.34 | R16: =F16/$P16 -> 0.054993462 | S16: =G16/$P16 -> 0 | T16: =H16/$P16 -> 0 | U16: =I16/$P16 -> 0 | V16: =J16/$P16 -> 0.48689931 | W16: =K16/$P16 -> 0.089530892 | X16: =L16/$P16 -> 0 | Y16: =M16/$P16 -> 0.11731775 | ... AA16: =O16/$P16 -> 0 | AB16: =SUM(R16:AA16) -> 1
A17: 1000430236 | B17: VDSI-VCG-H&M-Home-FWA | C17: VZGTTQ00009371 | D17: VDSI-VCG-H&M-Home-FWA | E17: Kalyanasundaram,Srinivasan | F17: 25699.52 | G17: 3109.92 | J17: 69222.56 | K17: 7626.08 | M17: 24640 | N17: 43428 | O17: 4408.8 | P17: =SUM(F17:O17) -> 178134.88 | R17: =F17/$P17 -> 0.14427 | S17: =G17/$P17 -> 0.017458232 | T17: =H17/$P17 -> 0 | U17: =I17/$P17 -> 0 | V17: =J17/$P17 -> 0.38859633 | W17: =K17/$P17 -> 0.042810706 | X17: =L17/$P17 -> 0 | Y17: =M17/$P17 -> 0.13832215 | ... AA17: =O17/$P17 -> 0.024749785 | AB17: =SUM(R17:AA17) -> 1
A18: 1000431127 | B18: Verizon- VCG H&M Flex - Strate | C18: VZGTTQ00009462 | D18: VCG Flex (Strategically Ready Offers) TQ4164 CTS | E18: Ilango,Parthiban | F18: 37296 | J18: 4200 | M18: 32592 | N18: 40992 | P18: =SUM(F18:O18) -> 115080 | R18: =F18/$P18 -> 0.32408759 | S18: =G18/$P18 -> 0 | T18: =H18/$P18 -> 0 | U18: =I18/$P18 -> 0 | V18: =J18/$P18 -> 0.03649635 | W18: =K18/$P18 -> 0 | X18: =L18/$P18 -> 0 | Y18: =M18/$P18 -> 0.28321168 | ... AA18: =O18/$P18 -> 0 | AB18: =SUM(R18:AA18) -> 1
A19: 1000417402 | B19: Verizon-VCG H&M Flex Elvis HM | C19: VZGTTQ00009564 | D19: VCG Flex (Project Elvis) TQ4164 CTS | E19: Subramanian,Vinu | F19: 134904 | J19: 15456 | M19: 76272 | N19: 86352 | P19: =SUM(F19:O19) -> 312984 | R19: =F19/$P19 -> 0.43102523 | S19: =G19/$P19 -> 0 | T19: =H19/$P19 -> 0 | U19: =I19/$P19 -> 0 | V19: =J19/$P19 -> 0.049382716 | W19: =K19/$P19 -> 0 | X19: =L19/$P19 -> 0 | Y19: =M19/$P19 -> 0.24369297 | ... AA19: =O19/$P19 -> 0 | AB19: =SUM(R19:AA19) -> 1
A20: 1000432850 | B20: VDSI VCG H&M Elvis | C20: VZGTTQ00009682 | D20: VCG_Elvis | E20: JOHN RAJ,Isaiah Ranjith Kumar | F20: 16674.927 | M20: 28518.439 | N20: 4889.3659 | P20: =SUM(F20:O20) -> 50082.732 | R20: =F20/$P20 -> 0.33294763 | S20: =G20/$P20 -> 0 | T20: =H20/$P20 -> 0 | U20: =I20/$P20 -> 0 | V20: =J20/$P20 -> 0 | W20: =K20/$P20 -> 0 | X20: =L20/$P20 -> 0 | Y20: =M20/$P20 -> 0.56942659 | ... AA20: =O20/$P20 -> 0 | AB20: =SUM(R20:AA20) -> 1
A21: 1000445090 | B21: Verizon-VCG H&M Tanglewood-JAN | C21: VZGTTQ00010318 | D21: VCG Flex (Tanglewood) TQ4164 CTS | E21: Mylapore Somasekhar,Jeyakumaar | F21: 182952 | J21: 50106 | L21: 15960 | M21: 77280 | N21: 44520 | P21: =SUM(F21:O21) -> 370818 | R21: =F21/$P21 -> 0.49337411 | S21: =G21/$P21 -> 0 | T21: =H21/$P21 -> 0 | U21: =I21/$P21 -> 0 | V21: =J21/$P21 -> 0.13512289 | W21: =K21/$P21 -> 0 | X21: =L21/$P21 -> 0.043039982 | Y21: =M21/$P21 -> 0.20840412 | ... AA21: =O21/$P21 -> 0 | AB21: =SUM(R21:AA21) -> 1
A22: 1000422748 | B22: Verizon-VCG H&M Flex Commissio | C22: VZGTTQ00010436 | D22: VCG Flex (Sales Performance and commission) TQ4164 CTS | E22: Singh,Shweta | F22: 58800 | P22: =SUM(F22:O22) -> 58800 | R22: =F22/$P22 -> 1 | S22: =G22/$P22 -> 0 | T22: =H22/$P22 -> 0 | U22: =I22/$P22 -> 0 | V22: =J22/$P22 -> 0 | W22: =K22/$P22 -> 0 | X22: =L22/$P22 -> 0 | Y22: =M22/$P22 -> 0 | ... AA22: =O22/$P22 -> 0 | AB22: =SUM(R22:AA22) -> 1
A23: 1000446727 | B23: Verizon-VCG H&M Maslov Instore | C23: VZGTTQ00010544 | D23: VCG Flex (Maslow) TQ4164 CTS | E23: Sriperumbudur Vangeepuram,Rangarajan | F23: 45192 | H23: 16296 | M23: 16296 | P23: =SUM(F23:O23) -> 77784 | R23: =F23/$P23 -> 0.58099352 | S23: =G23/$P23 -> 0 | T23: =H23/$P23 -> 0.20950324 | U23: =I23/$P23 -> 0 | V23: =J23/$P23 -> 0 | W23: =K23/$P23 -> 0 | X23: =L23/$P23 -> 0 | Y23: =M23/$P23 -> 0.20950324 | ... AA23: =O23/$P23 -> 0 | AB23: =SUM(R23:AA23) -> 1
A24: 1000448064 | B24: Verizon-VCG H&M Next Gen Commu | C24: VZGTTQ00010733 | D24: VCG Flex (Next Gen Comms) TQ4164 CTS | E24: Karuppasamy,Saravanan | F24: 0 | G24: 0 | H24: 0 | I24: 0 | J24: 0 | K24: 0 | L24: 0 | M24: 0 | N24: 0 | O24: 0 | P24: 0 | R24: =F24/$P24 -> #DIV/0! | S24: =G24/$P24 -> #DIV/0! | T24: =H24/$P24 -> #DIV/0! | U24: =I24/$P24 -> #DIV/0! | V24: =J24/$P24 -> #DIV/0! | W24: =K24/$P24 -> #DIV/0! | X24: =L24/$P24 -> #DIV/0! | Y24: =M24/$P24 -> #DIV/0! | ... AA24: =O24/$P24 -> #DIV/0! | AB24: =SUM(R24:AA24) -> #DIV/0!
A25: 1000451136 | B25: Verizon-VCG H&M Contract Trans | C25: VZGTTQ00011059 | D25: VCG Flex (XCIO VBG CBRO) CTS TQ4164 | E25: Mothe,Hanmantha Reddy | F25: 19096 | J25: 19696 | N25: 3200 | P25: =SUM(F25:O25) -> 41992 | R25: =F25/$P25 -> 0.45475329 | S25: =G25/$P25 -> 0 | T25: =H25/$P25 -> 0 | U25: =I25/$P25 -> 0 | V25: =J25/$P25 -> 0.46904172 | W25: =K25/$P25 -> 0 | X25: =L25/$P25 -> 0 | Y25: =M25/$P25 -> 0 | ... AA25: =O25/$P25 -> 0 | AB25: =SUM(R25:AA25) -> 1
A26: 1000453836 | B26: Verizon-VCG HM Offer Build-MAR | C26: VZGTTQ00011151 | D26: VCG Flex (Marketing Base Personalization) TQ4164 CTS | E26: Munuswamy,Sheela | F26: 61488 | G26: 4200 | N26: 3000 | P26: =SUM(F26:O26) -> 68688 | R26: =F26/$P26 -> 0.8951782 | S26: =G26/$P26 -> 0.061146052 | T26: =H26/$P26 -> 0 | U26: =I26/$P26 -> 0 | V26: =J26/$P26 -> 0 | W26: =K26/$P26 -> 0 | X26: =L26/$P26 -> 0 | Y26: =M26/$P26 -> 0 | ... AA26: =O26/$P26 -> 0 | AB26: =SUM(R26:AA26) -> 1
A27: Grand Total | F27: =SUM(F3:F26) -> 1810786.5 | G27: =SUM(G3:G26) -> 89216.847 | H27: =SUM(H3:H26) -> 39076.683 | I27: =SUM(I3:I26) -> 3786.1463 | J27: =SUM(J3:J26) -> 647441.15 | K27: =SUM(K3:K26) -> 34835.251 | L27: =SUM(L3:L26) -> 80808 | M27: =SUM(M3:M26) -> 521186.34 | ... P27: =SUM(P3:P26) -> 3728438.3 | R27: =SUM(R3:R26) -> #DIV/0! | S27: =SUM(S3:S26) -> #DIV/0! | T27: =SUM(T3:T26) -> #DIV/0! | U27: =SUM(U3:U26) -> #DIV/0! | V27: =SUM(V3:V26) -> #DIV/0! | W27: =SUM(W3:W26) -> #DIV/0! | X27: =SUM(X3:X26) -> #DIV/0! | Y27: =SUM(Y3:Y26) -> #DIV/0! | ... AB27: =SUM(AB3:AB26) -> #DIV/0!
A29: Cognizant Project ID | B29: Cognizant Project Descriptiom | C29: Verizon Project ID (TQ ID) | D29: Verizon Project Description | F29: ADM | G29: Adobe | H29: AIA | I29: CIS | J29: IDE | K29: IOA | L29: IOT | M29: Pega | N29: QEA | O29: Vertical Core | P29: Grand Total | R29: ADM | S29: Adobe | T29: AIA | U29: CIS | V29: IDE | W29: IOA | X29: IOT | Y29: Pega | Z29: QEA | AA29: Vertical Core | AB29: Grand Total
A30: 1000348365 | B30: VDSI-VCG H&M 1Messaging and Co | C30: VZGTTQ00005360 | D30: ONE MESSAGE AND COMPENSATION APPLICATIONS DEVELOPMENT | E30: Ramasamy,Ravisankar | F30: =F3/$P3 -> 0.75297862 | G30: =G3/$P3 -> 0.24702138 | H30: =H3/$P3 -> 0 | I30: =I3/$P3 -> 0 | J30: =J3/$P3 -> 0 | K30: =K3/$P3 -> 0 | L30: =L3/$P3 -> 0 | M30: =M3/$P3 -> 0 | ... P30: =P3/$P3 -> 1 | R30: =F30/$P30 -> 0.75297862 | S30: =G30/$P30 -> 0.24702138 | T30: =H30/$P30 -> 0 | U30: =I30/$P30 -> 0 | V30: =J30/$P30 -> 0 | W30: =K30/$P30 -> 0 | X30: =L30/$P30 -> 0 | Y30: =M30/$P30 -> 0 | ... AB30: =P30/$P30 -> 1
A31: 1000415076 | B31: Verizon-VCG H&M Flex FPP TQ835 | C31: VZGTTQ00008351 | D31: VCG Flex 2024 (FPP) CTS TQ4164 | E31: Ilango,Parthiban | F31: =F4/$P4 -> 0.35336538 | G31: =G4/$P4 -> 0 | H31: =H4/$P4 -> 0 | I31: =I4/$P4 -> 0 | J31: =J4/$P4 -> 0.030048077 | K31: =K4/$P4 -> 0 | L31: =L4/$P4 -> 0.11658654 | M31: =M4/$P4 -> 0.40985577 | ... P31: =P4/$P4 -> 1 | R31: =F31/$P31 -> 0.35336538 | S31: =G31/$P31 -> 0 | T31: =H31/$P31 -> 0 | U31: =I31/$P31 -> 0 | V31: =J31/$P31 -> 0.030048077 | W31: =K31/$P31 -> 0 | X31: =L31/$P31 -> 0.11658654 | Y31: =M31/$P31 -> 0.40985577 | ... AB31: =P31/$P31 -> 1
A33: 1000410707 | B33: Verizon-VCG H&M Flex ACT Dig H | C33: VZGTTQ00008374 | D33: VCG Flex (5G FWA Digital Experience) TQ4164 CTS | E33: Jayaprakash,Arun Kumar | F33: =F5/$P5 -> 0.51764706 | G33: =G5/$P5 -> 0 | H33: =H5/$P5 -> 0 | I33: =I5/$P5 -> 0 | J33: =J5/$P5 -> 0.24705882 | K33: =K5/$P5 -> 0 | L33: =L5/$P5 -> 0 | M33: =M5/$P5 -> 0 | ... P33: =P5/$P5 -> 1 | R33: =F33/$P33 -> 0.51764706 | S33: =G33/$P33 -> 0 | T33: =H33/$P33 -> 0 | U33: =I33/$P33 -> 0 | V33: =J33/$P33 -> 0.24705882 | W33: =K33/$P33 -> 0 | X33: =L33/$P33 -> 0 | Y33: =M33/$P33 -> 0 | ... AB33: =P33/$P33 -> 1
A34: 1000410706 | B34: Verizon-VCG H&M Flex ACT 5G Pr | C34: VZGTTQ00008385 | D34: VCG Flex 2024 (5G FWA Consumer Products) TQ4164 CTS | E34: Mylapore Somasekhar,Jeyakumaar | F34: =F6/$P6 -> 0.7080292 | G34: =G6/$P6 -> 0 | H34: =H6/$P6 -> 0 | I34: =I6/$P6 -> 0 | J34: =J6/$P6 -> 0.2919708 | K34: =K6/$P6 -> 0 | L34: =L6/$P6 -> 0 | M34: =M6/$P6 -> 0 | ... P34: =P6/$P6 -> 1 | R34: =F34/$P34 -> 0.7080292 | S34: =G34/$P34 -> 0 | T34: =H34/$P34 -> 0 | U34: =I34/$P34 -> 0 | V34: =J34/$P34 -> 0.2919708 | W34: =K34/$P34 -> 0 | X34: =L34/$P34 -> 0 | Y34: =M34/$P34 -> 0 | ... AB34: =P34/$P34 -> 1
A35: 1000416318 | B35: Verizon-VCG H&M Flex CPI EPC T | C35: VZGTTQ00008473 | D35: VCG Flex 2024 (CPI_EPC_PRE_DEEPSHIKHA) TQ4164 CTS | E35: Ilango,Parthiban | F35: =F7/$P7 -> 0.93374317 | G35: =G7/$P7 -> 0 | H35: =H7/$P7 -> 0 | I35: =I7/$P7 -> 0 | J35: =J7/$P7 -> 0.066256831 | K35: =K7/$P7 -> 0 | L35: =L7/$P7 -> 0 | M35: =M7/$P7 -> 0 | ... P35: =P7/$P7 -> 1 | R35: =F35/$P35 -> 0.93374317 | S35: =G35/$P35 -> 0 | T35: =H35/$P35 -> 0 | U35: =I35/$P35 -> 0 | V35: =J35/$P35 -> 0.066256831 | W35: =K35/$P35 -> 0 | X35: =L35/$P35 -> 0 | Y35: =M35/$P35 -> 0 | ... AB35: =P35/$P35 -> 1
A36: 1000417403 | B36: Verizon-VCG H&M Flex DigiOps - | C36: VZGTTQ00008593 | D36: VCG Flex (Digital Ops Enabler) TQ4164 CTS | E36: Jain,Atik | F36: =F8/$P8 -> 0 | G36: =G8/$P8 -> 1 | H36: =H8/$P8 -> 0 | I36: =I8/$P8 -> 0 | J36: =J8/$P8 -> 0 | K36: =K8/$P8 -> 0 | L36: =L8/$P8 -> 0 | M36: =M8/$P8 -> 0 | ... P36: =P8/$P8 -> 1 | R36: =F36/$P36 -> 0 | S36: =G36/$P36 -> 1 | T36: =H36/$P36 -> 0 | U36: =I36/$P36 -> 0 | V36: =J36/$P36 -> 0 | W36: =K36/$P36 -> 0 | X36: =L36/$P36 -> 0 | Y36: =M36/$P36 -> 0 | ... AB36: =P36/$P36 -> 1
A37: 1000412773 | B37: Verizon-VCG H&M Flex Mobile Of | C37: VZGTTQ00008730 | D37: VCG Flex (Mobile Offers Post Paid) TQ4164 CTS | E37: Vadlamudi,Vijay Kumar | F37: =F9/$P9 -> 0.49852449 | G37: =G9/$P9 -> 0 | H37: =H9/$P9 -> 0 | I37: =I9/$P9 -> 0 | J37: =J9/$P9 -> 0.22545741 | K37: =K9/$P9 -> 0.0043281527 | L37: =L9/$P9 -> 0.056856187 | M37: =M9/$P9 -> 0.1558135 | ... P37: =P9/$P9 -> 1 | R37: =F37/$P37 -> 0.49852449 | S37: =G37/$P37 -> 0 | T37: =H37/$P37 -> 0 | U37: =I37/$P37 -> 0 | V37: =J37/$P37 -> 0.22545741 | W37: =K37/$P37 -> 0.0043281527 | X37: =L37/$P37 -> 0.056856187 | Y37: =M37/$P37 -> 0.1558135 | ... AB37: =P37/$P37 -> 1
A38: 1000422748 | B38: Verizon-VCG H&M Flex Commissio | C38: VZGTTQ00008929 | D38: VCG Flex (Commissions) TQ4164 CTS | E38: Singh,Shweta | F38: =F10/$P10 -> 0.94175914 | G38: =G10/$P10 -> 0 | H38: =H10/$P10 -> 0.058240858 | I38: =I10/$P10 -> 0 | J38: =J10/$P10 -> 0 | K38: =K10/$P10 -> 0 | L38: =L10/$P10 -> 0 | M38: =M10/$P10 -> 0 | ... P38: =P10/$P10 -> 1 | R38: =F38/$P38 -> 0.94175914 | S38: =G38/$P38 -> 0 | T38: =H38/$P38 -> 0.058240858 | U38: =I38/$P38 -> 0 | V38: =J38/$P38 -> 0 | W38: =K38/$P38 -> 0 | X38: =L38/$P38 -> 0 | Y38: =M38/$P38 -> 0 | ... AB38: =P38/$P38 -> 1
A39: 1000422753 | B39: Verizon-VCG H&M Flex Home APP | C39: VZGTTQ00008947 | D39: VCG Flex (Home App) TQ4164 CTS | E39: Mylapore Somasekhar,Jeyakumaar | F39: =F11/$P11 -> 0.24234694 | G39: =G11/$P11 -> 0 | H39: =H11/$P11 -> 0 | I39: =I11/$P11 -> 0 | J39: =J11/$P11 -> 0 | K39: =K11/$P11 -> 0 | L39: =L11/$P11 -> 0 | M39: =M11/$P11 -> 0.29336735 | ... P39: =P11/$P11 -> 1 | R39: =F39/$P39 -> 0.24234694 | S39: =G39/$P39 -> 0 | T39: =H39/$P39 -> 0 | U39: =I39/$P39 -> 0 | V39: =J39/$P39 -> 0 | W39: =K39/$P39 -> 0 | X39: =L39/$P39 -> 0 | Y39: =M39/$P39 -> 0.29336735 | ... AB39: =P39/$P39 -> 1
A40: 1000416320 | B40: Verizon-VCG H&M Flex oneMessag | C40: VZGTTQ00009022 | D40: VCG Flex (VBG One Message AEM Migration) TQ4164 CTS | E40: Chennam,Sujana Sree | F40: =F12/$P12 -> 0.78419072 | G40: =G12/$P12 -> 0 | H40: =H12/$P12 -> 0 | I40: =I12/$P12 -> 0 | J40: =J12/$P12 -> 0 | K40: =K12/$P12 -> 0 | L40: =L12/$P12 -> 0 | M40: =M12/$P12 -> 0.1217064 | ... P40: =P12/$P12 -> 1 | R40: =F40/$P40 -> 0.78419072 | S40: =G40/$P40 -> 0 | T40: =H40/$P40 -> 0 | U40: =I40/$P40 -> 0 | V40: =J40/$P40 -> 0 | W40: =K40/$P40 -> 0 | X40: =L40/$P40 -> 0 | Y40: =M40/$P40 -> 0.1217064 | ... AB40: =P40/$P40 -> 1
A41: 1000425394 | B41: VDSI VCG H&M Knowledge Orchest | C41: VZGTTQ00009155 | D41: VCG Knowledge Orchestration | E41: Thangavadivel,Sharathkumar | F41: =F13/$P13 -> 0.21172658 | G41: =G13/$P13 -> 0.58950969 | H41: =H13/$P13 -> 0 | I41: =I13/$P13 -> 0 | J41: =J13/$P13 -> 0 | K41: =K13/$P13 -> 0 | L41: =L13/$P13 -> 0 | M41: =M13/$P13 -> 0 | ... P41: =P13/$P13 -> 1 | R41: =F41/$P41 -> 0.21172658 | S41: =G41/$P41 -> 0.58950969 | T41: =H41/$P41 -> 0 | U41: =I41/$P41 -> 0 | V41: =J41/$P41 -> 0 | W41: =K41/$P41 -> 0 | X41: =L41/$P41 -> 0 | Y41: =M41/$P41 -> 0 | ... AB41: =P41/$P41 -> 1
A42: 1000425175 | B42: VDSI VCG H&M IFE and BCP | C42: VZGTTQ00009158 | D42: VCG IFE and BCP | E42: P,Arunkumar | F42: =F14/$P14 -> 0.51838748 | G42: =G14/$P14 -> 0 | H42: =H14/$P14 -> 0 | I42: =I14/$P14 -> 0 | J42: =J14/$P14 -> 0.48161252 | K42: =K14/$P14 -> 0 | L42: =L14/$P14 -> 0 | M42: =M14/$P14 -> 0 | ... P42: =P14/$P14 -> 1 | R42: =F42/$P42 -> 0.51838748 | S42: =G42/$P42 -> 0 | T42: =H42/$P42 -> 0 | U42: =I42/$P42 -> 0 | V42: =J42/$P42 -> 0.48161252 | W42: =K42/$P42 -> 0 | X42: =L42/$P42 -> 0 | Y42: =M42/$P42 -> 0 | ... AB42: =P42/$P42 -> 1
A43: 1000428977 | B43: VDSI-VCG H&M 5G Home Network | C43: VZGTTQ00009363 | D43: VCG_5G Products, Home Network and Platform | E43: Periyakaruppan,Kannan | F43: =F15/$P15 -> 0.31269935 | G43: =G15/$P15 -> 0 | H43: =H15/$P15 -> 0.063291243 | I43: =I15/$P15 -> 0.014501332 | J43: =J15/$P15 -> 0.29062675 | K43: =K15/$P15 -> 0 | L43: =L15/$P15 -> 0 | M43: =M15/$P15 -> 0.033770675 | ... P43: =P15/$P15 -> 1 | R43: =F43/$P43 -> 0.31269935 | S43: =G43/$P43 -> 0 | T43: =H43/$P43 -> 0.063291243 | U43: =I43/$P43 -> 0.014501332 | V43: =J43/$P43 -> 0.29062675 | W43: =K43/$P43 -> 0 | X43: =L43/$P43 -> 0 | Y43: =M43/$P43 -> 0.033770675 | ... AB43: =P43/$P43 -> 1
A44: 1000428976 | B44: VDSI-VCG H&M 5G Home-Tanglewoo | C44: VZGTTQ00009364 | D44: VCG_5G Products and Tanglewood | E44: Periyakaruppan,Kannan | F44: =F16/$P16 -> 0.054993462 | G44: =G16/$P16 -> 0 | H44: =H16/$P16 -> 0 | I44: =I16/$P16 -> 0 | J44: =J16/$P16 -> 0.48689931 | K44: =K16/$P16 -> 0.089530892 | L44: =L16/$P16 -> 0 | M44: =M16/$P16 -> 0.11731775 | ... P44: =P16/$P16 -> 1 | R44: =F44/$P44 -> 0.054993462 | S44: =G44/$P44 -> 0 | T44: =H44/$P44 -> 0 | U44: =I44/$P44 -> 0 | V44: =J44/$P44 -> 0.48689931 | W44: =K44/$P44 -> 0.089530892 | X44: =L44/$P44 -> 0 | Y44: =M44/$P44 -> 0.11731775 | ... AB44: =P44/$P44 -> 1
... A51: 1000446727 | B51: Verizon-VCG H&M Maslov Instore | C51: VZGTTQ00010544 | D51: VCG Flex (Maslow) TQ4164 CTS | E51: Sriperumbudur Vangeepuram,Rangarajan | F51: =F23/$P23 -> 0.58099352 | G51: =G23/$P23 -> 0 | H51: =H23/$P23 -> 0.20950324 | I51: =I23/$P23 -> 0 | J51: =J23/$P23 -> 0 | K51: =K23/$P23 -> 0 | L51: =L23/$P23 -> 0 | M51: =M23/$P23 -> 0.20950324 | ... P51: =P23/$P23 -> 1 | R51: =F51/$P51 -> 0.58099352 | S51: =G51/$P51 -> 0 | T51: =H51/$P51 -> 0.20950324 | U51: =I51/$P51 -> 0 | V51: =J51/$P51 -> 0 | W51: =K51/$P51 -> 0 | X51: =L51/$P51 -> 0 | Y51: =M51/$P51 -> 0.20950324 | ... AB51: =P51/$P51 -> 1
A52: 1000448064 | B52: Verizon-VCG H&M Next Gen Commu | C52: VZGTTQ00010733 | D52: VCG Flex (Next Gen Comms) TQ4164 CTS | E52: Karuppasamy,Saravanan | F52: 0 | G52: 0 | H52: 0 | I52: 0 | J52: 0 | K52: 0 | L52: 0 | M52: 0 | N52: 0 | O52: 0 | P52: 0 | R52: =F52/$P52 -> #DIV/0! | S52: =G52/$P52 -> #DIV/0! | T52: =H52/$P52 -> #DIV/0! | U52: =I52/$P52 -> #DIV/0! | V52: =J52/$P52 -> #DIV/0! | W52: =K52/$P52 -> #DIV/0! | X52: =L52/$P52 -> #DIV/0! | Y52: =M52/$P52 -> #DIV/0! | ... AB52: =P52/$P52 -> #DIV/0!
A53: 1000451136 | B53: Verizon-VCG H&M Contract Trans | C53: VZGTTQ00011059 | D53: VCG Flex (XCIO VBG CBRO) CTS TQ4164 | E53: Mothe,Hanmantha Reddy | F53: =F25/$P25 -> 0.45475329 | G53: =G25/$P25 -> 0 | H53: =H25/$P25 -> 0 | I53: =I25/$P25 -> 0 | J53: =J25/$P25 -> 0.46904172 | K53: =K25/$P25 -> 0 | L53: =L25/$P25 -> 0 | M53: =M25/$P25 -> 0 | ... P53: =P25/$P25 -> 1 | R53: =F53/$P53 -> 0.45475329 | S53: =G53/$P53 -> 0 | T53: =H53/$P53 -> 0 | U53: =I53/$P53 -> 0 | V53: =J53/$P53 -> 0.46904172 | W53: =K53/$P53 -> 0 | X53: =L53/$P53 -> 0 | Y53: =M53/$P53 -> 0 | ... AB53: =P53/$P53 -> 1
A54: 1000453836 | B54: Verizon-VCG HM Offer Build-MAR | C54: VZGTTQ00011151 | D54: VCG Flex (Marketing Base Personalization) TQ4164 CTS | E54: Munuswamy,Sheela | F54: =F26/$P26 -> 0.8951782 | G54: =G26/$P26 -> 0.061146052 | H54: =H26/$P26 -> 0 | I54: =I26/$P26 -> 0 | J54: =J26/$P26 -> 0 | K54: =K26/$P26 -> 0 | L54: =L26/$P26 -> 0 | M54: =M26/$P26 -> 0 | ... P54: =P26/$P26 -> 1 | R54: =F54/$P54 -> 0.8951782 | S54: =G54/$P54 -> 0.061146052 | T54: =H54/$P54 -> 0 | U54: =I54/$P54 -> 0 | V54: =J54/$P54 -> 0 | W54: =K54/$P54 -> 0 | X54: =L54/$P54 -> 0 | Y54: =M54/$P54 -> 0 | ... AB54: =P54/$P54 -> 1
A55: Grand Total | F55: =F27/$P27 -> 0.4856689 | G55: =G27/$P27 -> 0.023928744 | H55: =H27/$P27 -> 0.010480711 | I55: =I27/$P27 -> 0.0010154778 | J55: =J27/$P27 -> 0.17364942 | K55: =K27/$P27 -> 0.009343121 | L55: =L27/$P27 -> 0.021673417 | M55: =M27/$P27 -> 0.13978677 | ... P55: =P27/$P27 -> 1 | R55: =R27/$P27 -> #DIV/0! | S55: =S27/$P27 -> #DIV/0! | T55: =T27/$P27 -> #DIV/0! | U55: =U27/$P27 -> #DIV/0! | V55: =V27/$P27 -> #DIV/0! | W55: =W27/$P27 -> #DIV/0! | X55: =X27/$P27 -> #DIV/0! | Y55: =Y27/$P27 -> #DIV/0! | ... AB55: =AB27/$P27 -> #DIV/0!

Sheet August RFR
J1: 2025 - Q3 - Quarter | M1: 2025 - Q4 - Quarter
A2: EmpID | B2: Name | C2: Location | D2: ACT/PCT | E2: Skill Set | F2: Verizon Level Mapping | G2: Cognizant Designation | H2: Hourly Rate ($) | I2: Monthly Rate ($) | J2: 45839 | K2: 45870 | L2: 45901 | M2: 45931 | N2: 45962 | O2: 45992 | P2: New Flex 2.0 ESA ID | Q2: New Flex 2.0 ESA Project Description | R2: New TQ ID | S2: New Verizon TQ Descroption | T2: Service Line
A3: 421594 | B3: Sunil Kumar Velaga | C3: Onshore Supplier Location | D3: ACT 238 | E3: Java Springboot Microservices SpringReactive | F3: Level 3 - Premium Skills | G3: M | H3: 96.56 | I3: 16222.08 | J3: 16222.08 | K3: 16222.08 | L3: 16222.08 | M3: 16222.08 | N3: 16222.08 | O3: 16222.08 | P3: 1000459566 | Q3: Verizon VCG Flex 2.0 HM Strate | R3: VZGTTQ00012012 | S3: VCG Flex (Strategically Ready Offers) TQ9703 CTS | T3: ADM
A4: 630134 | B4: Paramasivam, Arasakumar | C4: Onshore Supplier Location | D4: ACT 238 | E4: QA Analyst | F4: Level 3 - Standard Skills | G4: M | H4: 91.9 | I4: 15439.2 | J4: 15439.2 | K4: 15439.2 | L4: 15439.2 | M4: 15439.2 | N4: 15439.2 | O4: 15439.2 | P4: 1000459566 | Q4: Verizon VCG Flex 2.0 HM Strate | R4: VZGTTQ00012013 | S4: VCG Flex (Strategically Ready Offers) TQ9703 CTS | T4: QEA
A5: 955164 | B5: Gomez,Giovanni | C5: Onshore Supplier Location | D5: ACT 238 | E5: QA Analyst | F5: Level 2 - Standard Skills | G5: A | H5: 77 | I5: 12936 | J5: 12936 | K5: 12936 | L5: 12936 | M5: 12936 | N5: 12936 | O5: 12936 | P5: 1000459566 | Q5: Verizon VCG Flex 2.0 HM Strate | R5: VZGTTQ00012014 | S5: VCG Flex (Strategically Ready Offers) TQ9703 CTS | T5: QEA
A6: 2387626 | B6: Kamna,Bhuwan | C6: India | D6: ACT 238 | E6: Java Springboot Microservices SpringReactive | F6: Level 3 - Premium Skills | G6: M | H6: 24.8 | I6: 4687.2 | J6: 4687.2 | K6: 4687.2 | L6: 4687.2 | M6: 4687.2 | N6: 4687.2 | O6: 4687.2 | P6: 1000459566 | Q6: Verizon VCG Flex 2.0 HM Strate | R6: VZGTTQ00012015 | S6: VCG Flex (Strategically Ready Offers) TQ9703 CTS | T6: ADM
A7: 2397654 | B7: Ajey Srinivasu | C7: India | D7: ACT 238 | E7: Java Springboot Microservices SpringReactive | F7: Level 2 - Premium Skills | G7: Cont | H7: 21.3 | I7: 4025.7 | J7: 4025.7 | K7: 4025.7 | L7: 4025.7 | M7: 4025.7 | N7: 4025.7 | O7: 4025.7 | P7: 1000459566 | Q7: Verizon VCG Flex 2.0 HM Strate | R7: VZGTTQ00012016 | S7: VCG Flex (Strategically Ready Offers) TQ9703 CTS | T7: IDE
A8: 2089658 | B8: Lalkumar P | C8: India | D8: ACT 238 | E8: QA Analyst | F8: Level 2 - Standard Skills | G8: A | H8: 20 | I8: 3780 | J8: 3780 | K8: 3780 | L8: 3780 | M8: 3780 | N8: 3780 | O8: 3780 | P8: 1000459566 | Q8: Verizon VCG Flex 2.0 HM Strate | R8: VZGTTQ00012017 | S8: VCG Flex (Strategically Ready Offers) TQ9703 CTS | T8: QEA
A9: 912357 | B9: Shubhada Revanna | C9: India | D9: ACT 238 | E9: QA Analyst | F9: Level 2 - Standard Skills | G9: A | H9: 20 | I9: 3780 | J9: 3780 | K9: 3780 | L9: 3780 | M9: 3780 | N9: 3780 | O9: 3780 | P9: 1000459566 | Q9: Verizon VCG Flex 2.0 HM Strate | R9: VZGTTQ00012018 | S9: VCG Flex (Strategically Ready Offers) TQ9703 CTS | T9: QEA
A10: 783316 | B10: Mounika Bireddy | C10: India | D10: ACT 238 | E10: Java Springboot Microservices SpringReactive | F10: Level 3 - Premium Skills | G10: SA | H10: 24.8 | I10: 4687.2 | J10: 4687.2 | K10: 4687.2 | L10: 4687.2 | M10: 4687.2 | N10: 4687.2 | O10: 4687.2 | P10: 1000459566 | Q10: Verizon VCG Flex 2.0 HM Strate | R10: VZGTTQ00012019 | S10: VCG Flex (Strategically Ready Offers) TQ9703 CTS | T10: IDE
A11: 2345201 | B11: Narina, Sai Srikanth | C11: Onshore Supplier Location | D11: ACT 238 | E11: PEGA | F11: Level 3 - Niche Skills | G11: Cont | H11: 98.21 | I11: 18561.69 | J11: 16499.28 | K11: 16499.28 | L11: 16499.28 | M11: 16499.28 | N11: 16499.28 | O11: 16499.28 | P11: 1000459566 | Q11: Verizon VCG Flex 2.0 HM Strate | R11: VZGTTQ00012020 | S11: VCG Flex (Strategically Ready Offers) TQ9703 CTS | T11: EPS
A12: 2138272 | B12: S, Chithra | C12: India | D12: ACT 238 | E12: Release Train Engineer | F12: Level 3 - Standard Skills | G12: SA | H12: 22.9 | I12: 4328.1 | J12: 4328.1 | K12: 4328.1 | L12: 4328.1 | M12: 4328.1 | N12: 4328.1 | O12: 4328.1 | P12: 1000459566 | Q12: Verizon VCG Flex 2.0 HM Strate | R12: VZGTTQ00012021 | S12: VCG Flex (Strategically Ready Offers) TQ9703 CTS | T12: IOA
A13: 2088900 | B13: Naveen Durai | C13: Onshore Supplier Location | D13: ACT 238 | E13: PEGA | F13: Level 3 - Niche Skills | G13: Cont | H13: 98.21 | I13: 16499.28 | J13: 16499.28 | K13: 16499.28 | L13: 16499.28 | M13: 16499.28 | N13: 16499.28 | O13: 16499.28 | P13: 1000459566 | Q13: Verizon VCG Flex 2.0 HM Strate | R13: VZGTTQ00012022 | S13: VCG Flex (Strategically Ready Offers) TQ9703 CTS | T13: EPS
A14: 527576 | B14: Pradeep Kumar Selvaraj | C14: India | D14: ACT 238 | E14: Java Springboot Microservices SpringReactive | F14: Level 3 - Premium Skills | G14: SA | H14: 24.8 | I14: 4687.2 | J14: 4687.2 | K14: 4687.2 | L14: 4687.2 | M14: 4687.2 | N14: 4687.2 | O14: 4687.2 | P14: 1000459566 | Q14: Verizon VCG Flex 2.0 HM Strate | R14: VZGTTQ00012023 | S14: VCG Flex (Strategically Ready Offers) TQ9703 CTS | T14: ADM
A15: 2405817 | B15: Hariharasudan | C15: India | D15: ACT 238 | E15: Java Springboot Microservices SpringReactive | F15: Level 3 - Premium Skills | G15: M | H15: 24.8 | I15: 4687.2 | J15: 4687.2 | K15: 4687.2 | L15: 4687.2 | M15: 4687.2 | N15: 4687.2 | O15: 4687.2 | P15: 1000459566 | Q15: Verizon VCG Flex 2.0 HM Strate | R15: VZGTTQ00012024 | S15: VCG Flex (Strategically Ready Offers) TQ9703 CTS | T15: ADM
A16: TBD | B16: TBD | C16: Onshore Supplier Location | D16: ACT 238 | E16: PEGA | F16: Level 3 - Niche Skills | G16: M | H16: 98.21 | I16: 16499.28 | J16: 16499.28 | K16: 16499.28 | L16: 16499.28 | M16: 16499.28 | N16: 16499.28 | O16: 16499.28 | P16: 1000459566 | Q16: Verizon VCG Flex 2.0 HM Strate | R16: VZGTTQ00012025 | S16: VCG Flex (Strategically Ready Offers) TQ9703 CTS | T16: ADM
A17: 973537 | B17: Anitha Nalluri (50%) | C17: Onshore Supplier Location | D17: PCT 248 | E17: Java Springboot Microservices SpringReactive | F17: Level 3 - Premium Skills | G17: M | H17: 96.56 | I17: 16222.08 | J17: 16222.08 | K17: 16222.08 | L17: 16222.08 | M17: 16222.08 | N17: 16222.08 | O17: 16222.08 | P17: 1000456939 | Q17: Verizon-VCG HM Flex2.0 CPI EPC | R17: VZGTTQ00011503 | S17: VCG Flex 2024 (CPI_EPC_PRE_DEEPSHIKHA) TQ4164 CTS - 2025 | T17: ADM
A18: 953609 | B18: Deepika Gudise | C18: Onshore Supplier Location | D18: PCT 248 | E18: Scrum Master | F18: Level 3 - Standard Skills | G18: SA | H18: 91.9 | I18: 15439.2 | J18: 15439.2 | K18: 15439.2 | L18: 15439.2 | M18: 15439.2 | N18: 15439.2 | O18: 15439.2 | P18: 1000456939 | Q18: Verizon-VCG HM Flex2.0 CPI EPC | R18: VZGTTQ00011504 | S18: VCG Flex 2024 (CPI_EPC_PRE_DEEPSHIKHA) TQ4164 CTS - 2026 | T18: ADM
A19: 973456 | B19: Mikail Krochta (50%) | C19: Onshore Supplier Location | D19: PCT 248 | E19: Java Springboot Microservices SpringReactive | F19: Level 2 - Premium Skills | G19: A | H19: 82.05 | I19: 13784.4 | J19: 13784.4 | K19: 13784.4 | L19: 13784.4 | M19: 13784.4 | N19: 13784.4 | O19: 13784.4 | P19: 1000456939 | Q19: Verizon-VCG HM Flex2.0 CPI EPC | R19: VZGTTQ00011505 | S19: VCG Flex 2024 (CPI_EPC_PRE_DEEPSHIKHA) TQ4164 CTS - 2027 | T19: ADM
A20: 978430 | B20: Prasantha Deva (50%) | C20: Onshore Supplier Location | D20: PCT 248 | E20: Java Springboot Microservices SpringReactive | F20: Level 3 - Premium Skills | G20: M | H20: 96.56 | I20: 16222.08 | J20: 16222.08 | K20: 16222.08 | L20: 16222.08 | M20: 16222.08 | N20: 16222.08 | O20: 16222.08 | P20: 1000456939 | Q20: Verizon-VCG HM Flex2.0 CPI EPC | R20: VZGTTQ00011506 | S20: VCG Flex 2024 (CPI_EPC_PRE_DEEPSHIKHA) TQ4164 CTS - 2028 | T20: ADM
A21: 968349 | B21: Guzzi,Kathleen | C21: Onshore Supplier Location | D21: PCT 247 | E21: Business Analyst | F21: Level 4 - Expert Skills | G21: M | H21: 128 | I21: 21504 | J21: 21504 | K21: 21504 | L21: 21504 | M21: 21504 | N21: 21504 | O21: 21504 | P21: 1000456939 | Q21: Verizon-VCG HM Flex2.0 CPI EPC | R21: VZGTTQ00011507 | S21: VCG Flex 2024 (CPI_EPC_PRE_DEEPSHIKHA) TQ4164 CTS - 2029 | T21: ADM
A22: 952025 | B22: Vicki Pflughaupt | C22: Onshore Supplier Location | D22: PCT 247 | E22: Business Analyst | F22: Level 4 - Expert Skills | G22: SA | H22: 128 | I22: 21504 | J22: 21504 | K22: 21504 | L22: 21504 | M22: 21504 | N22: 21504 | O22: 21504 | P22: 1000456939 | Q22: Verizon-VCG HM Flex2.0 CPI EPC | R22: VZGTTQ00011508 | S22: VCG Flex 2024 (CPI_EPC_PRE_DEEPSHIKHA) TQ4164 CTS - 2030 | T22: ADM
A23: 758494 | B23: PremChand Maddineni (50%) | C23: Onshore Supplier Location | D23: PCT 246 | E23: Java Springboot Microservices SpringReactive | F23: Level 3 - Premium Skills | G23: SA | H23: 96.56 | I23: 16222.08 | J23: 16222.08 | K23: 16222.08 | L23: 16222.08 | M23: 16222.08 | N23: 16222.08 | O23: 16222.08 | P23: 1000456939 | Q23: Verizon-VCG HM Flex2.0 CPI EPC | R23: VZGTTQ00011509 | S23: VCG Flex 2024 (CPI_EPC_PRE_DEEPSHIKHA) TQ4164 CTS - 2031 | T23: ADM
A24: 969710 | B24: Bola Adebanwo | C24: Onshore Supplier Location | D24: PCT 246 | E24: Java Springboot Microservices SpringReactive | F24: Level 4 - Expert Skills | G24: A | H24: 128 | I24: 21504 | J24: 21504 | K24: 21504 | L24: 21504 | M24: 21504 | N24: 21504 | O24: 21504 | P24: 1000456939 | Q24: Verizon-VCG HM Flex2.0 CPI EPC | R24: VZGTTQ00011510 | S24: VCG Flex 2024 (CPI_EPC_PRE_DEEPSHIKHA) TQ4164 CTS - 2032 | T24: ADM
A25: 970927 | B25: Stefi Gomez | C25: Onshore Supplier Location | D25: PCT 054 | E25: Java Springboot Microservices SpringReactive | F25: Level 3 - Premium Skills | G25: SA | H25: 96.56 | I25: 16222.08 | J25: 16222.08 | K25: 16222.08 | L25: 16222.08 | M25: 16222.08 | N25: 16222.08 | O25: 16222.08 | P25: 1000456939 | Q25: Verizon-VCG HM Flex2.0 CPI EPC | R25: VZGTTQ00011511 | S25: VCG Flex 2024 (CPI_EPC_PRE_DEEPSHIKHA) TQ4164 CTS - 2033 | T25: ADM
A26: 968444 | B26: Suzanne Spadling | C26: Onshore Supplier Location | D26: PCT 246 | E26: Business Analyst | F26: Level 4 - Expert Skills | G26: M | H26: 128 | I26: 21504 | J26: 21504 | K26: 21504 | L26: 21504 | M26: 21504 | N26: 21504 | O26: 21504 | P26: 1000456939 | Q26: Verizon-VCG HM Flex2.0 CPI EPC | R26: VZGTTQ00011512 | S26: VCG Flex 2024 (CPI_EPC_PRE_DEEPSHIKHA) TQ4164 CTS - 2034 | T26: ADM
A27: 970667 | B27: Diane Hammer | C27: Onshore Supplier Location | D27: PCT 247 | E27: Business Analyst | F27: Level 4 - Expert Skills | G27: SA | H27: 128 | I27: 21504 | J27: 21504 | K27: 21504 | L27: 21504 | M27: 21504 | N27: 21504 | O27: 21504 | P27: 1000456939 | Q27: Verizon-VCG HM Flex2.0 CPI EPC | R27: VZGTTQ00011513 | S27: VCG Flex 2024 (CPI_EPC_PRE_DEEPSHIKHA) TQ4164 CTS - 2035 | T27: ADM
A28: 769131 | B28: Ramesh Ravilla (50%) | C28: Onshore Supplier Location | D28: PCT 073 | E28: Java Springboot Microservices SpringReactive | F28: Level 3 - Premium Skills | G28: M | H28: 96.56 | I28: 16222.08 | J28: 16222.08 | K28: 16222.08 | L28: 16222.08 | M28: 16222.08 | N28: 16222.08 | O28: 16222.08 | P28: 1000456939 | Q28: Verizon-VCG HM Flex2.0 CPI EPC | R28: VZGTTQ00011514 | S28: VCG Flex 2024 (CPI_EPC_PRE_DEEPSHIKHA) TQ4164 CTS - 2036 | T28: ADM
... A61: 2423639 | B61: Muralikrishnan Hariharan | C61: India | D61: PCT303 | E61: Java Springboot Microservices SpringReactive | F61: Level 3 - Premium Skills | G61: SA | H61: 24.8 | I61: 4687.2 | J61: 4218.48 | K61: 4218.48 | L61: 4218.48 | M61: 4218.48 | N61: 4218.48 | O61: 1004.4 | P61: 1000456941 | Q61: Verizon-VCG HM Flex2.0 Contrac | R61: VZGTTQ00012094 | S61: VCG Flex (XCIO VBG CBRO) CTS TQ4164 | T61: IDE
A62: 2426223 | B62: Sunny Bansal | C62: India | D62: PCT303 | E62: Java Springboot Microservices SpringReactive | F62: Level 3 - Premium Skills | G62: SA | H62: 24.8 | I62: 4687.2 | J62: 4218.48 | K62: 4218.48 | L62: 4218.48 | M62: 4218.48 | N62: 4218.48 | P62: 1000456941 | Q62: Verizon-VCG HM Flex2.0 Contrac | R62: VZGTTQ00012094 | S62: VCG Flex (XCIO VBG CBRO) CTS TQ4164 | T62: IDE
A63: 2220280 | B63: Suman, Gaurav | C63: India | D63: PCT303 | E63: ReactJS | F63: Level 2 - Premium Skills | G63: A | H63: 21.3 | I63: 4025.7 | J63: 3623.13 | K63: 3623.13 | L63: 3623.13 | M63: 3623.13 | N63: 3623.13 | P63: 1000456941 | Q63: Verizon-VCG HM Flex2.0 Contrac | R63: VZGTTQ00012094 | S63: VCG Flex (XCIO VBG CBRO) CTS TQ4164 | T63: IDE
A64: TBD | B64: TBD | C64: India | D64: PCT303 | E64: Java Springboot Microservices SpringReactive | F64: Level 3 - Premium Skills | G64: SA | H64: 24.8 | I64: 4687.2 | K64: 4218.48 | L64: 4218.48 | M64: 4218.48 | N64: 4218.48 | P64: 1000456941 | Q64: Verizon-VCG HM Flex2.0 Contrac | R64: VZGTTQ00012094 | S64: VCG Flex (XCIO VBG CBRO) CTS TQ4164 | T64: ADM
A65: TBD | B65: TBD | C65: India | D65: PCT303 | E65: Java Springboot Microservices SpringReactive | F65: Level 3 - Premium Skills | G65: SA | H65: 24.8 | I65: 4687.2 | K65: 4218.48 | L65: 4218.48 | M65: 4218.48 | N65: 4218.48 | P65: 1000456941 | Q65: Verizon-VCG HM Flex2.0 Contrac | R65: VZGTTQ00012094 | S65: VCG Flex (XCIO VBG CBRO) CTS TQ4164 | T65: ADM
A66: TBD | B66: TBD | C66: India | D66: PCT303 | E66: ReactJS | F66: Level 2 - Premium Skills | G66: A | H66: 21.3 | I66: 4025.7 | K66: 3623.13 | L66: 3623.13 | M66: 3623.13 | N66: 3623.13 | P66: 1000456941 | Q66: Verizon-VCG HM Flex2.0 Contrac | R66: VZGTTQ00012094 | S66: VCG Flex (XCIO VBG CBRO) CTS TQ4164 | T66: ADM
A67: 2399848 | B67: Mariyappan Sekar,Shruthi | C67: India | D67: PCT249 | E67: ReactJS | F67: Level 3 - Premium Skills | G67: SA | H67: 24.8 | I67: 4166.4 | J67: 4166.4 | K67: 4166.4 | L67: 4166.4 | M67: 4166.4 | N67: 4166.4 | O67: 4166.4 | P67: 1000454900 | Q67: Verizon-VCG HM OEM-Invoicing-J | R67: VZGTTQ00011403 | S67: VCG Flex (OEM Invoicing) TQ4164 CTS | T67: ADM
A68: 2418189 | B68: Giridhar Reddy | C68: India | D68: PCT249 | E68: Java Springboot Microservices SpringReactive | F68: Level 3 - Premium Skills | G68: SA | H68: 24.8 | I68: 4166.4 | J68: 4166.4 | K68: 4166.4 | L68: 4166.4 | M68: 4166.4 | N68: 4166.4 | O68: 4166.4 | P68: 1000454900 | Q68: Verizon-VCG HM OEM-Invoicing-J | R68: VZGTTQ00011404 | S68: VCG Flex (OEM Invoicing) TQ4164 CTS | T68: ADM
A69: 2415358 | B69: Makke Navya | C69: India | D69: PCT249 | E69: Java Springboot Microservices SpringReactive | F69: Level 3 - Premium Skills | G69: SA | H69: 24.8 | I69: 4687.2 | J69: 4687.2 | K69: 4687.2 | L69: 4687.2 | M69: 4687.2 | N69: 4687.2 | O69: 4687.2 | P69: 1000454900 | Q69: Verizon-VCG HM OEM-Invoicing-J | R69: VZGTTQ00011405 | S69: VCG Flex (OEM Invoicing) TQ4164 CTS | T69: ADM
A70: 554718 | B70: Karuppasamy, Saravanan | C70: Onshore Supplier Location | D70: PCT249 | E70: Full Stack | F70: Level 4 - Expert Skills | G70: SM | H70: 128 | I70: 24192 | J70: 21504 | K70: 21504 | L70: 21504 | M70: 21504 | N70: 21504 | O70: 21504 | P70: 1000454900 | Q70: Verizon-VCG HM OEM-Invoicing-J | R70: VZGTTQ00011406 | S70: VCG Flex (OEM Invoicing) TQ4164 CTS | T70: ADM
A71: 292063 | B71: Venkatesan, Damodaran | C71: India | D71: PCT249 | E71: QA Analyst | F71: Level 3 - Standard Skills | G71: SA | H71: 22.9 | I71: 4328.1 | J71: 4328.1 | K71: 4328.1 | L71: 4328.1 | M71: 4328.1 | N71: 4328.1 | O71: 4328.1 | P71: 1000454900 | Q71: Verizon-VCG HM OEM-Invoicing-J | R71: VZGTTQ00011407 | S71: VCG Flex (OEM Invoicing) TQ4164 CTS | T71: QEA
A72: 489559 | B72: Chandrasekharan, Anish Kumar | C72: India | D72: PCT249 | E72: QA Analyst | F72: Level 3 - Standard Skills | G72: M | H72: 22.9 | I72: 4328.1 | J72: 4328.1 | K72: 4328.1 | L72: 4328.1 | M72: 4328.1 | N72: 4328.1 | O72: 4328.1 | P72: 1000454900 | Q72: Verizon-VCG HM OEM-Invoicing-J | R72: VZGTTQ00011408 | S72: VCG Flex (OEM Invoicing) TQ4164 CTS | T72: QEA
A73: 2304870 | B73: Rathod, Sudhir | C73: India | D73: PCT249 | E73: Scrum Master | F73: Level 3 - Premium Skills | G73: SA | H73: 24.8 | I73: 4687.2 | J73: 4687.2 | K73: 4687.2 | L73: 4687.2 | M73: 4687.2 | N73: 4687.2 | O73: 4687.2 | P73: 1000454900 | Q73: Verizon-VCG HM OEM-Invoicing-J | R73: VZGTTQ00011409 | S73: VCG Flex (OEM Invoicing) TQ4164 CTS | T73: IOA
A74: 2417441 | B74: Chekkapalli, Satish Kumar | C74: India | D74: PCT249 | E74: Full Stack | F74: Level 3 - Premium Skills | G74: M | H74: 24.8 | I74: 4687.2 | J74: 4687.2 | K74: 4687.2 | L74: 4687.2 | M74: 4687.2 | N74: 4687.2 | O74: 4687.2 | P74: 1000454900 | Q74: Verizon-VCG HM OEM-Invoicing-J | R74: VZGTTQ00011410 | S74: VCG Flex (OEM Invoicing) TQ4164 CTS | T74: IDE
A75: 2409286 | B75: Ajay Balaji | C75: Onshore Supplier Location | D75: PCT249 | E75: ReactJS | F75: Level 3 - Premium Skills | G75: Cont | H75: 96.56 | I75: 18249.84 | J75: 16222.08 | K75: 16222.08 | L75: 16222.08 | M75: 16222.08 | N75: 16222.08 | O75: 16222.08 | P75: 1000454900 | Q75: Verizon-VCG HM OEM-Invoicing-J | R75: VZGTTQ00011411 | S75: VCG Flex (OEM Invoicing) TQ4164 CTS | T75: ADM
A76: 972854 | B76: Saravanan,Karthikeyan | C76: Onshore Supplier Location | D76: PCT249 | E76: Full Stack | F76: Level 4 - Expert Skills | G76: AD | H76: 128 | I76: 24192 | J76: 21504 | K76: 21504 | L76: 21504 | P76: 1000454900 | Q76: Verizon-VCG HM OEM-Invoicing-J | R76: VZGTTQ00011412 | S76: VCG Flex (OEM Invoicing) TQ4164 CTS | T76: IDE
A77: TBD | B77: TBD | C77: Onshore Supplier Location | D77: VBG NSA | E77: Java Springboot Microservices SpringReactive | F77: Level 3 - Premium Skills | G77: M | H77: 96.56 | I77: 16222.08 | J77: 16222.08 | K77: 16222.08 | L77: 16222.08 | M77: 16222.08 | N77: 16222.08 | O77: 16222.08 | P77: 1000458009 | Q77: Verizon-VCG HM TQ11465-VBG NSA | R77: VZGTTQ00011465 | S77: VCG Flex (VBG NSA Deepshikha) TQ4164 CTS | T77: ADM
A78: TBD | B78: TBD | C78: Onshore Supplier Location | D78: VBG NSA | E78: Java Springboot Microservices SpringReactive | F78: Level 3 - Premium Skills | G78: SA | H78: 96.56 | I78: 16222.08 | J78: 16222.08 | K78: 16222.08 | L78: 16222.08 | M78: 16222.08 | N78: 16222.08 | O78: 16222.08 | P78: 1000458009 | Q78: Verizon-VCG HM TQ11465-VBG NSA | R78: VZGTTQ00011466 | S78: VCG Flex (VBG NSA Deepshikha) TQ4164 CTS | T78: ADM
A79: TBD | B79: TBD | C79: Onshore Supplier Location | D79: VBG NSA | E79: Java Springboot Microservices SpringReactive | F79: Level 3 - Premium Skills | G79: SA | H79: 96.56 | I79: 16222.08 | J79: 16222.08 | K79: 16222.08 | L79: 16222.08 | M79: 16222.08 | N79: 16222.08 | O79: 16222.08 | P79: 1000458009 | Q79: Verizon-VCG HM TQ11465-VBG NSA | R79: VZGTTQ00011467 | S79: VCG Flex (VBG NSA Deepshikha) TQ4164 CTS | T79: ADM
A80: TBD | B80: TBD | C80: Onshore Supplier Location | D80: VBG NSA | E80: Java Springboot Microservices SpringReactive | F80: Level 4 - Expert Skills | G80: SM | H80: 128 | I80: 21504 | J80: 21504 | K80: 21504 | L80: 21504 | M80: 21504 | N80: 21504 | O80: 21504 | P80: 1000458009 | Q80: Verizon-VCG HM TQ11465-VBG NSA | R80: VZGTTQ00011468 | S80: VCG Flex (VBG NSA Deepshikha) TQ4164 CTS | T80: ADM
A81: TBD | B81: TBD | C81: Onshore Supplier Location | D81: VBG NSA | E81: Java Springboot Microservices SpringReactive | F81: Level 3 - Premium Skills | G81: M | H81: 96.56 | I81: 16222.08 | J81: 16222.08 | K81: 16222.08 | L81: 16222.08 | M81: 16222.08 | N81: 16222.08 | O81: 16222.08 | P81: 1000458009 | Q81: Verizon-VCG HM TQ11465-VBG NSA | R81: VZGTTQ00011469 | S81: VCG Flex (VBG NSA Deepshikha) TQ4164 CTS | T81: ADM
A82: TBD | B82: TBD | C82: Onshore Supplier Location | D82: VBG NSA | E82: Java Springboot Microservices SpringReactive | F82: Level 3 - Premium Skills | G82: M | H82: 96.56 | I82: 16222.08 | J82: 16222.08 | K82: 16222.08 | L82: 16222.08 | M82: 16222.08 | N82: 16222.08 | O82: 16222.08 | P82: 1000458009 | Q82: Verizon-VCG HM TQ11465-VBG NSA | R82: VZGTTQ00011470 | S82: VCG Flex (VBG NSA Deepshikha) TQ4164 CTS | T82: ADM
A83: 940159 | B83: Kopparapu, Venkata Ramana | C83: India | D83: VBG NSA | E83: Java Springboot Microservices SpringReactive | F83: Level 4 - Expert Skills | G83: SM | H83: 34.5 | I83: 5796 | J83: 5796 | K83: 5796 | L83: 5796 | M83: 5796 | N83: 5796 | O83: 5796 | P83: 1000458009 | Q83: Verizon-VCG HM TQ11465-VBG NSA | R83: VZGTTQ00011471 | S83: VCG Flex (VBG NSA Deepshikha) TQ4164 CTS | T83: VerticalCore
A84: 2391797 | B84: Verma, Amit | C84: India | D84: VBG NSA | E84: Java Springboot Microservices SpringReactive | F84: Level 3 - Premium Skills | G84: M | H84: 24.8 | I84: 4166.4 | J84: 4166.4 | K84: 4166.4 | L84: 4166.4 | M84: 4166.4 | N84: 4166.4 | O84: 4166.4 | P84: 1000458009 | Q84: Verizon-VCG HM TQ11465-VBG NSA | R84: VZGTTQ00011472 | S84: VCG Flex (VBG NSA Deepshikha) TQ4164 CTS | T84: IDE
A85: 2432275 | B85: Sachin Pokharkar | C85: India | D85: VBG NSA | E85: Java Springboot Microservices SpringReactive | F85: Level 3 - Premium Skills | G85: M | H85: 24.8 | I85: 4166.4 | J85: 4166.4 | K85: 4166.4 | L85: 4166.4 | M85: 4166.4 | N85: 4166.4 | O85: 4166.4 | P85: 1000458009 | Q85: Verizon-VCG HM TQ11465-VBG NSA | R85: VZGTTQ00011473 | S85: VCG Flex (VBG NSA Deepshikha) TQ4164 CTS | T85: IDE
A86: 2423295 | B86: Pankaj Bhaskar Jadhav - IFE BCP | C86: India | D86: VBG NSA | E86: Java Springboot Microservices SpringReactive | F86: Level 3 - Premium Skills | G86: SA | H86: 24.8 | I86: 4166.4 | J86: 4166.4 | K86: 4166.4 | L86: 4166.4 | M86: 4166.4 | N86: 4166.4 | O86: 4166.4 | P86: 1000458009 | Q86: Verizon-VCG HM TQ11465-VBG NSA | R86: VZGTTQ00011474 | S86: VCG Flex (VBG NSA Deepshikha) TQ4164 CTS | T86: IDE
A87: 2314270 | B87: Anjaneyulu Beeram | C87: India | D87: VBG NSA | E87: Java Springboot Microservices SpringReactive | F87: Level 3 - Premium Skills | G87: SA | H87: 24.8 | I87: 4166.4 | J87: 4166.4 | K87: 4166.4 | L87: 4166.4 | M87: 4166.4 | N87: 4166.4 | O87: 4166.4 | P87: 1000458009 | Q87: Verizon-VCG HM TQ11465-VBG NSA | R87: VZGTTQ00011475 | S87: VCG Flex (VBG NSA Deepshikha) TQ4164 CTS | T87: IDE
A88: 2421988 | B88: Gaikwad, Priyanka | C88: India | D88: VBG NSA | E88: Java Springboot Microservices SpringReactive | F88: Level 3 - Premium Skills | G88: SA | H88: 24.8 | I88: 4166.4 | J88: 4166.4 | K88: 4166.4 | L88: 4166.4 | M88: 4166.4 | N88: 4166.4 | O88: 4166.4 | P88: 1000458009 | Q88: Verizon-VCG HM TQ11465-VBG NSA | R88: VZGTTQ00011476 | S88: VCG Flex (VBG NSA Deepshikha) TQ4164 CTS | T88: IDE
A89: 2421456 | B89: Supriya Sagar | C89: India | D89: VBG NSA | E89: Java Springboot Microservices SpringReactive | F89: Level 3 - Premium Skills | G89: SA | H89: 24.8 | I89: 4166.4 | J89: 4166.4 | K89: 4166.4 | L89: 4166.4 | M89: 4166.4 | N89: 4166.4 | O89: 4166.4 | P89: 1000458009 | Q89: Verizon-VCG HM TQ11465-VBG NSA | R89: VZGTTQ00011477 | S89: VCG Flex (VBG NSA Deepshikha) TQ4164 CTS | T89: IDE
A90: 2422197 | B90: Priyanka Gonuguntla | C90: India | D90: VBG NSA | E90: Java Springboot Microservices SpringReactive | F90: Level 3 - Premium Skills | G90: SA | H90: 24.8 | I90: 4166.4 | J90: 4166.4 | K90: 4166.4 | L90: 4166.4 | M90: 4166.4 | N90: 4166.4 | O90: 4166.4 | P90: 1000458009 | Q90: Verizon-VCG HM TQ11465-VBG NSA | R90: VZGTTQ00011478 | S90: VCG Flex (VBG NSA Deepshikha) TQ4164 CTS | T90: IDE
A91: 2424784 | B91: Yohannan, Sobin - IFE BCP | C91: India | D91: VBG NSA | E91: Java Springboot Microservices SpringReactive | F91: Level 3 - Premium Skills | G91: SA | H91: 24.8 | I91: 4166.4 | J91: 4166.4 | K91: 4166.4 | L91: 4166.4 | M91: 4166.4 | N91: 4166.4 | O91: 4166.4 | P91: 1000458009 | Q91: Verizon-VCG HM TQ11465-VBG NSA | R91: VZGTTQ00011479 | S91: VCG Flex (VBG NSA Deepshikha) TQ4164 CTS | T91: IDE
A92: 2314997 | B92: Mangla Dubey - IFE BCP | C92: India | D92: VBG NSA | E92: Java Springboot Microservices SpringReactive | F92: Level 3 - Premium Skills | G92: SA | H92: 24.8 | I92: 4166.4 | J92: 4166.4 | K92: 4166.4 | L92: 4166.4 | M92: 4166.4 | N92: 4166.4 | O92: 4166.4 | P92: 1000458009 | Q92: Verizon-VCG HM TQ11465-VBG NSA | R92: VZGTTQ00011480 | S92: VCG Flex (VBG NSA Deepshikha) TQ4164 CTS | T92: ADM
A93: 2414207 | B93: Srinivas Yadav Ponkam - IFE BCP | C93: India | D93: VBG NSA | E93: Java Springboot Microservices SpringReactive | F93: Level 2 - Premium Skills | G93: A | H93: 21.3 | I93: 3578.4 | J93: 3578.4 | K93: 3578.4 | L93: 3578.4 | M93: 3578.4 | N93: 3578.4 | O93: 3578.4 | P93: 1000458009 | Q93: Verizon-VCG HM TQ11465-VBG NSA | R93: VZGTTQ00011481 | S93: VCG Flex (VBG NSA Deepshikha) TQ4164 CTS | T93: IDE
A94: 2421644 | B94: Jagadeshwar Keerthi | C94: India | D94: VBG NSA | E94: Java Springboot Microservices SpringReactive | F94: Level 2 - Premium Skills | G94: A | H94: 21.3 | I94: 3578.4 | J94: 3578.4 | K94: 3578.4 | L94: 3578.4 | M94: 3578.4 | N94: 3578.4 | O94: 3578.4 | P94: 1000458009 | Q94: Verizon-VCG HM TQ11465-VBG NSA | R94: VZGTTQ00011482 | S94: VCG Flex (VBG NSA Deepshikha) TQ4164 CTS | T94: IDE
... A111: 747085 | B111: Ravikumar Kongara - CXP | C111: Onshore Supplier Location | D111: ACT 220 | E111: Java Springboot Microservices SpringReactive | F111: Level 3 - Premium Skills | G111: SA | H111: 96.56 | I111: 16222.08 | J111: 16222.08 | K111: 16222.08 | L111: 16222.08 | M111: 16222.08 | N111: 16222.08 | O111: 16222.08 | P111: 1000459563 | Q111: Verizon-VCG Flex 2.0 HM Elvis | R111: VZGTTQ00011460 | S111: VCG Flex (Project Elvis) TQ4164 CTS - 2025 | T111: ADM
A112: 2385172 | B112: Muthusamy Ramasamy (Replaced by Shashank Reddy) | C112: Onshore Supplier Location | D112: ACT 220 | E112: Java Springboot Microservices SpringReactive | F112: Level 3 - Premium Skills | G112: SA | H112: 96.56 | I112: 16222.08 | J112: 16222.08 | P112: 1000459563 | Q112: Verizon-VCG Flex 2.0 HM Elvis | R112: VZGTTQ00011460 | S112: VCG Flex (Project Elvis) TQ4164 CTS - 2025 | T112: ADM
A113: 2443796 | B113: Shashank Reddy Nukala- CXP | C113: Onshore Supplier Location | D113: ACT 220 | E113: Java Springboot Microservices SpringReactive | F113: Level 3 - Premium Skills | G113: Cont | H113: 96.56 | I113: 16222.08 | K113: 16222.08 | L113: 16222.08 | M113: 16222.08 | N113: 16222.08 | O113: 16222.08 | P113: 1000459563 | Q113: Verizon-VCG Flex 2.0 HM Elvis | R113: VZGTTQ00011460 | S113: VCG Flex (Project Elvis) TQ4164 CTS - 2025 | T113: ADM
A114: 969389 | B114: Suresh Vemparala - CXP | C114: Onshore Supplier Location | D114: ACT 220 | E114: Java Springboot Microservices SpringReactive | F114: Level 3 - Premium Skills | G114: M | H114: 96.56 | I114: 16222.08 | J114: 16222.08 | K114: 16222.08 | L114: 16222.08 | M114: 16222.08 | N114: 16222.08 | O114: 16222.08 | P114: 1000459563 | Q114: Verizon-VCG Flex 2.0 HM Elvis | R114: VZGTTQ00011460 | S114: VCG Flex (Project Elvis) TQ4164 CTS - 2025 | T114: ADM
A115: 2304317 | B115: Ravi Adhikari- CXP | C115: Onshore Supplier Location | D115: ACT 220 | E115: Java Springboot Microservices SpringReactive | F115: Level 3 - Premium Skills | G115: Cont | H115: 96.56 | I115: 16222.08 | J115: 16222.08 | K115: 16222.08 | L115: 16222.08 | M115: 16222.08 | N115: 16222.08 | O115: 16222.08 | P115: 1000459563 | Q115: Verizon-VCG Flex 2.0 HM Elvis | R115: VZGTTQ00011460 | S115: VCG Flex (Project Elvis) TQ4164 CTS - 2025 | T115: ADM
A116: 148110 | B116: Someswara Rao Balam - E2E Tester | C116: Onshore Supplier Location | D116: ACT 220 | E116: QA Analyst | F116: Level 3 - Standard Skills | G116: M | H116: 91.9 | I116: 15439.2 | J116: 15439.2 | K116: 15439.2 | L116: 15439.2 | M116: 15439.2 | N116: 15439.2 | O116: 15439.2 | P116: 1000459563 | Q116: Verizon-VCG Flex 2.0 HM Elvis | R116: VZGTTQ00011460 | S116: VCG Flex (Project Elvis) TQ4164 CTS - 2025 | T116: QEA
A117: 343415 | B117: Venkata Sushma Bhuma - E2E Tester | C117: Onshore Supplier Location | D117: ACT 220 | E117: QA Analyst | F117: Level 3 - Standard Skills | G117: SA | H117: 91.9 | I117: 15439.2 | J117: 15439.2 | K117: 15439.2 | L117: 15439.2 | M117: 15439.2 | N117: 15439.2 | O117: 15439.2 | P117: 1000459563 | Q117: Verizon-VCG Flex 2.0 HM Elvis | R117: VZGTTQ00011460 | S117: VCG Flex (Project Elvis) TQ4164 CTS - 2025 | T117: QEA
A118: 844102 | B118: Lalitha Minisker - E2E Tester | C118: Onshore Supplier Location | D118: ACT 220 | E118: QA Analyst | F118: Level 3 - Standard Skills | G118: Cont | H118: 91.9 | I118: 15439.2 | J118: 15439.2 | K118: 15439.2 | L118: 15439.2 | M118: 15439.2 | N118: 15439.2 | O118: 15439.2 | P118: 1000459563 | Q118: Verizon-VCG Flex 2.0 HM Elvis | R118: VZGTTQ00011460 | S118: VCG Flex (Project Elvis) TQ4164 CTS - 2025 | T118: QEA
A119: 2319504 | B119: Bhavitha Gadiparthi - E2E Tester | C119: Onshore Supplier Location | D119: ACT 220 | E119: QA Analyst | F119: Level 3 - Standard Skills | G119: Cont | H119: 91.9 | I119: 15439.2 | J119: 15439.2 | K119: 15439.2 | L119: 15439.2 | M119: 15439.2 | N119: 15439.2 | O119: 15439.2 | P119: 1000459563 | Q119: Verizon-VCG Flex 2.0 HM Elvis | R119: VZGTTQ00011460 | S119: VCG Flex (Project Elvis) TQ4164 CTS - 2025 | T119: QEA
A120: 295426 | B120: Phayaz Shaik - E2E Tester | C120: India | D120: ACT 220 | E120: QA Analyst | F120: Level 3 - Standard Skills | G120: M | H120: 22.9 | I120: 4328.1 | J120: 4328.1 | K120: 4328.1 | L120: 4328.1 | M120: 4328.1 | N120: 4328.1 | O120: 4328.1 | P120: 1000459563 | Q120: Verizon-VCG Flex 2.0 HM Elvis | R120: VZGTTQ00011460 | S120: VCG Flex (Project Elvis) TQ4164 CTS - 2025 | T120: QEA
A121: 2239596 | B121: Krovi, Naga Venkata Sai Sudheer - E2E Tester | C121: India | D121: ACT 220 | E121: QA Analyst | F121: Level 2 - Standard Skills | G121: A | H121: 20 | I121: 3780 | J121: 3780 | K121: 3780 | L121: 3780 | M121: 3780 | N121: 3780 | O121: 3780 | P121: 1000459563 | Q121: Verizon-VCG Flex 2.0 HM Elvis | R121: VZGTTQ00011460 | S121: VCG Flex (Project Elvis) TQ4164 CTS - 2025 | T121: QEA
A122: 2150491 | B122: Kumar Jangam, Nikhil -E2E Tester | C122: India | D122: ACT 220 | E122: QA Analyst | F122: Level 2 - Standard Skills | G122: A | H122: 20 | I122: 3780 | J122: 3780 | K122: 3780 | L122: 3780 | M122: 3780 | N122: 3780 | O122: 3780 | P122: 1000459563 | Q122: Verizon-VCG Flex 2.0 HM Elvis | R122: VZGTTQ00011460 | S122: VCG Flex (Project Elvis) TQ4164 CTS - 2025 | T122: QEA
A123: 679999 | B123: S,Suganya Devi - E2E Tester | C123: India | D123: ACT 220 | E123: QA Analyst | F123: Level 2 - Standard Skills | G123: A | H123: 20 | I123: 3780 | J123: 3780 | K123: 3780 | L123: 3780 | M123: 3780 | N123: 3780 | O123: 3780 | P123: 1000459563 | Q123: Verizon-VCG Flex 2.0 HM Elvis | R123: VZGTTQ00011460 | S123: VCG Flex (Project Elvis) TQ4164 CTS - 2025 | T123: QEA
A124: 2244652 | B124: Reddy,D Sreekanth - E2E Tester | C124: India | D124: ACT 220 | E124: QA Analyst | F124: Level 2 - Standard Skills | G124: A | H124: 20 | I124: 3780 | J124: 3780 | K124: 3780 | L124: 3780 | M124: 3780 | N124: 3780 | O124: 3780 | P124: 1000459563 | Q124: Verizon-VCG Flex 2.0 HM Elvis | R124: VZGTTQ00011460 | S124: VCG Flex (Project Elvis) TQ4164 CTS - 2025 | T124: QEA
A125: 2115852 | B125: M Sujitha - E2E Tester | C125: India | D125: ACT 220 | E125: QA Analyst | F125: Level 3 - Standard Skills | G125: SA | H125: 22.9 | I125: 4328.1 | J125: 4328.1 | K125: 4328.1 | L125: 4328.1 | M125: 4328.1 | N125: 4328.1 | O125: 4328.1 | P125: 1000459563 | Q125: Verizon-VCG Flex 2.0 HM Elvis | R125: VZGTTQ00011460 | S125: VCG Flex (Project Elvis) TQ4164 CTS - 2025 | T125: QEA
... A176: 2389161 | B176: Chakka, Vishnu - PAT QA | C176: India | D176: ACT 220 | E176: QA Analyst | F176: Level 1 - Standard Skills | G176: PAT | H176: 16.3 | I176: 3080.7 | J176: 0 | K176: 0 | L176: 0 | M176: 0 | N176: 0 | O176: 0 | P176: 1000459563 | Q176: Verizon-VCG Flex 2.0 HM Elvis | R176: VZGTTQ00011460 | S176: VCG Flex (Project Elvis) TQ4164 CTS - 2025 | T176: ADM
A177: TBD | B177: TBD - PAT QA | C177: India | D177: ACT 220 | E177: QA Analyst | F177: Level 1 - Standard Skills | G177: PAT | H177: 16.3 | I177: 3080.7 | J177: 0 | K177: 0 | L177: 0 | M177: 0 | N177: 0 | O177: 0 | P177: 1000459563 | Q177: Verizon-VCG Flex 2.0 HM Elvis | R177: VZGTTQ00011460 | S177: VCG Flex (Project Elvis) TQ4164 CTS - 2025 | T177: ADM
A178: TBD | B178: TBD - PAT QA | C178: India | D178: ACT 220 | E178: QA Analyst | F178: Level 1 - Standard Skills | G178: PAT | H178: 16.3 | I178: 3080.7 | J178: 0 | K178: 0 | L178: 0 | M178: 0 | N178: 0 | O178: 0 | P178: 1000459563 | Q178: Verizon-VCG Flex 2.0 HM Elvis | R178: VZGTTQ00011460 | S178: VCG Flex (Project Elvis) TQ4164 CTS - 2025 | T178: ADM
A179: TBD | B179: TBD - PAT QA | C179: India | D179: ACT 220 | E179: QA Analyst | F179: Level 1 - Standard Skills | G179: PAT | H179: 16.3 | I179: 3080.7 | J179: 0 | K179: 0 | L179: 0 | M179: 0 | N179: 0 | O179: 0 | P179: 1000459563 | Q179: Verizon-VCG Flex 2.0 HM Elvis | R179: VZGTTQ00011460 | S179: VCG Flex (Project Elvis) TQ4164 CTS - 2025 | T179: ADM
A180: TBD | B180: TBD - PAT QA | C180: India | D180: ACT 220 | E180: QA Analyst | F180: Level 1 - Standard Skills | G180: PAT | H180: 16.3 | I180: 3080.7 | J180: 0 | K180: 0 | L180: 0 | M180: 0 | N180: 0 | O180: 0 | P180: 1000459563 | Q180: Verizon-VCG Flex 2.0 HM Elvis | R180: VZGTTQ00011460 | S180: VCG Flex (Project Elvis) TQ4164 CTS - 2025 | T180: ADM
A181: TBD | B181: TBD - PAT QA | C181: India | D181: ACT 220 | E181: QA Analyst | F181: Level 1 - Standard Skills | G181: PAT | H181: 16.3 | I181: 3080.7 | J181: 0 | K181: 0 | L181: 0 | M181: 0 | N181: 0 | O181: 0 | P181: 1000459563 | Q181: Verizon-VCG Flex 2.0 HM Elvis | R181: VZGTTQ00011460 | S181: VCG Flex (Project Elvis) TQ4164 CTS - 2025 | T181: ADM
A182: TBD | B182: TBD - PAT QA | C182: India | D182: ACT 220 | E182: QA Analyst | F182: Level 1 - Standard Skills | G182: PAT | H182: 16.3 | I182: 3080.7 | J182: 0 | K182: 0 | L182: 0 | M182: 0 | N182: 0 | O182: 0 | P182: 1000459563 | Q182: Verizon-VCG Flex 2.0 HM Elvis | R182: VZGTTQ00011460 | S182: VCG Flex (Project Elvis) TQ4164 CTS - 2025 | T182: ADM
A183: TBD | B183: TBD - PAT QA | C183: India | D183: ACT 220 | E183: QA Analyst | F183: Level 1 - Standard Skills | G183: PAT | H183: 16.3 | I183: 3080.7 | J183: 0 | K183: 0 | L183: 0 | M183: 0 | N183: 0 | O183: 0 | P183: 1000459563 | Q183: Verizon-VCG Flex 2.0 HM Elvis | R183: VZGTTQ00011460 | S183: VCG Flex (Project Elvis) TQ4164 CTS - 2025 | T183: ADM
A184: 793528 | B184: Jupally, Radhika Reddy | C184: Onshore Supplier Location | D184: ACT-199 | E184: ReactJS | F184: Level 3 - Premium Skills | G184: SA | H184: 96.56 | I184: 16222.08 | J184: 16222.08 | K184: 16222.08 | L184: 16222.08 | M184: 16222.08 | N184: 16222.08 | O184: 16222.08 | P184: 1000456932 | Q184: Verizon-VCG HM Flex 2.0 Mobile | R184: VZGTTQ00011797 | S184: VCG Flex (Mobile Offers Post Paid) TQ9703 CTS | T184: ADM
A185: 970768 | B185: Vaidya, Snehal Abhijeet | C185: Onshore Supplier Location | D185: ACT-196 | E185: QA Analyst | F185: Level 3 - Premium Skills | G185: M | H185: 96.56 | I185: 16222.08 | J185: 16222.08 | K185: 16222.08 | L185: 16222.08 | M185: 16222.08 | N185: 16222.08 | O185: 16222.08 | P185: 1000456932 | Q185: Verizon-VCG HM Flex 2.0 Mobile | R185: VZGTTQ00011797 | S185: VCG Flex (Mobile Offers Post Paid) TQ9703 CTS | T185: QEA
A186: 622443 | B186: Vijay Kumar Vadlamudi | C186: Onshore Supplier Location | D186: ACT-196 | E186: PATL | F186: Level 4 - Expert Skills | G186: AD | H186: 128 | I186: 21504 | J186: 21504 | K186: 21504 | L186: 21504 | M186: 21504 | N186: 21504 | O186: 21504 | P186: 1000456932 | Q186: Verizon-VCG HM Flex 2.0 Mobile | R186: VZGTTQ00011797 | S186: VCG Flex (Mobile Offers Post Paid) TQ9703 CTS | T186: ADM
A187: 630305 | B187: Thiyagu Rajendran | C187: Onshore Supplier Location | D187: ACT-196 | E187: Java Springboot Microservices SpringReactive | F187: Level 3 - Premium Skills | G187: M | H187: 96.56 | I187: 16222.08 | J187: 16222.08 | K187: 16222.08 | L187: 16222.08 | M187: 16222.08 | N187: 16222.08 | O187: 16222.08 | P187: 1000456932 | Q187: Verizon-VCG HM Flex 2.0 Mobile | R187: VZGTTQ00011797 | S187: VCG Flex (Mobile Offers Post Paid) TQ9703 CTS | T187: ADM
A188: 630304 | B188: Thangavel, Manikandan | C188: Onshore Supplier Location | D188: ACT-199 | E188: Java Springboot Microservices SpringReactive | F188: Level 3 - Premium Skills | G188: M | H188: 96.56 | I188: 16222.08 | J188: 16222.08 | K188: 16222.08 | L188: 16222.08 | M188: 16222.08 | N188: 16222.08 | O188: 16222.08 | P188: 1000456932 | Q188: Verizon-VCG HM Flex 2.0 Mobile | R188: VZGTTQ00011797 | S188: VCG Flex (Mobile Offers Post Paid) TQ9703 CTS | T188: ADM
A189: 913405 | B189: Gade, Sudheer Kumar | C189: Onshore Supplier Location | D189: ACT-196 | E189: PEGA | F189: Level 3 - Niche Skills | G189: Cont | H189: 98.21 | I189: 16499.28 | J189: 16499.28 | K189: 16499.28 | L189: 16499.28 | M189: 16499.28 | N189: 16499.28 | O189: 16499.28 | P189: 1000456932 | Q189: Verizon-VCG HM Flex 2.0 Mobile | R189: VZGTTQ00011797 | S189: VCG Flex (Mobile Offers Post Paid) TQ9703 CTS | T189: EPS
A190: 952674 | B190: Labib,Nehad Assad | C190: Onshore Supplier Location | D190: ACT-199 | E190: PEGA | F190: Level 4 - Expert Skills | G190: SM | H190: 128 | I190: 21504 | J190: 21504 | K190: 21504 | L190: 21504 | M190: 21504 | N190: 21504 | O190: 21504 | P190: 1000456932 | Q190: Verizon-VCG HM Flex 2.0 Mobile | R190: VZGTTQ00011797 | S190: VCG Flex (Mobile Offers Post Paid) TQ9703 CTS | T190: IDE
A191: 883179 | B191: Pottipati, Sreenadh | C191: Onshore Supplier Location | D191: ACT-115 | E191: Pro*C | F191: Level 3 - Niche Skills | G191: SA | H191: 98.21 | I191: 16499.28 | J191: 16499.28 | K191: 16499.28 | L191: 16499.28 | M191: 16499.28 | N191: 16499.28 | O191: 16499.28 | P191: 1000456932 | Q191: Verizon-VCG HM Flex 2.0 Mobile | R191: VZGTTQ00011797 | S191: VCG Flex (Mobile Offers Post Paid) TQ9703 CTS | T191: IoT
A192: 969769 | B192: Debra Burbank | C192: Onshore Supplier Location | D192: ACT125 | E192: Release Train Engineer | F192: Level 3 - Premium Skills | G192: SM | H192: 96.56 | I192: 16222.08 | J192: 16222.08 | K192: 16222.08 | L192: 16222.08 | M192: 16222.08 | N192: 16222.08 | O192: 16222.08 | P192: 1000456932 | Q192: Verizon-VCG HM Flex 2.0 Mobile | R192: VZGTTQ00011797 | S192: VCG Flex (Mobile Offers Post Paid) TQ9703 CTS | T192: ADM
A193: 2101630 | B193: Santosh Wankhade, DhanaSree | C193: India | D193: ACT-196 | E193: ReactJS | F193: Level 3 - Premium Skills | G193: A | H193: 24.8 | I193: 4687.2 | J193: 4687.2 | K193: 4687.2 | L193: 4687.2 | M193: 4687.2 | N193: 4687.2 | O193: 4687.2 | P193: 1000456932 | Q193: Verizon-VCG HM Flex 2.0 Mobile | R193: VZGTTQ00011797 | S193: VCG Flex (Mobile Offers Post Paid) TQ9703 CTS | T193: IDE
A194: 2247050 | B194: AnuMeenakshi Murugan | C194: India | D194: ACT-196 | E194: Java Springboot Microservices SpringReactive | F194: Level 3 - Premium Skills | G194: M | H194: 24.8 | I194: 4687.2 | J194: 4687.2 | K194: 4687.2 | L194: 4687.2 | M194: 4687.2 | N194: 4687.2 | O194: 4687.2 | P194: 1000456932 | Q194: Verizon-VCG HM Flex 2.0 Mobile | R194: VZGTTQ00011797 | S194: VCG Flex (Mobile Offers Post Paid) TQ9703 CTS | T194: ADM
A195: 2018995 | B195: Parameshwari Periyasamy | C195: India | D195: ACT-199 | E195: Java Springboot Microservices SpringReactive | F195: Level 3 - Premium Skills | G195: SA | H195: 24.8 | I195: 4687.2 | J195: 4687.2 | K195: 4687.2 | L195: 4687.2 | M195: 4687.2 | N195: 4687.2 | O195: 4687.2 | P195: 1000456932 | Q195: Verizon-VCG HM Flex 2.0 Mobile | R195: VZGTTQ00011797 | S195: VCG Flex (Mobile Offers Post Paid) TQ9703 CTS | T195: ADM
... A246: 703821 | B246: Vithanala, Janaki Ramudu | C246: Onshore Supplier Location | D246: PCT 143 | E246: Java Springboot Microservices SpringReactive | F246: Level 3 - Premium Skills | G246: M | H246: 96.56 | I246: 16222.08 | J246: 16222.08 | K246: 16222.08 | L246: 16222.08 | M246: 16222.08 | N246: 16222.08 | O246: 16222.08 | P246: 1000456896 | Q246: Verizon-VCG HM Flex2.0 One Mes | R246: VZGTTQ00009022 | S246: VCG Flex (VBG One Message AEM Migration) TQ4164 CTS | T246: ADM
A247: TBD | B247: TBD | C247: Onshore Supplier Location | D247: PCT 143 | E247: Java Springboot Microservices SpringReactive | F247: Level 4 - Expert Skills | G247: AD | H247: 128 | I247: 24192 | J247: 24192 | K247: 24192 | L247: 24192 | M247: 24192 | N247: 24192 | O247: 24192 | P247: 1000456896 | Q247: Verizon-VCG HM Flex2.0 One Mes | R247: VZGTTQ00009022 | S247: VCG Flex (VBG One Message AEM Migration) TQ4164 CTS | T247: ADM
A248: 2397455 | B248: Prakash D | C248: Onshore Supplier Location | D248: PCT 143 | E248: Architect | F248: Level 4 - Expert Skills | G248: Cont | H248: 128 | I248: 21504 | J248: 21504 | K248: 21504 | L248: 21504 | M248: 21504 | N248: 21504 | O248: 21504 | P248: 1000456896 | Q248: Verizon-VCG HM Flex2.0 One Mes | R248: VZGTTQ00009022 | S248: VCG Flex (VBG One Message AEM Migration) TQ4164 CTS | T248: ADM
...

Sheet 1000458637 - Anto
A1: Verizon Senior Director (USA) | C1: Brian Hurd
A2: Verizon Senior Director (India) | C2: Mangala Seetharaman
A3: Verizon PATL (Onshore) Verizon PATL (Offshore) | C3: Harini Kattekola , Senthilkumar Chellasamy / Anto Giscard , Hari kumar
A4: Verizon TQ ID | C4: VZGTTQ00011938
A5: Verzion TQ Description | C5: VCG VZI_Plans ,Perks& Service Offers_CTS_Samta
A6: Cognizant POC | C6: Srinivasan K
P7: 2026 - Q1 - Quarter | S7: 2026 - Q2 - Quarter | V7: 2026 - Q3 - Quarter | Y7: 2026 - Q4 - Quarter
A8: EmpID | B8: Name | C8: Location | D8: ACT/PCT | E8: Skill Set | F8: Verizon Level Mapping | G8: Classification | H8: Key | I8: Cognizant Designation | J8: ESA ID | K8: ESA Description | L8: Service Line | M8: Hourly Rate (Rs) | N8: Hourly Rate ($) | O8: Monthly Rate ($) | P8: 46023 | Q8: 46054 | R8: 46082 | S8: 46113 | T8: 46143 | U8: 46174 | V8: 46204 | W8: 46235 | X8: 46266 | Y8: 46296 | Z8: 46327 | AA8: 46357 | AB8: Q1 Burn | AC8: Q2 Burn | AD8: Q3 Burn | AE8: Q4 Burn | AF8: H1 Burn | AG8: H2 Burn Total | AH8: 2026 Burn | AI8: Comments
A9: 2298348 | B9: Kalaiselvan Ganesan | C9: ODC | D9: ACT 200 | E9: Java Springboot Microservices SpringReactive | F9: Level 3 | G9: Premium | H9: =CONCATENATE(G9,C9,F9) -> PremiumODCLevel 3 | I9: SA | J9: 1000471622 | K9: Verizon-Verizon Flex - H&M -VZ | L9: IDE | P9: =N9*176 -> 0 | Q9: =N9*176 -> 0 | R9: =N9*176 -> 0 | S9: 0 | T9: 0 | U9: 0 | V9: 0 | W9: 0 | X9: 0 | Y9: 0 | Z9: 0 | AA9: 0 | AB9: =SUM(P9:R9) -> 0 | AC9: =SUM(S9:U9) -> 0 | AD9: =SUM(V9:X9) -> 0 | AE9: =SUM(Y9:AA9) -> 0 | AF9: =SUM(AB9:AC9) -> 0 | AG9: =SUM(AD9:AE9) -> 0 | AH9: =SUM(AF9:AG9) -> 0
A10: 630149 | B10: Vasu Gattu | C10: ODC | D10: ACT 200 | E10: QA Analyst | F10: Level 3 | G10: Standard | H10: =CONCATENATE(G10,C10,F10) -> StandardODCLevel 3 | I10: SA | J10: 1000471622 | K10: Verizon-Verizon Flex - H&M -VZ | L10: QEA | P10: =N10*176 -> 0 | Q10: =N10*176 -> 0 | R10: =N10*176 -> 0 | S10: 0 | T10: 0 | U10: 0 | V10: 0 | W10: 0 | X10: 0 | Y10: 0 | Z10: 0 | AA10: 0 | AB10: =SUM(P10:R10) -> 0 | AC10: =SUM(S10:U10) -> 0 | AD10: =SUM(V10:X10) -> 0 | AE10: =SUM(Y10:AA10) -> 0 | AF10: =SUM(AB10:AC10) -> 0 | AG10: =SUM(AD10:AE10) -> 0 | AH10: =SUM(AF10:AG10) -> 0
A11: 2254287 | B11: Manoj Kumar P | C11: ODC | D11: ACT 200 | E11: Release Train Engineer | F11: Level 2 | G11: Standard | H11: =CONCATENATE(G11,C11,F11) -> StandardODCLevel 2 | I11: SA | J11: 1000471622 | K11: Verizon-Verizon Flex - H&M -VZ | L11: IOT | P11: =N11*176 -> 0 | Q11: =N11*176 -> 0 | R11: =N11*176 -> 0 | S11: 0 | T11: 0 | U11: 0 | V11: 0 | W11: 0 | X11: 0 | Y11: 0 | Z11: 0 | AA11: 0 | AB11: =SUM(P11:R11) -> 0 | AC11: =SUM(S11:U11) -> 0 | AD11: =SUM(V11:X11) -> 0 | AE11: =SUM(Y11:AA11) -> 0 | AF11: =SUM(AB11:AC11) -> 0 | AG11: =SUM(AD11:AE11) -> 0 | AH11: =SUM(AF11:AG11) -> 0
A12: 560353 | B12: Ramamoorthy Swetha | C12: ODC | D12: ACT 200 | E12: Java Springboot Microservices SpringReactive | F12: Level 3 | G12: Premium | H12: =CONCATENATE(G12,C12,F12) -> PremiumODCLevel 3 | I12: M | J12: 1000471622 | K12: Verizon-Verizon Flex - H&M -VZ | L12: ADM | P12: =N12*176 -> 0 | Q12: =N12*176 -> 0 | R12: =N12*176 -> 0 | S12: 0 | T12: 0 | U12: 0 | V12: 0 | W12: 0 | X12: 0 | Y12: 0 | Z12: 0 | AA12: 0 | AB12: =SUM(P12:R12) -> 0 | AC12: =SUM(S12:U12) -> 0 | AD12: =SUM(V12:X12) -> 0 | AE12: =SUM(Y12:AA12) -> 0 | AF12: =SUM(AB12:AC12) -> 0 | AG12: =SUM(AD12:AE12) -> 0 | AH12: =SUM(AF12:AG12) -> 0
A13: 2359998 | B13: Gnanasundaram M | C13: ODC | D13: ACT 200 | E13: ReactJS | F13: Level 3 | G13: Premium | H13: =CONCATENATE(G13,C13,F13) -> PremiumODCLevel 3 | I13: SA | J13: 1000471622 | K13: Verizon-Verizon Flex - H&M -VZ | L13: ADM | P13: =N13*176 -> 0 | Q13: =N13*176 -> 0 | R13: =N13*176 -> 0 | S13: 0 | T13: 0 | U13: 0 | V13: 0 | W13: 0 | X13: 0 | Y13: 0 | Z13: 0 | AA13: 0 | AB13: =SUM(P13:R13) -> 0 | AC13: =SUM(S13:U13) -> 0 | AD13: =SUM(V13:X13) -> 0 | AE13: =SUM(Y13:AA13) -> 0 | AF13: =SUM(AB13:AC13) -> 0 | AG13: =SUM(AD13:AE13) -> 0 | AH13: =SUM(AF13:AG13) -> 0
A14: 2175721 | B14: Phani kumar, Prudhivi M | C14: ODC | D14: ACT 200 | E14: ReactJS | F14: Level 3 | G14: Premium | H14: =CONCATENATE(G14,C14,F14) -> PremiumODCLevel 3 | I14: SA | J14: 1000471622 | K14: Verizon-Verizon Flex - H&M -VZ | L14: IDE | P14: =N14*176 -> 0 | Q14: =N14*176 -> 0 | R14: =N14*176 -> 0 | S14: 0 | T14: 0 | U14: 0 | V14: 0 | W14: 0 | X14: 0 | Y14: 0 | Z14: 0 | AA14: 0 | AB14: =SUM(P14:R14) -> 0 | AC14: =SUM(S14:U14) -> 0 | AD14: =SUM(V14:X14) -> 0 | AE14: =SUM(Y14:AA14) -> 0 | AF14: =SUM(AB14:AC14) -> 0 | AG14: =SUM(AD14:AE14) -> 0 | AH14: =SUM(AF14:AG14) -> 0
A15: 2018995 | B15: Parameshwari Periyasamy | C15: ODC | D15: ACT 199 | E15: Java Springboot Microservices SpringReactive | F15: Level 3 | G15: Premium | H15: =CONCATENATE(G15,C15,F15) -> PremiumODCLevel 3 | I15: SA | J15: 1000471622 | K15: Verizon-Verizon Flex - H&M -VZ | L15: ADM | P15: =N15*176 -> 0 | Q15: =N15*176 -> 0 | R15: =N15*176 -> 0 | S15: 0 | T15: 0 | U15: 0 | V15: 0 | W15: 0 | X15: 0 | Y15: 0 | Z15: 0 | AA15: 0 | AB15: =SUM(P15:R15) -> 0 | AC15: =SUM(S15:U15) -> 0 | AD15: =SUM(V15:X15) -> 0 | AE15: =SUM(Y15:AA15) -> 0 | AF15: =SUM(AB15:AC15) -> 0 | AG15: =SUM(AD15:AE15) -> 0 | AH15: =SUM(AF15:AG15) -> 0
A16: 2074327 | B16: P V, Saicharan | C16: ODC | D16: ACT 199 | E16: PTL | F16: Level 3 | G16: Standard | H16: =CONCATENATE(G16,C16,F16) -> StandardODCLevel 3 | I16: M | J16: 1000471622 | K16: Verizon-Verizon Flex - H&M -VZ | L16: ADM | P16: =N16*176 -> 0 | Q16: =N16*176 -> 0 | R16: =N16*176 -> 0 | S16: 0 | T16: 0 | U16: 0 | V16: 0 | W16: 0 | X16: 0 | Y16: 0 | Z16: 0 | AA16: 0 | AB16: =SUM(P16:R16) -> 0 | AC16: =SUM(S16:U16) -> 0 | AD16: =SUM(V16:X16) -> 0 | AE16: =SUM(Y16:AA16) -> 0 | AF16: =SUM(AB16:AC16) -> 0 | AG16: =SUM(AD16:AE16) -> 0 | AH16: =SUM(AF16:AG16) -> 0
A17: 686399 | B17: Dheepak Kumar Sathyamurthy | C17: ODC | D17: ACT 199 | E17: Java Springboot Microservices SpringReactive | F17: Level 3 | G17: Premium | H17: =CONCATENATE(G17,C17,F17) -> PremiumODCLevel 3 | I17: SA | J17: 1000471622 | K17: Verizon-Verizon Flex - H&M -VZ | L17: IDE | P17: =N17*176 -> 0 | Q17: =N17*176 -> 0 | R17: =N17*176 -> 0 | S17: 0 | T17: 0 | U17: 0 | V17: 0 | W17: 0 | X17: 0 | Y17: 0 | Z17: 0 | AA17: 0 | AB17: =SUM(P17:R17) -> 0 | AC17: =SUM(S17:U17) -> 0 | AD17: =SUM(V17:X17) -> 0 | AE17: =SUM(Y17:AA17) -> 0 | AF17: =SUM(AB17:AC17) -> 0 | AG17: =SUM(AD17:AE17) -> 0 | AH17: =SUM(AF17:AG17) -> 0
A18: 2271407 | B18: Vijay V | C18: ODC | D18: ACT 199 | E18: QA Analyst | F18: Level 1 | G18: Standard | H18: =CONCATENATE(G18,C18,F18) -> StandardODCLevel 1 | I18: PA | J18: 1000471622 | K18: Verizon-Verizon Flex - H&M -VZ | L18: QEA | P18: =N18*176 -> 0 | Q18: =N18*176 -> 0 | R18: =N18*176 -> 0 | S18: 0 | T18: 0 | U18: 0 | V18: 0 | W18: 0 | X18: 0 | Y18: 0 | Z18: 0 | AA18: 0 | AB18: =SUM(P18:R18) -> 0 | AC18: =SUM(S18:U18) -> 0 | AD18: =SUM(V18:X18) -> 0 | AE18: =SUM(Y18:AA18) -> 0 | AF18: =SUM(AB18:AC18) -> 0 | AG18: =SUM(AD18:AE18) -> 0 | AH18: =SUM(AF18:AG18) -> 0
A19: 2160943 | B19: Manda Sai Sravanth | C19: ODC | D19: ACT 199 | E19: QA Analyst | F19: Level 2 | G19: Standard | H19: =CONCATENATE(G19,C19,F19) -> StandardODCLevel 2 | I19: A | J19: 1000471622 | K19: Verizon-Verizon Flex - H&M -VZ | L19: QEA | P19: =N19*176 -> 0 | Q19: =N19*176 -> 0 | R19: =N19*176 -> 0 | S19: 0 | T19: 0 | U19: 0 | V19: 0 | W19: 0 | X19: 0 | Y19: 0 | Z19: 0 | AA19: 0 | AB19: =SUM(P19:R19) -> 0 | AC19: =SUM(S19:U19) -> 0 | AD19: =SUM(V19:X19) -> 0 | AE19: =SUM(Y19:AA19) -> 0 | AF19: =SUM(AB19:AC19) -> 0 | AG19: =SUM(AD19:AE19) -> 0 | AH19: =SUM(AF19:AG19) -> 0
A20: 2067572 | B20: Sarath Babu | C20: ODC | D20: ACT 199 | E20: Java Springboot Microservices SpringReactive | F20: Level 3 | G20: Premium | H20: =CONCATENATE(G20,C20,F20) -> PremiumODCLevel 3 | I20: SA | J20: 1000471622 | K20: Verizon-Verizon Flex - H&M -VZ | L20: IDE | P20: =N20*176 -> 0 | Q20: =N20*176 -> 0 | R20: =N20*176 -> 0 | S20: 0 | T20: 0 | U20: 0 | V20: 0 | W20: 0 | X20: 0 | Y20: 0 | Z20: 0 | AA20: 0 | AB20: =SUM(P20:R20) -> 0 | AC20: =SUM(S20:U20) -> 0 | AD20: =SUM(V20:X20) -> 0 | AE20: =SUM(Y20:AA20) -> 0 | AF20: =SUM(AB20:AC20) -> 0 | AG20: =SUM(AD20:AE20) -> 0 | AH20: =SUM(AF20:AG20) -> 0
... A45: 2387626 | B45: Kamna Bhuvan | C45: ODC | D45: ACT 116 | E45: Java Springboot Microservices SpringReactive | F45: Level 3 | G45: Premium | H45: =CONCATENATE(G45,C45,F45) -> PremiumODCLevel 3 | I45: M | J45: 1000459566 | K45: Verizon VCG Flex 2.0 HM Strate | L45: ADM | P45: =N45*176 -> 0 | Q45: =N45*176 -> 0 | R45: =N45*176 -> 0 | S45: 0 | T45: 0 | U45: 0 | V45: 0 | W45: 0 | X45: 0 | Y45: 0 | Z45: 0 | AA45: 0 | AB45: =SUM(P45:R45) -> 0 | AC45: =SUM(S45:U45) -> 0 | AD45: =SUM(V45:X45) -> 0 | AE45: =SUM(Y45:AA45) -> 0 | AF45: =SUM(AB45:AC45) -> 0 | AG45: =SUM(AD45:AE45) -> 0 | AH45: =SUM(AF45:AG45) -> 0
A46: Total | P46: =SUM(P9:P45) -> 0 | Q46: =SUM(Q9:Q45) -> 0 | R46: =SUM(R9:R45) -> 0 | S46: =SUM(S9:S45) -> 0 | T46: =SUM(T9:T45) -> 0 | U46: =SUM(U9:U45) -> 0 | V46: =SUM(V9:V45) -> 0 | W46: =SUM(W9:W45) -> 0 | ... AH46: =SUM(AH9:AH45) -> 0
A47: LOE Value | P47: =P46*90% -> 0 | Q47: =Q46*90% -> 0 | R47: =R46*90% -> 0 | S47: =S46*90% -> 0 | T47: =T46*90% -> 0 | U47: =U46*90% -> 0 | V47: =V46*90% -> 0 | W47: =W46*90% -> 0 | ... AH47: =AH46*90% -> 0
A48: UPT Value | P48: =P47*94.15% -> 0 | Q48: =Q47*94.15% -> 0 | R48: =R47*94.15% -> 0 | S48: =S46*84.15% -> 0 | T48: =T46*84.15% -> 0 | U48: =U46*84.15% -> 0 | V48: =V46*84.15% -> 0 | W48: =W46*84.15% -> 0 | X48: =X46*84.15% -> 0 | Y48: =Y46*84.15% -> 0 | Z48: =Z46*84.15% -> 0 | AA48: =AA46*84.15% -> 0 | AB48: =AB47*94.15% -> 0 | AC48: =AC46*84.15% -> 0 | AD48: =AD46*84.15% -> 0 | AE48: =AE46*84.15% -> 0 | AF48: =AF47*94.15% -> 0 | AG48: =AG46*84.15% -> 0 | AH48: =AH47*94.15% -> 0
P50: 131063
P51: =P47-P50 -> -131063
R55: =SUM(S46:U46) -> 0 | X55: =SUM(Y46:AA46) -> 0
R56: =R55*10% -> 0 | X56: =X55*10% -> 0
R57: =R55-R56 -> 0 | X57: =X55-X56 -> 0

Sheet 1000458649 - Arun Prakash
A1: Verizon Senior Director (USA) | C1: Brian Hurd
A2: Verizon Senior Director (India) | C2: Mangala Seetharaman
A3: Verizon PATL (Onshore) Verizon PATL (Offshore) | C3: Seldon Jones / Arun Prakash
A4: Verizon TQ ID | C4: VZGTTQ00011836
A5: Verzion TQ Description | C5: VCG VZI_Device & Accessory/ Consumer Products/ MarketingAutomation_CTS_Arun
A6: Cognizant POC | C6: JOHN RAJ, Isaiah Ranjith Kumar
G7: ` | P7: 2026 - Q1 - Quarter | S7: 2026 - Q2 - Quarter | V7: 2026 - Q3 - Quarter | Y7: 2026 - Q4 - Quarter
A8: EmpID | B8: Name | C8: Location | D8: ACT/PCT | E8: Skill Set | F8: Verizon Level Mapping | G8: Classification | H8: Key | I8: Cognizant Designation | J8: ESA ID | K8: ESA Description | L8: Service Line | M8: Hourly Rate (Rs) | N8: Hourly Rate ($) | O8: Monthly Rate ($) | P8: 46023 | Q8: 46054 | R8: 46082 | S8: 46113 | T8: 46143 | U8: 46174 | V8: 46204 | W8: 46235 | X8: 46266 | Y8: 46296 | Z8: 46327 | AA8: 46357 | AB8: Q1 Burn | AC8: Q2 Burn | AD8: Q3 Burn | AE8: Q4 Burn | AF8: H1 Burn | AG8: H2 Burn Total | AH8: 2026 Burn | AI8: Comments | AJ8: c
A9: 2081055 | B9: Gadiraju,Yugala | C9: ODC | D9: ACT234 | E9: Java Springboot Microservices SpringReactive | F9: Level 3 | G9: Premium | H9: =CONCATENATE(G9,C9,F9) -> PremiumODCLevel 3 | I9: A | J9: 1000458649 | K9: VDSI-Flex-H&M-Marketing Produc | L9: ADM | P9: =N9*176 -> 0 | Q9: =N9*176 -> 0 | R9: =N9*176 -> 0 | S9: 0 | T9: 0 | U9: 0 | V9: 0 | W9: 0 | X9: 0 | Y9: 0 | Z9: 0 | AA9: 0 | AB9: =SUM(P9:R9) -> 0 | AC9: =SUM(S9:U9) -> 0 | AD9: =SUM(V9:X9) -> 0 | AE9: =SUM(Y9:AA9) -> 0 | AF9: =SUM(AB9:AC9) -> 0 | AG9: =SUM(AD9:AE9) -> 0 | AH9: =SUM(AF9:AG9) -> 0 | AJ9: 2081055
A10: 2087175 | B10: Raju,Sri Vandhana | C10: ODC | D10: ACT260 | E10: Java Springboot Microservices SpringReactive | F10: Level 2 | G10: Premium | H10: =CONCATENATE(G10,C10,F10) -> PremiumODCLevel 2 | I10: A | J10: 1000458649 | K10: VDSI-Flex-H&M-Marketing Produc | L10: ADM | P10: =N10*176 -> 0 | Q10: =N10*176 -> 0 | R10: =N10*176 -> 0 | S10: 0 | T10: 0 | U10: 0 | V10: 0 | W10: 0 | X10: 0 | Y10: 0 | Z10: 0 | AA10: 0 | AB10: =SUM(P10:R10) -> 0 | AC10: =SUM(S10:U10) -> 0 | AD10: =SUM(V10:X10) -> 0 | AE10: =SUM(Y10:AA10) -> 0 | AF10: =SUM(AB10:AC10) -> 0 | AG10: =SUM(AD10:AE10) -> 0 | AH10: =SUM(AF10:AG10) -> 0 | AJ10: 2087175
A11: 2112043 | B11: Rathore,Anshika | C11: ODC | D11: ACT234 | E11: QA Analyst | F11: Level 1 | G11: Standard | H11: =CONCATENATE(G11,C11,F11) -> StandardODCLevel 1 | I11: PA | J11: 1000458649 | K11: VDSI-Flex-H&M-Marketing Produc | L11: QEA | P11: =N11*176 -> 0 | Q11: =N11*176 -> 0 | R11: =N11*176 -> 0 | S11: 0 | T11: 0 | U11: 0 | V11: 0 | W11: 0 | X11: 0 | Y11: 0 | Z11: 0 | AA11: 0 | AB11: =SUM(P11:R11) -> 0 | AC11: =SUM(S11:U11) -> 0 | AD11: =SUM(V11:X11) -> 0 | AE11: =SUM(Y11:AA11) -> 0 | AF11: =SUM(AB11:AC11) -> 0 | AG11: =SUM(AD11:AE11) -> 0 | AH11: =SUM(AF11:AG11) -> 0 | AJ11: 2112043
A12: 2166013 | B12: Doke,Trushant Sadashiv | C12: ODC | D12: ACT234 | E12: ReactJS | F12: Level 3 | G12: Premium | H12: =CONCATENATE(G12,C12,F12) -> PremiumODCLevel 3 | I12: M | J12: 1000458649 | K12: VDSI-Flex-H&M-Marketing Produc | L12: IDE | P12: =N12*176 -> 0 | Q12: =N12*176 -> 0 | R12: =N12*176 -> 0 | S12: 0 | T12: 0 | U12: 0 | V12: 0 | W12: 0 | X12: 0 | Y12: 0 | Z12: 0 | AA12: 0 | AB12: =SUM(P12:R12) -> 0 | AC12: =SUM(S12:U12) -> 0 | AD12: =SUM(V12:X12) -> 0 | AE12: =SUM(Y12:AA12) -> 0 | AF12: =SUM(AB12:AC12) -> 0 | AG12: =SUM(AD12:AE12) -> 0 | AH12: =SUM(AF12:AG12) -> 0 | AJ12: 2166013
A13: 2177358 | B13: R,Praveen Kumar | C13: ODC | D13: ACT211 | E13: ReactJS | F13: Level 3 | G13: Premium | H13: =CONCATENATE(G13,C13,F13) -> PremiumODCLevel 3 | I13: SA | J13: 1000458649 | K13: VDSI-Flex-H&M-Marketing Produc | L13: ADM | P13: =N13*176 -> 0 | Q13: =N13*176 -> 0 | R13: =N13*176 -> 0 | S13: 0 | T13: 0 | U13: 0 | V13: 0 | W13: 0 | X13: 0 | Y13: 0 | Z13: 0 | AA13: 0 | AB13: =SUM(P13:R13) -> 0 | AC13: =SUM(S13:U13) -> 0 | AD13: =SUM(V13:X13) -> 0 | AE13: =SUM(Y13:AA13) -> 0 | AF13: =SUM(AB13:AC13) -> 0 | AG13: =SUM(AD13:AE13) -> 0 | AH13: =SUM(AF13:AG13) -> 0 | AJ13: 2177358
A14: 2230389 | B14: R,Priyanka | C14: ODC | D14: ACT260 | E14: QA Analyst | F14: Level 1 | G14: Standard | H14: =CONCATENATE(G14,C14,F14) -> StandardODCLevel 1 | I14: PA | J14: 1000458649 | K14: VDSI-Flex-H&M-Marketing Produc | L14: QEA | P14: =N14*176 -> 0 | Q14: =N14*176 -> 0 | R14: =N14*176 -> 0 | S14: 0 | T14: 0 | U14: 0 | V14: 0 | W14: 0 | X14: 0 | Y14: 0 | Z14: 0 | AA14: 0 | AB14: =SUM(P14:R14) -> 0 | AC14: =SUM(S14:U14) -> 0 | AD14: =SUM(V14:X14) -> 0 | AE14: =SUM(Y14:AA14) -> 0 | AF14: =SUM(AB14:AC14) -> 0 | AG14: =SUM(AD14:AE14) -> 0 | AH14: =SUM(AF14:AG14) -> 0 | AJ14: 2230389
A15: 2257652 | B15: Y,Sujatha | C15: ODC | D15: ACT125 | E15: Java Springboot Microservices SpringReactive | F15: Level 3 | G15: Premium | H15: =CONCATENATE(G15,C15,F15) -> PremiumODCLevel 3 | I15: SA | J15: 1000458649 | K15: VDSI-Flex-H&M-Marketing Produc | L15: IDE | P15: =N15*176 -> 0 | Q15: =N15*176 -> 0 | R15: =N15*176 -> 0 | S15: 0 | T15: 0 | U15: 0 | V15: 0 | W15: 0 | X15: 0 | Y15: 0 | Z15: 0 | AA15: 0 | AB15: =SUM(P15:R15) -> 0 | AC15: =SUM(S15:U15) -> 0 | AD15: =SUM(V15:X15) -> 0 | AE15: =SUM(Y15:AA15) -> 0 | AF15: =SUM(AB15:AC15) -> 0 | AG15: =SUM(AD15:AE15) -> 0 | AH15: =SUM(AF15:AG15) -> 0 | AJ15: 2257652
A16: 2434889 | B16: N,Vaishnavi | C16: ODC | D16: PCT248 | E16: QA Analyst | F16: Level 3 | G16: Standard | H16: =CONCATENATE(G16,C16,F16) -> StandardODCLevel 3 | I16: M | J16: 1000458649 | K16: VDSI-Flex-H&M-Marketing Produc | L16: ADM | P16: =N16*176 -> 0 | Q16: =N16*176 -> 0 | R16: =N16*176 -> 0 | S16: 0 | T16: 0 | U16: 0 | V16: 0 | W16: 0 | X16: 0 | Y16: 0 | Z16: 0 | AA16: 0 | AB16: =SUM(P16:R16) -> 0 | AC16: =SUM(S16:U16) -> 0 | AD16: =SUM(V16:X16) -> 0 | AE16: =SUM(Y16:AA16) -> 0 | AF16: =SUM(AB16:AC16) -> 0 | AG16: =SUM(AD16:AE16) -> 0 | AH16: =SUM(AF16:AG16) -> 0 | AJ16: 2434889
A17: 2284572 | B17: Rajapandi,Niverlin | C17: ODC | D17: PCT054 | E17: Java Springboot Microservices SpringReactive | F17: Level 1 | G17: Premium | H17: =CONCATENATE(G17,C17,F17) -> PremiumODCLevel 1 | I17: PA | J17: 1000458649 | K17: VDSI-Flex-H&M-Marketing Produc | L17: ADM | P17: =N17*176 -> 0 | Q17: =N17*176 -> 0 | R17: =N17*176 -> 0 | S17: 0 | T17: 0 | U17: 0 | V17: 0 | W17: 0 | X17: 0 | Y17: 0 | Z17: 0 | AA17: 0 | AB17: =SUM(P17:R17) -> 0 | AC17: =SUM(S17:U17) -> 0 | AD17: =SUM(V17:X17) -> 0 | AE17: =SUM(Y17:AA17) -> 0 | AF17: =SUM(AB17:AC17) -> 0 | AG17: =SUM(AD17:AE17) -> 0 | AH17: =SUM(AF17:AG17) -> 0 | AJ17: #N/A
A18: 169770 | B18: Sampath,Gokulakrishnan | C18: ODC | D18: PCT246 - CPI 2.0 | E18: Java Springboot Microservices SpringReactive | F18: Level 3 | G18: Premium | H18: =CONCATENATE(G18,C18,F18) -> PremiumODCLevel 3 | I18: SM | J18: 1000458649 | K18: VDSI-Flex-H&M-Marketing Produc | L18: ADM | P18: =N18*176 -> 0 | Q18: =N18*176 -> 0 | R18: =N18*176 -> 0 | S18: 0 | T18: 0 | U18: 0 | V18: 0 | W18: 0 | X18: 0 | Y18: 0 | Z18: 0 | AA18: 0 | AB18: =SUM(P18:R18) -> 0 | AC18: =SUM(S18:U18) -> 0 | AD18: =SUM(V18:X18) -> 0 | AE18: =SUM(Y18:AA18) -> 0 | AF18: =SUM(AB18:AC18) -> 0 | AG18: =SUM(AD18:AE18) -> 0 | AH18: =SUM(AF18:AG18) -> 0 | AJ18: 169770
A19: 265354 | B19: JOHN RAJ,Isaiah Ranjith Kumar | C19: ODC | D19: ACT260 | E19: Java Springboot Microservices SpringReactive | F19: Level 4 | G19: Expert | H19: =CONCATENATE(G19,C19,F19) -> ExpertODCLevel 4 | I19: AD | J19: 1000458649 | K19: VDSI-Flex-H&M-Marketing Produc | L19: ADM | P19: =N19*176 -> 0 | Q19: =N19*176 -> 0 | R19: =N19*176 -> 0 | S19: 0 | T19: 0 | U19: 0 | V19: 0 | W19: 0 | X19: 0 | Y19: 0 | Z19: 0 | AA19: 0 | AB19: =SUM(P19:R19) -> 0 | AC19: =SUM(S19:U19) -> 0 | AD19: =SUM(V19:X19) -> 0 | AE19: =SUM(Y19:AA19) -> 0 | AF19: =SUM(AB19:AC19) -> 0 | AG19: =SUM(AD19:AE19) -> 0 | AH19: =SUM(AF19:AG19) -> 0 | AJ19: 265354
A20: 862952 | B20: Sathiamurthy,Vikraman | C20: ODC | D20: ACT211 | E20: Java Springboot Microservices SpringReactive | F20: Level 3 | G20: Premium | H20: =CONCATENATE(G20,C20,F20) -> PremiumODCLevel 3 | I20: M | J20: 1000458649 | K20: VDSI-Flex-H&M-Marketing Produc | L20: ADM | P20: =N20*176 -> 0 | Q20: =N20*176 -> 0 | R20: =N20*176 -> 0 | S20: 0 | T20: 0 | U20: 0 | V20: 0 | W20: 0 | X20: 0 | Y20: 0 | Z20: 0 | AA20: 0 | AB20: =SUM(P20:R20) -> 0 | AC20: =SUM(S20:U20) -> 0 | AD20: =SUM(V20:X20) -> 0 | AE20: =SUM(Y20:AA20) -> 0 | AF20: =SUM(AB20:AC20) -> 0 | AG20: =SUM(AD20:AE20) -> 0 | AH20: =SUM(AF20:AG20) -> 0 | AJ20: 862952
A21: 894318 | B21: Aradadi,Likhithanjali | C21: ODC | D21: ACT260 | E21: Java Springboot Microservices SpringReactive | F21: Level 2 | G21: Premium | H21: =CONCATENATE(G21,C21,F21) -> PremiumODCLevel 2 | I21: A | J21: 1000458649 | K21: VDSI-Flex-H&M-Marketing Produc | L21: ADM | P21: =N21*176 -> 0 | Q21: =N21*176 -> 0 | R21: =N21*176 -> 0 | S21: 0 | T21: 0 | U21: 0 | V21: 0 | W21: 0 | X21: 0 | Y21: 0 | Z21: 0 | AA21: 0 | AB21: =SUM(P21:R21) -> 0 | AC21: =SUM(S21:U21) -> 0 | AD21: =SUM(V21:X21) -> 0 | AE21: =SUM(Y21:AA21) -> 0 | AF21: =SUM(AB21:AC21) -> 0 | AG21: =SUM(AD21:AE21) -> 0 | AH21: =SUM(AF21:AG21) -> 0 | AJ21: 894318
A22: 2252709 | B22: Kulkarni, Abhishek | C22: ODC | D22: ACT234 | E22: Java Springboot Microservices SpringReactive | F22: Level 2 | G22: Premium | H22: =CONCATENATE(G22,C22,F22) -> PremiumODCLevel 2 | I22: A | J22: 1000458649 | K22: VDSI-Flex-H&M-Marketing Produc | L22: ADM | P22: =N22*176 -> 0 | Q22: =N22*176 -> 0 | R22: =N22*176 -> 0 | S22: 0 | T22: 0 | U22: 0 | V22: 0 | W22: 0 | X22: 0 | Y22: 0 | Z22: 0 | AA22: 0 | AB22: =SUM(P22:R22) -> 0 | AC22: =SUM(S22:U22) -> 0 | AD22: =SUM(V22:X22) -> 0 | AE22: =SUM(Y22:AA22) -> 0 | AF22: =SUM(AB22:AC22) -> 0 | AG22: =SUM(AD22:AE22) -> 0 | AH22: =SUM(AF22:AG22) -> 0 | AJ22: 2252709
A23: 905064 | B23: Kumar,Alok | C23: ODC | D23: ACT260 | E23: Java Springboot Microservices SpringReactive | F23: Level 2 | G23: Premium | H23: =CONCATENATE(G23,C23,F23) -> PremiumODCLevel 2 | I23: A | J23: 1000458649 | K23: VDSI-Flex-H&M-Marketing Produc | L23: IDE | P23: =N23*176 -> 0 | Q23: =N23*176 -> 0 | R23: =N23*176 -> 0 | S23: 0 | T23: 0 | U23: 0 | V23: 0 | W23: 0 | X23: 0 | Y23: 0 | Z23: 0 | AA23: 0 | AB23: =SUM(P23:R23) -> 0 | AC23: =SUM(S23:U23) -> 0 | AD23: =SUM(V23:X23) -> 0 | AE23: =SUM(Y23:AA23) -> 0 | AF23: =SUM(AB23:AC23) -> 0 | AG23: =SUM(AD23:AE23) -> 0 | AH23: =SUM(AF23:AG23) -> 0 | AJ23: 905064
A24: 931121 | B24: M,Muthu Lakshmi | C24: ODC | D24: ACT211 | E24: Java Springboot Microservices SpringReactive | F24: Level 3 | G24: Premium | H24: =CONCATENATE(G24,C24,F24) -> PremiumODCLevel 3 | I24: M | J24: 1000458649 | K24: VDSI-Flex-H&M-Marketing Produc | L24: ADM | P24: =N24*176 -> 0 | Q24: =N24*176 -> 0 | R24: =N24*176 -> 0 | S24: 0 | T24: 0 | U24: 0 | V24: 0 | W24: 0 | X24: 0 | Y24: 0 | Z24: 0 | AA24: 0 | AB24: =SUM(P24:R24) -> 0 | AC24: =SUM(S24:U24) -> 0 | AD24: =SUM(V24:X24) -> 0 | AE24: =SUM(Y24:AA24) -> 0 | AF24: =SUM(AB24:AC24) -> 0 | AG24: =SUM(AD24:AE24) -> 0 | AH24: =SUM(AF24:AG24) -> 0 | AJ24: 931121
A25: 2344705 | B25: Bondada,Lavanya | C25: ODC | D25: PCT303 | E25: Java Springboot Microservices SpringReactive | F25: Level 3 | G25: Premium | H25: =CONCATENATE(G25,C25,F25) -> PremiumODCLevel 3 | I25: M | J25: 1000458649 | K25: VDSI-Flex-H&M-Marketing Produc | L25: ADM | P25: =N25*176 -> 0 | Q25: =N25*176 -> 0 | R25: =N25*176 -> 0 | S25: 0 | T25: 0 | U25: 0 | V25: 0 | W25: 0 | X25: 0 | Y25: 0 | Z25: 0 | AA25: 0 | AB25: =SUM(P25:R25) -> 0 | AC25: =SUM(S25:U25) -> 0 | AD25: =SUM(V25:X25) -> 0 | AE25: =SUM(Y25:AA25) -> 0 | AF25: =SUM(AB25:AC25) -> 0 | AG25: =SUM(AD25:AE25) -> 0 | AH25: =SUM(AF25:AG25) -> 0 | AJ25: 2344705
A26: 2399905 | B26: S,Fazila | C26: ODC | D26: PCT246 - CPI 2.0 | E26: Java Springboot Microservices SpringReactive | F26: Level 2 | G26: Premium | H26: =CONCATENATE(G26,C26,F26) -> PremiumODCLevel 2 | I26: A | J26: 1000458649 | K26: VDSI-Flex-H&M-Marketing Produc | L26: ADM | P26: =N26*176 -> 0 | Q26: =N26*176 -> 0 | R26: =N26*176 -> 0 | S26: 0 | T26: 0 | U26: 0 | V26: 0 | W26: 0 | X26: 0 | Y26: 0 | Z26: 0 | AA26: 0 | AB26: =SUM(P26:R26) -> 0 | AC26: =SUM(S26:U26) -> 0 | AD26: =SUM(V26:X26) -> 0 | AE26: =SUM(Y26:AA26) -> 0 | AF26: =SUM(AB26:AC26) -> 0 | AG26: =SUM(AD26:AE26) -> 0 | AH26: =SUM(AF26:AG26) -> 0 | AJ26: 2399905
A27: 615219 | B27: Kothapalli,Ravi Kumar | C27: ODC | D27: PCT303 | E27: ReactJS | F27: Level 3 | G27: Premium | H27: =CONCATENATE(G27,C27,F27) -> PremiumODCLevel 3 | I27: SA | J27: 1000458649 | K27: VDSI-Flex-H&M-Marketing Produc | L27: ADM | P27: =N27*176 -> 0 | Q27: =N27*176 -> 0 | R27: =N27*176 -> 0 | S27: 0 | T27: 0 | U27: 0 | V27: 0 | W27: 0 | X27: 0 | Y27: 0 | Z27: 0 | AA27: 0 | AB27: =SUM(P27:R27) -> 0 | AC27: =SUM(S27:U27) -> 0 | AD27: =SUM(V27:X27) -> 0 | AE27: =SUM(Y27:AA27) -> 0 | AF27: =SUM(AB27:AC27) -> 0 | AG27: =SUM(AD27:AE27) -> 0 | AH27: =SUM(AF27:AG27) -> 0 | AJ27: 615219
A28: 792760 | B28: Soundararajan,Malathi | C28: ODC | D28: PCT303 | E28: Java Springboot Microservices SpringReactive | F28: Level 3 | G28: Premium | H28: =CONCATENATE(G28,C28,F28) -> PremiumODCLevel 3 | I28: SA | J28: 1000458649 | K28: VDSI-Flex-H&M-Marketing Produc | L28: ADM | P28: =N28*176 -> 0 | Q28: =N28*176 -> 0 | R28: =N28*176 -> 0 | S28: 0 | T28: 0 | U28: 0 | V28: 0 | W28: 0 | X28: 0 | Y28: 0 | Z28: 0 | AA28: 0 | AB28: =SUM(P28:R28) -> 0 | AC28: =SUM(S28:U28) -> 0 | AD28: =SUM(V28:X28) -> 0 | AE28: =SUM(Y28:AA28) -> 0 | AF28: =SUM(AB28:AC28) -> 0 | AG28: =SUM(AD28:AE28) -> 0 | AH28: =SUM(AF28:AG28) -> 0 | AJ28: 792760
A29: 2201330 | B29: MKC Arunachalam | C29: ODC | D29: PCT248 | E29: Mainframe | F29: Level 1 | G29: Standard | H29: =CONCATENATE(G29,C29,F29) -> StandardODCLevel 1 | I29: PA | J29: 1000458649 | K29: VDSI-Flex-H&M-Marketing Produc | L29: ADM | P29: =N29*176 -> 0 | Q29: =N29*176 -> 0 | R29: =N29*176 -> 0 | S29: 0 | T29: 0 | U29: 0 | V29: 0 | W29: 0 | X29: 0 | Y29: 0 | Z29: 0 | AA29: 0 | AB29: =SUM(P29:R29) -> 0 | AC29: =SUM(S29:U29) -> 0 | AD29: =SUM(V29:X29) -> 0 | AE29: =SUM(Y29:AA29) -> 0 | AF29: =SUM(AB29:AC29) -> 0 | AG29: =SUM(AD29:AE29) -> 0 | AH29: =SUM(AF29:AG29) -> 0 | AJ29: 2201330
... A45: 2129264 | B45: Durga Devi E | C45: ODC | D45: ACT234 | E45: Java Springboot Microservices SpringReactive | F45: Level 2 | G45: Premium | H45: =CONCATENATE(G45,C45,F45) -> PremiumODCLevel 2 | I45: A | J45: 1000458649 | K45: VDSI-Flex-H&M-Marketing Produc | L45: ADM | P45: =N45*176 -> 0 | Q45: =N45*176 -> 0 | R45: =N45*176 -> 0 | S45: 0 | T45: 0 | U45: 0 | V45: 0 | W45: 0 | X45: 0 | Y45: 0 | Z45: 0 | AA45: 0 | AB45: =SUM(P45:R45) -> 0 | AC45: =SUM(S45:U45) -> 0 | AD45: =SUM(V45:X45) -> 0 | AE45: =SUM(Y45:AA45) -> 0 | AF45: =SUM(AB45:AC45) -> 0 | AG45: =SUM(AD45:AE45) -> 0 | AH45: =SUM(AF45:AG45) -> 0 | AJ45: 2129264
A46: 695292 | B46: MADURAI VEERAN, VIJAYA ANAND | C46: ODC | D46: PCT248 | E46: Java Springboot Microservices SpringReactive | F46: Level 3 | G46: Premium | H46: =CONCATENATE(G46,C46,F46) -> PremiumODCLevel 3 | I46: M | J46: 1000458649 | K46: VDSI-Flex-H&M-Marketing Produc | L46: ADM | P46: =N46*176 -> 0 | Q46: =N46*176 -> 0 | R46: =N46*176 -> 0 | S46: 0 | T46: 0 | U46: 0 | V46: 0 | W46: 0 | X46: 0 | Y46: 0 | Z46: 0 | AA46: 0 | AB46: =SUM(P46:R46) -> 0 | AC46: =SUM(S46:U46) -> 0 | AD46: =SUM(V46:X46) -> 0 | AE46: =SUM(Y46:AA46) -> 0 | AF46: =SUM(AB46:AC46) -> 0 | AG46: =SUM(AD46:AE46) -> 0 | AH46: =SUM(AF46:AG46) -> 0
A47: 2400732 | B47: Debabrato Sikder | C47: ODC | D47: CP - Buffer - ACT211 | E47: Java Springboot Microservices SpringReactive | F47: Level 1 | G47: Premium | H47: =CONCATENATE(G47,C47,F47) -> PremiumODCLevel 1 | I47: PAT | J47: 1000458649 | K47: VDSI-Flex-H&M-Marketing Produc | L47: ADM | P47: 0 | Q47: 0 | R47: 0 | S47: 0 | T47: 0 | U47: 0 | V47: 0 | W47: 0 | X47: 0 | Y47: 0 | Z47: 0 | AA47: 0 | AB47: =SUM(P47:R47) -> 0 | AC47: =SUM(S47:U47) -> 0 | AD47: =SUM(V47:X47) -> 0 | AE47: =SUM(Y47:AA47) -> 0 | AF47: =SUM(AB47:AC47) -> 0 | AG47: =SUM(AD47:AE47) -> 0 | AH47: =SUM(AF47:AG47) -> 0 | AJ47: #N/A
A48: 2401204 | B48: Arghya Kundu | C48: ODC | D48: MP - Buffer - PCT303 | E48: Java Springboot Microservices SpringReactive | F48: Level 1 | G48: Premium | H48: =CONCATENATE(G48,C48,F48) -> PremiumODCLevel 1 | I48: PAT | J48: 1000458649 | K48: VDSI-Flex-H&M-Marketing Produc | L48: ADM | P48: 0 | Q48: 0 | R48: 0 | S48: 0 | T48: 0 | U48: 0 | V48: 0 | W48: 0 | X48: 0 | Y48: 0 | Z48: 0 | AA48: 0 | AB48: =SUM(P48:R48) -> 0 | AC48: =SUM(S48:U48) -> 0 | AD48: =SUM(V48:X48) -> 0 | AE48: =SUM(Y48:AA48) -> 0 | AF48: =SUM(AB48:AC48) -> 0 | AG48: =SUM(AD48:AE48) -> 0 | AH48: =SUM(AF48:AG48) -> 0 | AJ48: #N/A
A49: 2400177 | B49: Manojkumar Velusamy | C49: ODC | D49: CP - Buffer - ACT211 | E49: Java Springboot Microservices SpringReactive | F49: Level 1 | G49: Premium | H49: =CONCATENATE(G49,C49,F49) -> PremiumODCLevel 1 | I49: PAT | J49: 1000458649 | K49: VDSI-Flex-H&M-Marketing Produc | L49: ADM | P49: 0 | Q49: 0 | R49: 0 | S49: 0 | T49: 0 | U49: 0 | V49: 0 | W49: 0 | X49: 0 | Y49: 0 | Z49: 0 | AA49: 0 | AB49: =SUM(P49:R49) -> 0 | AC49: =SUM(S49:U49) -> 0 | AD49: =SUM(V49:X49) -> 0 | AE49: =SUM(Y49:AA49) -> 0 | AF49: =SUM(AB49:AC49) -> 0 | AG49: =SUM(AD49:AE49) -> 0 | AH49: =SUM(AF49:AG49) -> 0 | AJ49: #N/A
A50: 2400215 | B50: Monica Balakrishnan | C50: ODC | D50: CP - Buffer - ACT234 | E50: Java Springboot Microservices SpringReactive | F50: Level 1 | G50: Premium | H50: =CONCATENATE(G50,C50,F50) -> PremiumODCLevel 1 | I50: PAT | J50: 1000458649 | K50: VDSI-Flex-H&M-Marketing Produc | L50: ADM | P50: 0 | Q50: 0 | R50: 0 | S50: 0 | T50: 0 | U50: 0 | V50: 0 | W50: 0 | X50: 0 | Y50: 0 | Z50: 0 | AA50: 0 | AB50: =SUM(P50:R50) -> 0 | AC50: =SUM(S50:U50) -> 0 | AD50: =SUM(V50:X50) -> 0 | AE50: =SUM(Y50:AA50) -> 0 | AF50: =SUM(AB50:AC50) -> 0 | AG50: =SUM(AD50:AE50) -> 0 | AH50: =SUM(AF50:AG50) -> 0 | AJ50: #N/A
A51: 2400166 | B51: SK Akhtar | C51: ODC | D51: MP - Buffer - PCT248 | E51: Java Springboot Microservices SpringReactive | F51: Level 1 | G51: Premium | H51: =CONCATENATE(G51,C51,F51) -> PremiumODCLevel 1 | I51: PAT | J51: 1000458649 | K51: VDSI-Flex-H&M-Marketing Produc | L51: ADM | P51: 0 | Q51: 0 | R51: 0 | S51: 0 | T51: 0 | U51: 0 | V51: 0 | W51: 0 | X51: 0 | Y51: 0 | Z51: 0 | AA51: 0 | AB51: =SUM(P51:R51) -> 0 | AC51: =SUM(S51:U51) -> 0 | AD51: =SUM(V51:X51) -> 0 | AE51: =SUM(Y51:AA51) -> 0 | AF51: =SUM(AB51:AC51) -> 0 | AG51: =SUM(AD51:AE51) -> 0 | AH51: =SUM(AF51:AG51) -> 0 | AJ51: #N/A
A52: 2400123 | B52: Subhrankita Pradhan | C52: ODC | D52: CP - Buffer - ACT234 | E52: Java Springboot Microservices SpringReactive | F52: Level 1 | G52: Premium | H52: =CONCATENATE(G52,C52,F52) -> PremiumODCLevel 1 | I52: PAT | J52: 1000458649 | K52: VDSI-Flex-H&M-Marketing Produc | L52: ADM | P52: 0 | Q52: 0 | R52: 0 | S52: 0 | T52: 0 | U52: 0 | V52: 0 | W52: 0 | X52: 0 | Y52: 0 | Z52: 0 | AA52: 0 | AB52: =SUM(P52:R52) -> 0 | AC52: =SUM(S52:U52) -> 0 | AD52: =SUM(V52:X52) -> 0 | AE52: =SUM(Y52:AA52) -> 0 | AF52: =SUM(AB52:AC52) -> 0 | AG52: =SUM(AD52:AE52) -> 0 | AH52: =SUM(AF52:AG52) -> 0 | AJ52: #N/A
A53: 2400273 | B53: Jasmine Hepziba | C53: ODC | D53: CP - Buffer - ACT234 | E53: Java Springboot Microservices SpringReactive | F53: Level 1 | G53: Premium | H53: =CONCATENATE(G53,C53,F53) -> PremiumODCLevel 1 | I53: PAT | J53: 1000458649 | K53: VDSI-Flex-H&M-Marketing Produc | L53: ADM | P53: 0 | Q53: 0 | R53: 0 | S53: 0 | T53: 0 | U53: 0 | V53: 0 | W53: 0 | X53: 0 | Y53: 0 | Z53: 0 | AA53: 0 | AB53: =SUM(P53:R53) -> 0 | AC53: =SUM(S53:U53) -> 0 | AD53: =SUM(V53:X53) -> 0 | AE53: =SUM(Y53:AA53) -> 0 | AF53: =SUM(AB53:AC53) -> 0 | AG53: =SUM(AD53:AE53) -> 0 | AH53: =SUM(AF53:AG53) -> 0 | AJ53: #N/A
A54: 2400200 | B54: Sakshi Suwarna | C54: ODC | D54: MP - Buffer - PCT248 | E54: Java Springboot Microservices SpringReactive | F54: Level 1 | G54: Premium | H54: =CONCATENATE(G54,C54,F54) -> PremiumODCLevel 1 | I54: PAT | J54: 1000458649 | K54: VDSI-Flex-H&M-Marketing Produc | L54: ADM | P54: 0 | Q54: 0 | R54: 0 | S54: 0 | T54: 0 | U54: 0 | V54: 0 | W54: 0 | X54: 0 | Y54: 0 | Z54: 0 | AA54: 0 | AB54: =SUM(P54:R54) -> 0 | AC54: =SUM(S54:U54) -> 0 | AD54: =SUM(V54:X54) -> 0 | AE54: =SUM(Y54:AA54) -> 0 | AF54: =SUM(AB54:AC54) -> 0 | AG54: =SUM(AD54:AE54) -> 0 | AH54: =SUM(AF54:AG54) -> 0 | AJ54: #N/A
A55: 2416879 | B55: Aditi, Koppole | C55: ODC | D55: CP - Buffer - QA | E55: QA Analyst | F55: Level 1 | G55: Premium | H55: =CONCATENATE(G55,C55,F55) -> PremiumODCLevel 1 | I55: PAT | J55: 1000459873 | K55: Verizon-Value NSA /BAU Testing | L55: QEA | P55: 0 | Q55: 0 | R55: 0 | S55: 0 | T55: 0 | U55: 0 | V55: 0 | W55: 0 | X55: 0 | Y55: 0 | Z55: 0 | AA55: 0 | AB55: =SUM(P55:R55) -> 0 | AC55: =SUM(S55:U55) -> 0 | AD55: =SUM(V55:X55) -> 0 | AE55: =SUM(Y55:AA55) -> 0 | AF55: =SUM(AB55:AC55) -> 0 | AG55: =SUM(AD55:AE55) -> 0 | AH55: =SUM(AF55:AG55) -> 0 | AJ55: #N/A
A56: 2416880 | B56: Piduguralla, Rashmi | C56: ODC | D56: CP - Buffer - QA | E56: QA Analyst | F56: Level 1 | G56: Premium | H56: =CONCATENATE(G56,C56,F56) -> PremiumODCLevel 1 | I56: PAT | J56: 1000456961 | K56: Verizon-VCG Flex Cetralized Te | L56: QEA | P56: 0 | Q56: 0 | R56: 0 | S56: 0 | T56: 0 | U56: 0 | V56: 0 | W56: 0 | X56: 0 | Y56: 0 | Z56: 0 | AA56: 0 | AB56: =SUM(P56:R56) -> 0 | AC56: =SUM(S56:U56) -> 0 | AD56: =SUM(V56:X56) -> 0 | AE56: =SUM(Y56:AA56) -> 0 | AF56: =SUM(AB56:AC56) -> 0 | AG56: =SUM(AD56:AE56) -> 0 | AH56: =SUM(AF56:AG56) -> 0 | AJ56: #N/A
A57: Total | P57: =SUM(P9:P56) -> 0 | Q57: =SUM(Q9:Q56) -> 0 | R57: =SUM(R9:R56) -> 0 | S57: =SUM(S9:S56) -> 0 | T57: =SUM(T9:T56) -> 0 | U57: =SUM(U9:U56) -> 0 | V57: =SUM(V9:V56) -> 0 | W57: =SUM(W9:W56) -> 0 | ... AH57: =SUM(AH9:AH56) -> 0 | AJ57: #N/A
A58: LOE Value | P58: =P57*90% -> 0 | Q58: =Q57*90% -> 0 | R58: =R57*90% -> 0 | S58: =S57*90% -> 0 | T58: =T57*90% -> 0 | U58: =U57*90% -> 0 | V58: =V57*90% -> 0 | W58: =W57*90% -> 0 | ... AH58: =AH57*90% -> 0 | AJ58: #N/A
A59: UPT Value | P59: =P58*94.15% -> 0 | Q59: =Q58*94.15% -> 0 | R59: =R58*94.15% -> 0 | S59: =S57*84.15% -> 0 | T59: =T57*84.15% -> 0 | U59: =U57*84.15% -> 0 | V59: =V57*84.15% -> 0 | W59: =W57*84.15% -> 0 | X59: =X57*84.15% -> 0 | Y59: =Y57*84.15% -> 0 | Z59: =Z57*84.15% -> 0 | AA59: =AA57*84.15% -> 0 | AB59: =AB58*94.15% -> 0 | AC59: =AC57*84.15% -> 0 | AD59: =AD57*84.15% -> 0 | AE59: =AE57*84.15% -> 0 | AF59: =AF58*94.15% -> 0 | AG59: =AG57*84.15% -> 0 | AH59: =AH58*94.15% -> 0 | AJ59: #N/A
P61: 105158.33 | Q61: =P58-P61 -> -105158.33

Sheet 2026 - Price List India BFD
A1: CTS Hourly Rate | H1: CTS Hourly Rate
A2: Levels & Skills Matrix | B2: Concatenate | C2: Classification | D2: Location | E2: Level | F2: India- ODC / OnPrem | H2: Levels & Skills Matrix | I2: India- ODC | J2: Classification | K2: Location | L2: Level | M2: Concatenate
A3: Level 1 - Standard Skills | B3: =CONCATENATE(C3,D3,E3) -> StandardODCLevel 1 | C3: Standard | D3: ODC | E3: Level 1 | F3: 1450 | H3: Level 1 - Standard Skills | I3: 1400 | J3: Standard | K3: ODC | L3: Level 1 | M3: =CONCATENATE(J3,K3,L3) -> StandardODCLevel 1
A4: Level 2 - Standard Skills | B4: =CONCATENATE(C4,D4,E4) -> StandardODCLevel 2 | C4: Standard | D4: ODC | E4: Level 2 | F4: 1716 | H4: Level 2 - Standard Skills | I4: 1656 | J4: Standard | K4: ODC | L4: Level 2 | M4: =CONCATENATE(J4,K4,L4) -> StandardODCLevel 2
A5: Level 3 - Standard Skills | B5: =CONCATENATE(C5,D5,E5) -> StandardODCLevel 3 | C5: Standard | D5: ODC | E5: Level 3 | F5: 1965 | H5: Level 3 - Standard Skills | I5: 1897 | J5: Standard | K5: ODC | L5: Level 3 | M5: =CONCATENATE(J5,K5,L5) -> StandardODCLevel 3
A6: Level 1 - Premium Skills | B6: =CONCATENATE(C6,D6,E6) -> PremiumODCLevel 1 | C6: Premium | D6: ODC | E6: Level 1 | F6: 1502 | H6: Level 1 - Premium Skills | I6: 1449 | J6: Premium | K6: ODC | L6: Level 1 | M6: =CONCATENATE(J6,K6,L6) -> PremiumODCLevel 1
A7: Level 2 - Premium Skills | B7: =CONCATENATE(C7,D7,E7) -> PremiumODCLevel 2 | C7: Premium | D7: ODC | E7: Level 2 | F7: 1828 | H7: Level 2 - Premium Skills | I7: 1764 | J7: Premium | K7: ODC | L7: Level 2 | M7: =CONCATENATE(J7,K7,L7) -> PremiumODCLevel 2
A8: Level 3 - Premium Skills | B8: =CONCATENATE(C8,D8,E8) -> PremiumODCLevel 3 | C8: Premium | D8: ODC | E8: Level 3 | F8: 2128 | H8: Level 3 - Premium Skills | I8: 2054 | J8: Premium | K8: ODC | L8: Level 3 | M8: =CONCATENATE(J8,K8,L8) -> PremiumODCLevel 3
A9: Level 1 - Niche Skills | B9: =CONCATENATE(C9,D9,E9) -> NicheODCLevel 1 | C9: Niche | D9: ODC | E9: Level 1 | F9: 1630 | H9: Level 1 - Niche Skills | I9: 1574 | J9: Niche | K9: ODC | L9: Level 1 | M9: =CONCATENATE(J9,K9,L9) -> NicheODCLevel 1
A10: Level 2 - Niche Skills | B10: =CONCATENATE(C10,D10,E10) -> NicheODCLevel 2 | C10: Niche | D10: ODC | E10: Level 2 | F10: 1956 | H10: Level 2 - Niche Skills | I10: 1888 | J10: Niche | K10: ODC | L10: Level 2 | M10: =CONCATENATE(J10,K10,L10) -> NicheODCLevel 2
A11: Level 3 - Niche Skills | B11: =CONCATENATE(C11,D11,E11) -> NicheODCLevel 3 | C11: Niche | D11: ODC | E11: Level 3 | F11: 2360 | H11: Level 3 - Niche Skills | I11: 2278 | J11: Niche | K11: ODC | L11: Level 3 | M11: =CONCATENATE(J11,K11,L11) -> NicheODCLevel 3
A12: Level 4 - Expert Skills | B12: =CONCATENATE(C12,D12,E12) -> ExpertODCLevel 4 | C12: Expert | D12: ODC | E12: Level 4 | F12: 2960 | H12: Level 4 - Expert Skills | I12: 2857 | J12: Expert | K12: ODC | L12: Level 4 | M12: =CONCATENATE(J12,K12,L12) -> ExpertODCLevel 4
A13: Level 1 - Standard Skills | B13: =CONCATENATE(C13,D13,E13) -> StandardOnPremLevel 1 | C13: Standard | D13: OnPrem | E13: Level 1 | F13: 1305 | H13: Level 1 - Standard Skills | I13: 1260 | J13: Standard | K13: OnPrem | L13: Level 1 | M13: =CONCATENATE(J13,K13,L13) -> StandardOnPremLevel 1
A14: Level 2 - Standard Skills | B14: =CONCATENATE(C14,D14,E14) -> StandardOnPremLevel 2 | C14: Standard | D14: OnPrem | E14: Level 2 | F14: 1545 | H14: Level 2 - Standard Skills | I14: 1491 | J14: Standard | K14: OnPrem | L14: Level 2 | M14: =CONCATENATE(J14,K14,L14) -> StandardOnPremLevel 2
... A22: Level 4 - Expert Skills | B22: =CONCATENATE(C22,D22,E22) -> ExpertOnPremLevel 4 | C22: Expert | D22: OnPrem | E22: Level 4 | F22: 2664 | H22: Level 4 - Expert Skills | I22: 2572 | J22: Expert | K22: OnPrem | L22: Level 4 | M22: =CONCATENATE(J22,K22,L22) -> ExpertOnPremLevel 4
F25: =F22/82 -> 32.487805

Sheet 1000458633- Sai Kishore
A1: Verizon Senior Director (USA) | C1: Umar Mujeeb
A2: Verizon Senior Director (India) | C2: Mangala Seetharaman
A3: Verizon PATL (Onshore) Verizon PATL (Offshore) | C3: Rajkumar Williams and YS / Rajan Kumar
A4: Verizon TQ ID | C4: VZGTTQ00011931 | F4: 4033116000
A5: Verzion TQ Description | C5: VCG VZI_Base Marketing_CTS_Sai
A6: Cognizant POC | C6: Kali Prasad
P7: 2026 - Q1 - Quarter | S7: 2026 - Q2 - Quarter | V7: 2026 - Q3 - Quarter | Y7: 2026 - Q4 - Quarter
A8: EmpID | B8: Name | C8: Location | D8: ACT/PCT | E8: Skill Set | F8: Verizon Level Mapping | G8: Classification | H8: Key | I8: Cognizant Designation | J8: ESA ID | K8: ESA Description | L8: Service Line | M8: ESA Description | N8: Hourly Rate ($) | O8: Monthly Rate ($) | P8: 46023 | Q8: 46054 | R8: 46082 | S8: 46113 | T8: 46143 | U8: 46174 | V8: 46204 | W8: 46235 | X8: 46266 | Y8: 46296 | Z8: 46327 | AA8: 46357 | AB8: Q1 Burn | AC8: Q2 Burn | AD8: Q3 Burn | AE8: Q4 Burn | AF8: H1 Burn | AG8: H2 Burn | AH8: 2026 Burn | AI8: Comments
A9: 608999 | B9: A,Sakthivel | C9: ODC | D9: ACT011 | E9: ReactJS | F9: Level 3 | G9: Premium | H9: =CONCATENATE(G9,C9,F9) -> PremiumODCLevel 3 | I9: M | J9: 1000458633 | K9: VDSI-Flex-H&M-Base Marketing | L9: ADM | M9: =VLOOKUP(H9,'2026 - Price List India BFD'!B:F,5,0) -> 2128 | N9: =M9/87.5 -> 24.32 | O9: =N9*176 -> 4280.32 | P9: =N9*176 -> 4280.32 | Q9: =N9*176 -> 4280.32 | R9: =N9*176 -> 4280.32 | S9: 0 | T9: 0 | U9: 0 | V9: 0 | W9: 0 | X9: 0 | Y9: 0 | Z9: 0 | AA9: 0 | AB9: =SUM(P9:R9) -> 12840.96 | AC9: =SUM(S9:U9) -> 0 | AD9: =SUM(V9:X9) -> 0 | AE9: =SUM(Y9:AA9) -> 0 | AF9: =SUM(AB9:AC9) -> 12840.96 | AG9: =SUM(AD9:AE9) -> 0 | AH9: =SUM(AF9:AG9) -> 12840.96
A10: 2255455 | B10: E,Bharat | C10: ODC | D10: ACT011 | E10: ReactJS | F10: Level 2 | G10: Premium | H10: =CONCATENATE(G10,C10,F10) -> PremiumODCLevel 2 | I10: A | J10: 1000458633 | K10: VDSI-Flex-H&M-Base Marketing | L10: ADM | M10: =VLOOKUP(H10,'2026 - Price List India BFD'!B:F,5,0) -> 1828 | N10: =M10/87.5 -> 20.891429 | O10: =N10*176 -> 3676.8914 | P10: =N10*176 -> 3676.8914 | Q10: =N10*176 -> 3676.8914 | R10: =N10*176 -> 3676.8914 | S10: 0 | T10: 0 | U10: 0 | V10: 0 | W10: 0 | X10: 0 | Y10: 0 | Z10: 0 | AA10: 0 | AB10: =SUM(P10:R10) -> 11030.674 | AC10: =SUM(S10:U10) -> 0 | AD10: =SUM(V10:X10) -> 0 | AE10: =SUM(Y10:AA10) -> 0 | AF10: =SUM(AB10:AC10) -> 11030.674 | AG10: =SUM(AD10:AE10) -> 0 | AH10: =SUM(AF10:AG10) -> 11030.674
A11: 2274572 | B11: Murugesan,Keerthana | C11: ODC | D11: ACT011 | E11: Java Springboot Microservices SpringReactive | F11: Level 2 | G11: Premium | H11: =CONCATENATE(G11,C11,F11) -> PremiumODCLevel 2 | I11: A | J11: 1000458633 | K11: VDSI-Flex-H&M-Base Marketing | L11: ADM | M11: =VLOOKUP(H11,'2026 - Price List India BFD'!B:F,5,0) -> 1828 | N11: =M11/87.5 -> 20.891429 | O11: =N11*176 -> 3676.8914 | P11: =N11*176 -> 3676.8914 | Q11: =N11*176 -> 3676.8914 | R11: =N11*176 -> 3676.8914 | S11: 0 | T11: 0 | U11: 0 | V11: 0 | W11: 0 | X11: 0 | Y11: 0 | Z11: 0 | AA11: 0 | AB11: =SUM(P11:R11) -> 11030.674 | AC11: =SUM(S11:U11) -> 0 | AD11: =SUM(V11:X11) -> 0 | AE11: =SUM(Y11:AA11) -> 0 | AF11: =SUM(AB11:AC11) -> 11030.674 | AG11: =SUM(AD11:AE11) -> 0 | AH11: =SUM(AF11:AG11) -> 11030.674
A12: 2375391 | B12: B R,Niju | C12: ODC | D12: ACT011 | E12: Java Springboot Microservices SpringReactive | F12: Level 2 | G12: Premium | H12: =CONCATENATE(F12,G12,C12) -> Level 2PremiumODC | I12: A | J12: 1000471622 | K12: Verizon-Verizon Flex - H&M -VZ | L12: ADM | M12: =VLOOKUP(H12,'New Rate Card India - BFD'!C:L,10,0) -> 1764 | N12: =M12/82 -> 21.512195 | O12: =N12*176 -> 3786.1463 | S12: 0 | T12: 0 | U12: 0 | V12: 0 | W12: 0 | X12: 0 | Y12: 0 | Z12: 0 | AA12: 0 | AB12: =SUM(P12:R12) -> 0 | AC12: =SUM(S12:U12) -> 0 | AD12: =SUM(V12:X12) -> 0 | AE12: =SUM(Y12:AA12) -> 0 | AF12: =SUM(AB12:AC12) -> 0 | AG12: =SUM(AD12:AE12) -> 0 | AH12: =SUM(AF12:AG12) -> 0
A13: 2211606 | B13: Swarnakar, Preeti | C13: ODC | D13: ACT011 | E13: PEGA | F13: Level 3 | G13: Niche | H13: =CONCATENATE(F13,G13,C13) -> Level 3NicheODC | I13: A | J13: 1000458633 | K13: VDSI-Flex-H&M-Base Marketing | L13: EPS | M13: =VLOOKUP(H13,'New Rate Card India - BFD'!C:L,10,0) -> 2278 | N13: =M13/82 -> 27.780488 | O13: =N13*176 -> 4889.3659 | S13: 0 | T13: 0 | U13: 0 | V13: 0 | W13: 0 | X13: 0 | Y13: 0 | Z13: 0 | AA13: 0 | AB13: =SUM(P13:R13) -> 0 | AC13: =SUM(S13:U13) -> 0 | AD13: =SUM(V13:X13) -> 0 | AE13: =SUM(Y13:AA13) -> 0 | AF13: =SUM(AB13:AC13) -> 0 | AG13: =SUM(AD13:AE13) -> 0 | AH13: =SUM(AF13:AG13) -> 0
A14: 894812 | B14: Batchu,Venkata Sai Kumar | C14: ODC | D14: ACT011 | E14: ReactJS | F14: Level 2 | G14: Premium | H14: =CONCATENATE(F14,G14,C14) -> Level 2PremiumODC | I14: A | J14: 1000471622 | K14: Verizon-Verizon Flex - H&M -VZ | L14: ADM | M14: =VLOOKUP(H14,'New Rate Card India - BFD'!C:L,10,0) -> 1764 | N14: =M14/82 -> 21.512195 | O14: =N14*176 -> 3786.1463 | S14: 0 | T14: 0 | U14: 0 | V14: 0 | W14: 0 | X14: 0 | Y14: 0 | Z14: 0 | AA14: 0 | AB14: =SUM(P14:R14) -> 0 | AC14: =SUM(S14:U14) -> 0 | AD14: =SUM(V14:X14) -> 0 | AE14: =SUM(Y14:AA14) -> 0 | AF14: =SUM(AB14:AC14) -> 0 | AG14: =SUM(AD14:AE14) -> 0 | AH14: =SUM(AF14:AG14) -> 0
A15: 2211749 | B15: A P,Shanmugapriya | C15: ODC | D15: ACT011 | E15: Java Springboot Microservices SpringReactive | F15: Level 2 | G15: Premium | H15: =CONCATENATE(G15,C15,F15) -> PremiumODCLevel 2 | I15: #N/A | J15: #N/A | K15: #N/A | L15: #N/A | M15: =VLOOKUP(H15,'2026 - Price List India BFD'!B:F,5,0) -> 1828 | N15: =M15/87.5 -> 20.891429 | O15: =N15*176 -> 3676.8914 | P15: =N15*176 -> 3676.8914 | Q15: =N15*176 -> 3676.8914 | R15: =N15*176 -> 3676.8914 | S15: 0 | T15: 0 | U15: 0 | V15: 0 | W15: 0 | X15: 0 | Y15: 0 | Z15: 0 | AA15: 0 | AB15: =SUM(P15:R15) -> 11030.674 | AC15: =SUM(S15:U15) -> 0 | AD15: =SUM(V15:X15) -> 0 | AE15: =SUM(Y15:AA15) -> 0 | AF15: =SUM(AB15:AC15) -> 11030.674 | AG15: =SUM(AD15:AE15) -> 0 | AH15: =SUM(AF15:AG15) -> 11030.674
A16: 797435 | B16: CH, Gopalakrishna | C16: ODC | D16: ACT11 | E16: PEGA | F16: Level 3 | G16: Niche | H16: =CONCATENATE(G16,C16,F16) -> NicheODCLevel 3 | I16: SA | J16: 1000458633 | K16: VDSI-Flex-H&M-Base Marketing | L16: EPS | M16: =VLOOKUP(H16,'2026 - Price List India BFD'!B:F,5,0) -> 2360 | N16: =M16/87.5 -> 26.971429 | O16: =N16*176 -> 4746.9714 | S16: 0 | T16: 0 | U16: 0 | V16: 0 | W16: 0 | X16: 0 | Y16: 0 | Z16: 0 | AA16: 0 | AB16: =SUM(P16:R16) -> 0 | AC16: =SUM(S16:U16) -> 0 | AD16: =SUM(V16:X16) -> 0 | AE16: =SUM(Y16:AA16) -> 0 | AF16: =SUM(AB16:AC16) -> 0 | AG16: =SUM(AD16:AE16) -> 0 | AH16: =SUM(AF16:AG16) -> 0
A17: 2104821 | B17: Madisetty, Jeevana | C17: ODC | D17: ACT67 | E17: Java Springboot Microservices SpringReactive | F17: Level 3 | G17: Premium | H17: =CONCATENATE(F17,G17,C17) -> Level 3PremiumODC | I17: SA | J17: 1000471622 | K17: Verizon-Verizon Flex - H&M -VZ | L17: ADM | M17: =VLOOKUP(H17,'New Rate Card India - BFD'!C:L,10,0) -> 2054 | N17: =M17/82 -> 25.04878 | O17: =N17*176 -> 4408.5854 | S17: 0 | T17: 0 | U17: 0 | V17: 0 | W17: 0 | X17: 0 | Y17: 0 | Z17: 0 | AA17: 0 | AB17: =SUM(P17:R17) -> 0 | AC17: =SUM(S17:U17) -> 0 | AD17: =SUM(V17:X17) -> 0 | AE17: =SUM(Y17:AA17) -> 0 | AF17: =SUM(AB17:AC17) -> 0 | AG17: =SUM(AD17:AE17) -> 0 | AH17: =SUM(AF17:AG17) -> 0
A18: 2198542 | B18: Rajkumar Venkatesan | C18: ODC | D18: ACT35 | E18: Java Springboot Microservices SpringReactive | F18: Level 3 | G18: Premium | H18: =CONCATENATE(F18,G18,C18) -> Level 3PremiumODC | I18: M | J18: 1000458633 | K18: VDSI-Flex-H&M-Base Marketing | L18: IDE | M18: =VLOOKUP(H18,'New Rate Card India - BFD'!C:L,10,0) -> 2054 | N18: =M18/82 -> 25.04878 | O18: =N18*176 -> 4408.5854 | S18: 0 | T18: 0 | U18: 0 | V18: 0 | W18: 0 | X18: 0 | Y18: 0 | Z18: 0 | AA18: 0 | AB18: =SUM(P18:R18) -> 0 | AC18: =SUM(S18:U18) -> 0 | AD18: =SUM(V18:X18) -> 0 | AE18: =SUM(Y18:AA18) -> 0 | AF18: =SUM(AB18:AC18) -> 0 | AG18: =SUM(AD18:AE18) -> 0 | AH18: =SUM(AF18:AG18) -> 0
A19: 2352633 | B19: Thangavel, Premnath | C19: ODC | D19: ACT 11 | E19: Java Springboot Microservices SpringReactive | F19: Level 3 | G19: Premium | H19: =CONCATENATE(F19,G19,C19) -> Level 3PremiumODC | I19: SA | J19: 1000471622 | K19: Verizon-Verizon Flex - H&M -VZ | L19: ADM | M19: =VLOOKUP(H19,'New Rate Card India - BFD'!C:L,10,0) -> 2054 | N19: =M19/82 -> 25.04878 | O19: =N19*176 -> 4408.5854 | S19: 0 | T19: 0 | U19: 0 | V19: 0 | W19: 0 | X19: 0 | Y19: 0 | Z19: 0 | AA19: 0 | AB19: =SUM(P19:R19) -> 0 | AC19: =SUM(S19:U19) -> 0 | AD19: =SUM(V19:X19) -> 0 | AE19: =SUM(Y19:AA19) -> 0 | AF19: =SUM(AB19:AC19) -> 0 | AG19: =SUM(AD19:AE19) -> 0 | AH19: =SUM(AF19:AG19) -> 0
A20: 854966 | B20: Sareddy,Shivani | C20: ODC | D20: ACT 11 | E20: PEGA | F20: Level 2 | G20: Niche | H20: =CONCATENATE(F20,G20,C20) -> Level 2NicheODC | I20: A | J20: 1000471622 | K20: Verizon-Verizon Flex - H&M -VZ | L20: EPS | M20: =VLOOKUP(H20,'New Rate Card India - BFD'!C:L,10,0) -> 1888 | N20: =M20/82 -> 23.02439 | O20: =N20*176 -> 4052.2927 | S20: 0 | T20: 0 | U20: 0 | V20: 0 | W20: 0 | X20: 0 | Y20: 0 | Z20: 0 | AA20: 0 | AB20: =SUM(P20:R20) -> 0 | AC20: =SUM(S20:U20) -> 0 | AD20: =SUM(V20:X20) -> 0 | AE20: =SUM(Y20:AA20) -> 0 | AF20: =SUM(AB20:AC20) -> 0 | AG20: =SUM(AD20:AE20) -> 0 | AH20: =SUM(AF20:AG20) -> 0
A21: 2331217 | B21: Harsha Babu, Adithya | C21: ODC | D21: ACT 91 | E21: ReactJS | F21: Level 2 | G21: Premium | H21: =CONCATENATE(G21,C21,F21) -> PremiumODCLevel 2 | I21: A | J21: 1000458633 | K21: VDSI-Flex-H&M-Base Marketing | L21: ADM | M21: =VLOOKUP(H21,'2026 - Price List India BFD'!B:F,5,0) -> 1828 | N21: =M21/87.5 -> 20.891429 | O21: =N21*176 -> 3676.8914 | P21: =N21*176 -> 3676.8914 | Q21: =N21*176 -> 3676.8914 | R21: =N21*176 -> 3676.8914 | S21: 0 | T21: 0 | U21: 0 | V21: 0 | W21: 0 | X21: 0 | Y21: 0 | Z21: 0 | AA21: 0 | AB21: =SUM(P21:R21) -> 11030.674 | AC21: =SUM(S21:U21) -> 0 | AD21: =SUM(V21:X21) -> 0 | AE21: =SUM(Y21:AA21) -> 0 | AF21: =SUM(AB21:AC21) -> 11030.674 | AG21: =SUM(AD21:AE21) -> 0 | AH21: =SUM(AF21:AG21) -> 11030.674
A22: 2205326 | B22: Ravi Prasad Gajji | C22: ODC | D22: ACT 11 | E22: PEGA | F22: Level 2 | G22: Niche | H22: =CONCATENATE(F22,G22,C22) -> Level 2NicheODC | I22: A | J22: 1000471622 | K22: Verizon-Verizon Flex - H&M -VZ | L22: EPS | M22: =VLOOKUP(H22,'New Rate Card India - BFD'!C:L,10,0) -> 1888 | N22: =M22/82 -> 23.02439 | O22: =N22*176 -> 4052.2927 | P22: =N22*176 -> 4052.2927 | Q22: =N22*176 -> 4052.2927 | R22: =N22*176 -> 4052.2927 | S22: 0 | T22: 0 | U22: 0 | V22: 0 | W22: 0 | X22: 0 | Y22: 0 | Z22: 0 | AA22: 0 | AB22: =SUM(P22:R22) -> 12156.878 | AC22: =SUM(S22:U22) -> 0 | AD22: =SUM(V22:X22) -> 0 | AE22: =SUM(Y22:AA22) -> 0 | AF22: =SUM(AB22:AC22) -> 12156.878 | AG22: =SUM(AD22:AE22) -> 0 | AH22: =SUM(AF22:AG22) -> 12156.878
A23: 828866 | B23: Lakshmi Devi | C23: ODC | D23: ACT35 | E23: QA Analyst | F23: Level 2 | G23: Standard | H23: =CONCATENATE(F23,G23,C23) -> Level 2StandardODC | I23: A | J23: 1000471622 | K23: Verizon-Verizon Flex - H&M -VZ | L23: QEA | M23: =VLOOKUP(H23,'New Rate Card India - BFD'!C:L,10,0) -> 1656 | N23: =M23/82 -> 20.195122 | O23: =N23*176 -> 3554.3415 | S23: 0 | T23: 0 | U23: 0 | V23: 0 | W23: 0 | X23: 0 | Y23: 0 | Z23: 0 | AA23: 0 | AB23: =SUM(P23:R23) -> 0 | AC23: =SUM(S23:U23) -> 0 | AD23: =SUM(V23:X23) -> 0 | AE23: =SUM(Y23:AA23) -> 0 | AF23: =SUM(AB23:AC23) -> 0 | AG23: =SUM(AD23:AE23) -> 0 | AH23: =SUM(AF23:AG23) -> 0
A24: 821231 | B24: Sandeepchandra, Mandanapu | C24: ODC | D24: PCT006 | E24: Adobe Experience Manager (AEM) | F24: Level 3 | G24: Premium | H24: =CONCATENATE(G24,C24,F24) -> PremiumODCLevel 3 | I24: SA | J24: 1000458633 | K24: VDSI-Flex-H&M-Base Marketing | L24: Moment | M24: =VLOOKUP(H24,'2026 - Price List India BFD'!B:F,5,0) -> 2128 | N24: =M24/87.5 -> 24.32 | O24: =N24*176 -> 4280.32 | P24: =N24*176 -> 4280.32 | Q24: =N24*176 -> 4280.32 | R24: =N24*176 -> 4280.32 | S24: 0 | T24: 0 | U24: 0 | V24: 0 | W24: 0 | X24: 0 | Y24: 0 | Z24: 0 | AA24: 0 | AB24: =SUM(P24:R24) -> 12840.96 | AC24: =SUM(S24:U24) -> 0 | AD24: =SUM(V24:X24) -> 0 | AE24: =SUM(Y24:AA24) -> 0 | AF24: =SUM(AB24:AC24) -> 12840.96 | AG24: =SUM(AD24:AE24) -> 0 | AH24: =SUM(AF24:AG24) -> 12840.96
A25: 738105 | B25: Yallabandi, Nagathatharao | C25: ODC | D25: PCT006 | E25: Adobe Experience Manager (AEM) | F25: Level 3 | G25: Premium | H25: =CONCATENATE(F25,G25,C25) -> Level 3PremiumODC | I25: SA | J25: 1000458633 | K25: VDSI-Flex-H&M-Base Marketing | L25: Moment | M25: =VLOOKUP(H25,'New Rate Card India - BFD'!C:L,10,0) -> 2054 | N25: =M25/82 -> 25.04878 | O25: =N25*176 -> 4408.5854 | S25: 0 | T25: 0 | U25: 0 | V25: 0 | W25: 0 | X25: 0 | Y25: 0 | Z25: 0 | AA25: 0 | AB25: =SUM(P25:R25) -> 0 | AC25: =SUM(S25:U25) -> 0 | AD25: =SUM(V25:X25) -> 0 | AE25: =SUM(Y25:AA25) -> 0 | AF25: =SUM(AB25:AC25) -> 0 | AG25: =SUM(AD25:AE25) -> 0 | AH25: =SUM(AF25:AG25) -> 0
A26: 2344555 | B26: Bathala, Sai Durga Deekshit | C26: ODC | D26: PCT006 | E26: Adobe Experience Manager (AEM) | F26: Level 3 | G26: Premium | H26: =CONCATENATE(F26,G26,C26) -> Level 3PremiumODC | I26: SA | J26: 1000458633 | K26: VDSI-Flex-H&M-Base Marketing | L26: Moment | M26: =VLOOKUP(H26,'New Rate Card India - BFD'!C:L,10,0) -> 2054 | N26: =M26/82 -> 25.04878 | O26: =N26*176 -> 4408.5854 | S26: 0 | T26: 0 | U26: 0 | V26: 0 | W26: 0 | X26: 0 | Y26: 0 | Z26: 0 | AA26: 0 | AB26: =SUM(P26:R26) -> 0 | AC26: =SUM(S26:U26) -> 0 | AD26: =SUM(V26:X26) -> 0 | AE26: =SUM(Y26:AA26) -> 0 | AF26: =SUM(AB26:AC26) -> 0 | AG26: =SUM(AD26:AE26) -> 0 | AH26: =SUM(AF26:AG26) -> 0
A27: 2323886 | B27: Arasavilli, Sindhu | C27: ODC | D27: PCT006 | E27: Adobe Experience Manager (AEM) | F27: Level 2 | G27: Premium | H27: =CONCATENATE(F27,G27,C27) -> Level 2PremiumODC | I27: A | J27: 1000458633 | K27: VDSI-Flex-H&M-Base Marketing | L27: Moment | M27: =VLOOKUP(H27,'New Rate Card India - BFD'!C:L,10,0) -> 1764 | N27: =M27/82 -> 21.512195 | O27: =N27*176 -> 3786.1463 | S27: 0 | T27: 0 | U27: 0 | V27: 0 | W27: 0 | X27: 0 | Y27: 0 | Z27: 0 | AA27: 0 | AB27: =SUM(P27:R27) -> 0 | AC27: =SUM(S27:U27) -> 0 | AD27: =SUM(V27:X27) -> 0 | AE27: =SUM(Y27:AA27) -> 0 | AF27: =SUM(AB27:AC27) -> 0 | AG27: =SUM(AD27:AE27) -> 0 | AH27: =SUM(AF27:AG27) -> 0
A28: 406042 | B28: Mandoori, Sravanthi | C28: ODC | D28: PCT006 | E28: Adobe Experience Manager (AEM) | F28: Level 3 | G28: Premium | H28: =CONCATENATE(G28,C28,F28) -> PremiumODCLevel 3 | I28: SA | J28: 1000458633 | K28: VDSI-Flex-H&M-Base Marketing | L28: Moment | M28: =VLOOKUP(H28,'2026 - Price List India BFD'!B:F,5,0) -> 2128 | N28: =M28/87.5 -> 24.32 | O28: =N28*176 -> 4280.32 | P28: =N28*176 -> 4280.32 | Q28: =N28*176 -> 4280.32 | R28: =N28*176 -> 4280.32 | S28: 0 | T28: 0 | U28: 0 | V28: 0 | W28: 0 | X28: 0 | Y28: 0 | Z28: 0 | AA28: 0 | AB28: =SUM(P28:R28) -> 12840.96 | AC28: =SUM(S28:U28) -> 0 | AD28: =SUM(V28:X28) -> 0 | AE28: =SUM(Y28:AA28) -> 0 | AF28: =SUM(AB28:AC28) -> 12840.96 | AG28: =SUM(AD28:AE28) -> 0 | AH28: =SUM(AF28:AG28) -> 12840.96
A29: 2280922 | B29: Das, Tarulekha | C29: ODC | D29: PCT006 | E29: Adobe Experience Manager (AEM) | F29: Level 2 | G29: Premium | H29: =CONCATENATE(F29,G29,C29) -> Level 2PremiumODC | I29: A | J29: 1000458633 | K29: VDSI-Flex-H&M-Base Marketing | L29: Moment | M29: =VLOOKUP(H29,'New Rate Card India - BFD'!C:L,10,0) -> 1764 | N29: =M29/82 -> 21.512195 | O29: =N29*176 -> 3786.1463 | S29: 0 | T29: 0 | U29: 0 | V29: 0 | W29: 0 | X29: 0 | Y29: 0 | Z29: 0 | AA29: 0 | AB29: =SUM(P29:R29) -> 0 | AC29: =SUM(S29:U29) -> 0 | AD29: =SUM(V29:X29) -> 0 | AE29: =SUM(Y29:AA29) -> 0 | AF29: =SUM(AB29:AC29) -> 0 | AG29: =SUM(AD29:AE29) -> 0 | AH29: =SUM(AF29:AG29) -> 0
A30: 476823 | B30: Sammeta Kiran Kumar | C30: ODC | D30: PCT006 | E30: Adobe Experience Manager (AEM) | F30: Level 3 | G30: Premium | H30: =CONCATENATE(G30,C30,F30) -> PremiumODCLevel 3 | I30: M | J30: 1000458633 | K30: VDSI-Flex-H&M-Base Marketing | L30: Moment | M30: =VLOOKUP(H30,'2026 - Price List India BFD'!B:F,5,0) -> 2128 | N30: =M30/87.5 -> 24.32 | O30: =N30*176 -> 4280.32 | P30: =N30*176 -> 4280.32 | Q30: =N30*176 -> 4280.32 | R30: =N30*176 -> 4280.32 | S30: 0 | T30: 0 | U30: 0 | V30: 0 | W30: 0 | X30: 0 | Y30: 0 | Z30: 0 | AA30: 0 | AB30: =SUM(P30:R30) -> 12840.96 | AC30: =SUM(S30:U30) -> 0 | AD30: =SUM(V30:X30) -> 0 | AE30: =SUM(Y30:AA30) -> 0 | AF30: =SUM(AB30:AC30) -> 12840.96 | AG30: =SUM(AD30:AE30) -> 0 | AH30: =SUM(AF30:AG30) -> 12840.96
A31: 2420430 | B31: Natanasabapathy, Venkateswaran | C31: ODC | D31: Architect | E31: Java Springboot Microservices SpringReactive | F31: Level 4 | G31: Expert | H31: =CONCATENATE(F31,G31,C31) -> Level 4ExpertODC | I31: AD | J31: 1000458633 | K31: VDSI-Flex-H&M-Base Marketing | L31: IDE | M31: =VLOOKUP(H31,'New Rate Card India - BFD'!C:L,10,0) -> 2857 | N31: =M31/82 -> 34.841463 | O31: =N31*176 -> 6132.0976 | S31: 0 | T31: 0 | U31: 0 | V31: 0 | W31: 0 | X31: 0 | Y31: 0 | Z31: 0 | AA31: 0 | AB31: =SUM(P31:R31) -> 0 | AC31: =SUM(S31:U31) -> 0 | AD31: =SUM(V31:X31) -> 0 | AE31: =SUM(Y31:AA31) -> 0 | AF31: =SUM(AB31:AC31) -> 0 | AG31: =SUM(AD31:AE31) -> 0 | AH31: =SUM(AF31:AG31) -> 0
A32: 2421107 | B32: Vintha S | C32: ODC | D32: PCT006 | E32: Adobe Experience Manager (AEM) | F32: Level 2 | G32: Premium | H32: =CONCATENATE(F32,G32,C32) -> Level 2PremiumODC | I32: A | J32: 1000471622 | K32: Verizon-Verizon Flex - H&M -VZ | L32: Moment | M32: =VLOOKUP(H32,'New Rate Card India - BFD'!C:L,10,0) -> 1764 | N32: =M32/82 -> 21.512195 | O32: =N32*176 -> 3786.1463 | P32: =N32*176 -> 3786.1463 | Q32: =N32*176 -> 3786.1463 | R32: =N32*176 -> 3786.1463 | S32: 0 | T32: 0 | U32: 0 | V32: 0 | W32: 0 | X32: 0 | Y32: 0 | Z32: 0 | AA32: 0 | AB32: =SUM(P32:R32) -> 11358.439 | AC32: =SUM(S32:U32) -> 0 | AD32: =SUM(V32:X32) -> 0 | AE32: =SUM(Y32:AA32) -> 0 | AF32: =SUM(AB32:AC32) -> 11358.439 | AG32: =SUM(AD32:AE32) -> 0 | AH32: =SUM(AF32:AG32) -> 11358.439
A33: 839959 | B33: Dogra, Rashi | C33: ODC | D33: ACT 07 | E33: Java Springboot Microservices SpringReactive | F33: Level 2 | G33: Premium | H33: =CONCATENATE(F33,G33,C33) -> Level 2PremiumODC | I33: A | J33: 1000471622 | K33: Verizon-Verizon Flex - H&M -VZ | L33: ADM | M33: =VLOOKUP(H33,'New Rate Card India - BFD'!C:L,10,0) -> 1764 | N33: =M33/82 -> 21.512195 | O33: =N33*176 -> 3786.1463 | S33: 0 | T33: 0 | U33: 0 | V33: 0 | W33: 0 | X33: 0 | Y33: 0 | Z33: 0 | AA33: 0 | AB33: =SUM(P33:R33) -> 0 | AC33: =SUM(S33:U33) -> 0 | AD33: =SUM(V33:X33) -> 0 | AE33: =SUM(Y33:AA33) -> 0 | AF33: =SUM(AB33:AC33) -> 0 | AG33: =SUM(AD33:AE33) -> 0 | AH33: =SUM(AF33:AG33) -> 0
A34: 2041730 | B34: Kachhwaha, Sandeep | C34: ODC | D34: ACT 07 | E34: Java Springboot Microservices SpringReactive | F34: Level 2 | G34: Premium | H34: =CONCATENATE(F34,G34,C34) -> Level 2PremiumODC | I34: A | J34: 1000471622 | K34: Verizon-Verizon Flex - H&M -VZ | L34: IDE | M34: =VLOOKUP(H34,'New Rate Card India - BFD'!C:L,10,0) -> 1764 | N34: =M34/82 -> 21.512195 | O34: =N34*176 -> 3786.1463 | S34: 0 | T34: 0 | U34: 0 | V34: 0 | W34: 0 | X34: 0 | Y34: 0 | Z34: 0 | AA34: 0 | AB34: =SUM(P34:R34) -> 0 | AC34: =SUM(S34:U34) -> 0 | AD34: =SUM(V34:X34) -> 0 | AE34: =SUM(Y34:AA34) -> 0 | AF34: =SUM(AB34:AC34) -> 0 | AG34: =SUM(AD34:AE34) -> 0 | AH34: =SUM(AF34:AG34) -> 0
A35: 2175924 | B35: Kaliyamoorthy, Ilayaraja | C35: ODC | D35: ACT 07 | E35: Java Springboot Microservices SpringReactive | F35: Level 3 | G35: Premium | H35: =CONCATENATE(F35,G35,C35) -> Level 3PremiumODC | I35: M | J35: 1000458633 | K35: VDSI-Flex-H&M-Base Marketing | L35: ADM | M35: =VLOOKUP(H35,'New Rate Card India - BFD'!C:L,10,0) -> 2054 | N35: =M35/82 -> 25.04878 | O35: =N35*176 -> 4408.5854 | S35: 0 | T35: 0 | U35: 0 | V35: 0 | W35: 0 | X35: 0 | Y35: 0 | Z35: 0 | AA35: 0 | AB35: =SUM(P35:R35) -> 0 | AC35: =SUM(S35:U35) -> 0 | AD35: =SUM(V35:X35) -> 0 | AE35: =SUM(Y35:AA35) -> 0 | AF35: =SUM(AB35:AC35) -> 0 | AG35: =SUM(AD35:AE35) -> 0 | AH35: =SUM(AF35:AG35) -> 0
A36: 594408 | B36: Adapala, Venkataramana | C36: ODC | D36: ACT 07 | E36: Java Springboot Microservices SpringReactive | F36: Level 4 | G36: Expert | H36: =CONCATENATE(F36,G36,C36) -> Level 4ExpertODC | I36: SM | J36: 1000458633 | K36: VDSI-Flex-H&M-Base Marketing | L36: ISG | M36: =VLOOKUP(H36,'New Rate Card India - BFD'!C:L,10,0) -> 2857 | N36: =M36/82 -> 34.841463 | O36: =N36*176 -> 6132.0976 | S36: 0 | T36: 0 | U36: 0 | V36: 0 | W36: 0 | X36: 0 | Y36: 0 | Z36: 0 | AA36: 0 | AB36: =SUM(P36:R36) -> 0 | AC36: =SUM(S36:U36) -> 0 | AD36: =SUM(V36:X36) -> 0 | AE36: =SUM(Y36:AA36) -> 0 | AF36: =SUM(AB36:AC36) -> 0 | AG36: =SUM(AD36:AE36) -> 0 | AH36: =SUM(AF36:AG36) -> 0
A37: Total | P37: =SUM(P9:P36) -> 39667.285 | Q37: =SUM(Q9:Q36) -> 39667.285 | R37: =SUM(R9:R36) -> 39667.285 | S37: =SUM(S9:S36) -> 0 | T37: =SUM(T9:T36) -> 0 | U37: =SUM(U9:U36) -> 0 | V37: =SUM(V9:V36) -> 0 | W37: =SUM(W9:W36) -> 0 | ... AH37: =SUM(AH9:AH36) -> 119001.85
A38: LOE Value | P38: =P37*90% -> 35700.556 | Q38: =Q37*90% -> 35700.556 | R38: =R37*90% -> 35700.556 | S38: =S37*90% -> 0 | T38: =T37*90% -> 0 | U38: =U37*90% -> 0 | V38: =V37*90% -> 0 | W38: =W37*90% -> 0 | ... AG38: =AG37*90% -> 0 | AH38: =SUM(AF38:AG38) -> 107101.67
A39: UPT Value | P39: =P38*94.15% -> 33612.074 | Q39: =Q38*94.15% -> 33612.074 | R39: =R38*94.15% -> 33612.074 | S39: =S37*84.15% -> 0 | T39: =T37*84.15% -> 0 | U39: =U37*84.15% -> 0 | V39: =V37*84.15% -> 0 | W39: =W37*84.15% -> 0 | X39: =X37*84.15% -> 0 | Y39: =Y37*84.15% -> 0 | Z39: =Z37*84.15% -> 0 | AA39: =AA37*84.15% -> 0 | AB39: =AB38*94.15% -> 100836.22 | AC39: =AC37*84.15% -> 0 | AD39: =AD37*84.15% -> 0 | AE39: =AE37*84.15% -> 0 | AF39: =AF38*94.15% -> 100836.22 | AG39: =AG37*84.15% -> 0 | AH39: =SUM(AF39:AG39) -> 100836.22
P41: 30644.67
Y42: =Y37*90% -> 0

Sheet 1000467271 - Sai Kishore
A1: Verizon Senior Director (USA) | C1: Umar Mujeeb
A2: Verizon Senior Director (India) | C2: Mangala Seetharaman
A3: Verizon PATL (Onshore) Verizon PATL (Offshore) | C3: Vidya Reddy / Anil S
A4: Verizon TQ ID | C4: VZGTTQ00012348
A5: Verzion TQ Description | C5: VCG VZI_AI & Automation_CTS_Sai
A6: Cognizant POC | C6: Bhimeswarao Bondada
P7: 2026 - Q1 - Quarter | S7: 2026 - Q2 - Quarter | V7: 2026 - Q3 - Quarter | Y7: 2026 - Q4 - Quarter
A8: EmpID | B8: Name | C8: Location | D8: ACT/PCT | E8: Skill Set | F8: Verizon Level Mapping | G8: Classification | H8: Key | I8: Cognizant Designation | J8: ESA ID | K8: ESA Description | L8: Service Line | M8: Hourly Rate (Rs) | N8: Hourly Rate ($) | O8: Monthly Rate ($) | P8: 46023 | Q8: 46054 | R8: 46082 | S8: 46113 | T8: 46143 | U8: 46174 | V8: 46204 | W8: 46235 | X8: 46266 | Y8: 46296 | Z8: 46327 | AA8: 46357 | AB8: Q1 Burn | AC8: Q2 Burn | AD8: Q3 Burn | AE8: Q4 Burn | AF8: H1 Burn | AG8: H2 Burn | AH8: 2026 Burn | AI8: Comments
A9: 2298722 | B9: Jahan Shaik,Afroze | C9: ODC | D9: ACT 132 | E9: PEGA | F9: Level 2 | G9: Niche | H9: =CONCATENATE(G9,C9,F9) -> NicheODCLevel 2 | I9: A | J9: 1000467271 | K9: VDSI-Flex-H&M-Turing_AI | L9: EPS | M9: =VLOOKUP(H9,'2026 - Price List India BFD'!B:F,5,0) -> 1956 | N9: =M9/87.5 -> 22.354286 | O9: =N9*176 -> 3934.3543 | P9: =N9*176 -> 3934.3543 | Q9: =N9*176 -> 3934.3543 | R9: =N9*176 -> 3934.3543 | S9: 0 | T9: 0 | U9: 0 | V9: 0 | W9: 0 | X9: 0 | Y9: 0 | Z9: 0 | AA9: 0 | AB9: =SUM(P9:R9) -> 11803.063 | AC9: =SUM(S9:U9) -> 0 | AD9: =SUM(V9:X9) -> 0 | AE9: =SUM(Y9:AA9) -> 0 | AF9: =SUM(AB9:AC9) -> 11803.063 | AG9: =SUM(AD9:AE9) -> 0 | AH9: =SUM(AF9:AG9) -> 11803.063
A10: 924074 | B10: Sahu,Kailash | C10: ODC | D10: ACT 132 | E10: PEGA | F10: Level 2 | G10: Standard | H10: =CONCATENATE(G10,C10,F10) -> StandardODCLevel 2 | I10: A | J10: 1000467271 | K10: VDSI-Flex-H&M-Turing_AI | L10: EPS | M10: =VLOOKUP(H10,'2026 - Price List India BFD'!B:F,5,0) -> 1716 | N10: =M10/87.5 -> 19.611429 | O10: =N10*176 -> 3451.6114 | P10: =N10*176 -> 3451.6114 | Q10: =N10*176 -> 3451.6114 | R10: =N10*176 -> 3451.6114 | S10: 0 | T10: 0 | U10: 0 | V10: 0 | W10: 0 | X10: 0 | Y10: 0 | Z10: 0 | AA10: 0 | AB10: =SUM(P10:R10) -> 10354.834 | AC10: =SUM(S10:U10) -> 0 | AD10: =SUM(V10:X10) -> 0 | AE10: =SUM(Y10:AA10) -> 0 | AF10: =SUM(AB10:AC10) -> 10354.834 | AG10: =SUM(AD10:AE10) -> 0 | AH10: =SUM(AF10:AG10) -> 10354.834
A11: 2266831 | B11: Verma,Sonu Kumar | C11: ODC | D11: ACT 132 | E11: PEGA | F11: Level 1 | G11: Niche | H11: =CONCATENATE(F11,G11,C11) -> Level 1NicheODC | I11: PA | J11: 1000467271 | K11: VDSI-Flex-H&M-Turing_AI | L11: EPS | M11: =VLOOKUP(H11,'New Rate Card India - BFD'!C:L,10,0) -> 1574 | N11: =M11/82 -> 19.195122 | O11: =N11*176 -> 3378.3415 | S11: 0 | T11: 0 | U11: 0 | V11: 0 | W11: 0 | X11: 0 | Y11: 0 | Z11: 0 | AA11: 0 | AB11: =SUM(P11:R11) -> 0 | AC11: =SUM(S11:U11) -> 0 | AD11: =SUM(V11:X11) -> 0 | AE11: =SUM(Y11:AA11) -> 0 | AF11: =SUM(AB11:AC11) -> 0 | AG11: =SUM(AD11:AE11) -> 0 | AH11: =SUM(AF11:AG11) -> 0
A12: 2220139 | B12: Jana,Barnali | C12: ODC | D12: ACT 132 | E12: PEGA | F12: Level 1 | G12: Niche | H12: =CONCATENATE(F12,G12,C12) -> Level 1NicheODC | I12: PA | J12: 1000467271 | K12: VDSI-Flex-H&M-Turing_AI | L12: EPS | M12: =VLOOKUP(H12,'New Rate Card India - BFD'!C:L,10,0) -> 1574 | N12: =M12/82 -> 19.195122 | O12: =N12*176 -> 3378.3415 | S12: 0 | T12: 0 | U12: 0 | V12: 0 | W12: 0 | X12: 0 | Y12: 0 | Z12: 0 | AA12: 0 | AB12: =SUM(P12:R12) -> 0 | AC12: =SUM(S12:U12) -> 0 | AD12: =SUM(V12:X12) -> 0 | AE12: =SUM(Y12:AA12) -> 0 | AF12: =SUM(AB12:AC12) -> 0 | AG12: =SUM(AD12:AE12) -> 0 | AH12: =SUM(AF12:AG12) -> 0
A13: 2318325 | B13: Nag, Rimpi | C13: ODC | D13: ACT 132 | E13: PEGA | F13: Level 2 | G13: Niche | H13: =CONCATENATE(F13,G13,C13) -> Level 2NicheODC | I13: PA | J13: 1000467271 | K13: VDSI-Flex-H&M-Turing_AI | L13: EPS | M13: =VLOOKUP(H13,'New Rate Card India - BFD'!C:L,10,0) -> 1888 | N13: =M13/82 -> 23.02439 | O13: =N13*176 -> 4052.2927 | S13: 0 | T13: 0 | U13: 0 | V13: 0 | W13: 0 | X13: 0 | Y13: 0 | Z13: 0 | AA13: 0 | AB13: =SUM(P13:R13) -> 0 | AC13: =SUM(S13:U13) -> 0 | AD13: =SUM(V13:X13) -> 0 | AE13: =SUM(Y13:AA13) -> 0 | AF13: =SUM(AB13:AC13) -> 0 | AG13: =SUM(AD13:AE13) -> 0 | AH13: =SUM(AF13:AG13) -> 0
